Workbook
Name UPDATE: 'Data Sheet'!$E$1

Sheet Financials>

Sheet Historical FS
B2: ="Historical Financial Statements "&"- "&'Data Sheet'!$B$1 -> Historical Financial Statements - ITC LTD
B3: Years | C3: ='Data Sheet'!B56 -> 42460 | D3: ='Data Sheet'!C56 -> 42825 | E3: ='Data Sheet'!D56 -> 43190 | F3: ='Data Sheet'!E56 -> 43555 | G3: ='Data Sheet'!F56 -> 43921 | H3: ='Data Sheet'!G56 -> 44286 | I3: ='Data Sheet'!H56 -> 44651 | J3: ='Data Sheet'!I56 -> 45016 | ... L3: ='Data Sheet'!K56 -> 45747 | M3: LTM
A5: # | B5: Income Statement
B7: Sales | C7: =IFERROR('Data Sheet'!B17,0) -> 39192.1 | D7: =IFERROR('Data Sheet'!C17,0) -> 42767.6 | E7: =IFERROR('Data Sheet'!D17,0) -> 43448.94 | F7: =IFERROR('Data Sheet'!E17,0) -> 48339.58 | G7: =IFERROR('Data Sheet'!F17,0) -> 49387.7 | H7: =IFERROR('Data Sheet'!G17,0) -> 49257.45 | I7: =IFERROR('Data Sheet'!H17,0) -> 60644.54 | J7: =IFERROR('Data Sheet'!I17,0) -> 70919.03 | ... L7: =IFERROR('Data Sheet'!K17,0) -> 75323.34 | M7: =IFERROR(SUM('Data Sheet'!H42:K42),0) -> 79808.72
B8: Sales Growth | C8: - | D8: =D7/C7-1 -> 0.09123012 | E8: =E7/D7-1 -> 0.015931219 | F8: =F7/E7-1 -> 0.11256063 | G8: =G7/F7-1 -> 0.021682439 | H8: =H7/G7-1 -> -0.0026372963 | I8: =I7/H7-1 -> 0.23117498 | J8: =J7/I7-1 -> 0.16942152 | K8: =K7/J7-1 -> -0.042119724 | ... M8: =M7/L7-1 -> 0.059548342
B10: COGS | C10: =IFERROR(SUM('Data Sheet'!B18,'Data Sheet'!B20:B21)-1*'Data Sheet'!B19,0) -> 15721.97 | D10: =IFERROR(SUM('Data Sheet'!C18,'Data Sheet'!C20:C21)-1*'Data Sheet'!C19,0) -> 18317.39 | E10: =IFERROR(SUM('Data Sheet'!D18,'Data Sheet'!D20:D21)-1*'Data Sheet'!D19,0) -> 18206.6 | F10: =IFERROR(SUM('Data Sheet'!E18,'Data Sheet'!E20:E21)-1*'Data Sheet'!E19,0) -> 20038.07 | G10: =IFERROR(SUM('Data Sheet'!F18,'Data Sheet'!F20:F21)-1*'Data Sheet'!F19,0) -> 20034.61 | H10: =IFERROR(SUM('Data Sheet'!G18,'Data Sheet'!G20:G21)-1*'Data Sheet'!G19,0) -> 22418.18 | I10: =IFERROR(SUM('Data Sheet'!H18,'Data Sheet'!H20:H21)-1*'Data Sheet'!H19,0) -> 29162.51 | J10: =IFERROR(SUM('Data Sheet'!I18,'Data Sheet'!I20:I21)-1*'Data Sheet'!I19,0) -> 32565.91 | ... L10: =IFERROR(SUM('Data Sheet'!K18,'Data Sheet'!K20:K21)-1*'Data Sheet'!K19,0) -> 35299.43 | M10: =IFERROR(SUM('Data Sheet'!H43:K43),0) -> 52895.65
B11: COGS %Sales | C11: =C10/C7 -> 0.40115151 | D11: =D10/D7 -> 0.42830063 | E11: =E10/E7 -> 0.41903439 | F11: =F10/F7 -> 0.41452718 | G11: =G10/G7 -> 0.40565991 | H11: =H10/H7 -> 0.45512263 | I11: =I10/I7 -> 0.4808761 | J11: =J10/J7 -> 0.45919847 | ... M11: =M10/M7 -> 0.66278033
B13: Gross Profit | C13: =C7-C10 -> 23470.13 | D13: =D7-D10 -> 24450.21 | E13: =E7-E10 -> 25242.34 | F13: =F7-F10 -> 28301.51 | G13: =G7-G10 -> 29353.09 | H13: =H7-H10 -> 26839.27 | I13: =I7-I10 -> 31482.03 | J13: =J7-J10 -> 38353.12 | ... M13: =M7-M10 -> 26913.07
B14: Gross Margins | C14: =C13/C7 -> 0.59884849 | D14: =D13/D7 -> 0.57169937 | E14: =E13/E7 -> 0.58096561 | F14: =F13/F7 -> 0.58547282 | G14: =G13/G7 -> 0.59434009 | H14: =H13/H7 -> 0.54487737 | I14: =I13/I7 -> 0.5191239 | J14: =J13/J7 -> 0.54080153 | ... M14: =M13/M7 -> 0.33721967
B16: Selling and Other Expenses | C16: =IFERROR(SUM('Data Sheet'!B22:B24),0) -> 8938.64 | D16: =IFERROR(SUM('Data Sheet'!C22:C24),0) -> 8980.7 | E16: =IFERROR(SUM('Data Sheet'!D22:D24),0) -> 8721.75 | F16: =IFERROR(SUM('Data Sheet'!E22:E24),0) -> 9764.12 | G16: =IFERROR(SUM('Data Sheet'!F22:F24),0) -> 10009.55 | H16: =IFERROR(SUM('Data Sheet'!G22:G24),0) -> 9774.49 | I16: =IFERROR(SUM('Data Sheet'!H22:H24),0) -> 10858.88 | J16: =IFERROR(SUM('Data Sheet'!I22:I24),0) -> 12648.86 | ... M16: =IFERROR(SUM('Data Sheet'!L22:L24),0) -> 0
B17: S&G Expenses %Sales | C17: =C16/C7 -> 0.22807249 | D17: =D16/D7 -> 0.2099884 | E17: =E16/E7 -> 0.20073562 | F17: =F16/F7 -> 0.20199017 | G17: =G16/G7 -> 0.20267293 | H17: =H16/H7 -> 0.19843678 | I17: =I16/I7 -> 0.17905783 | J17: =J16/J7 -> 0.17835636 | ... M17: =M16/M7 -> 0
B19: EBITDA | C19: =C13-C16 -> 14531.49 | D19: =D13-D16 -> 15469.51 | E19: =E13-E16 -> 16520.59 | F19: =F13-F16 -> 18537.39 | G19: =G13-G16 -> 19343.54 | H19: =H13-H16 -> 17064.78 | I19: =I13-I16 -> 20623.15 | J19: =J13-J16 -> 25704.26 | ... M19: =M13-M16 -> 26913.07
B20: EBITDA Margin | C20: =C19/C7 -> 0.370776 | D20: =D19/D7 -> 0.36171097 | E20: =E19/E7 -> 0.38022999 | F20: =F19/F7 -> 0.38348265 | G20: =G19/G7 -> 0.39166716 | H20: =H19/H7 -> 0.34644059 | I20: =I19/I7 -> 0.34006606 | J20: =J19/J7 -> 0.36244517 | ... M20: =M19/M7 -> 0.33721967
B22: Depreciation | C22: =IFERROR('Data Sheet'!B26,0) -> 1077.4 | D22: =IFERROR('Data Sheet'!C26,0) -> 1152.79 | E22: =IFERROR('Data Sheet'!D26,0) -> 1236.28 | F22: =IFERROR('Data Sheet'!E26,0) -> 1396.61 | G22: =IFERROR('Data Sheet'!F26,0) -> 1644.91 | H22: =IFERROR('Data Sheet'!G26,0) -> 1645.59 | I22: =IFERROR('Data Sheet'!H26,0) -> 1732.41 | J22: =IFERROR('Data Sheet'!I26,0) -> 1809.01 | ... L22: =IFERROR('Data Sheet'!K26,0) -> 1646.32 | M22: =IFERROR(SUM('Data Sheet'!H45:K45),0) -> 1699.61
B23: Depreciation %Sales | C23: =C22/C7 -> 0.027490234 | D23: =D22/D7 -> 0.026954751 | E23: =E22/E7 -> 0.028453629 | F23: =F22/F7 -> 0.028891645 | G23: =G22/G7 -> 0.033306066 | H23: =H22/H7 -> 0.033407941 | I23: =I22/I7 -> 0.028566628 | J23: =J22/J7 -> 0.025508104 | ... M23: =M22/M7 -> 0.021296044
B25: EBIT | C25: =C19-C22 -> 13454.09 | D25: =D19-D22 -> 14316.72 | E25: =E19-E22 -> 15284.31 | F25: =F19-F22 -> 17140.78 | G25: =G19-G22 -> 17698.63 | H25: =H19-H22 -> 15419.19 | I25: =I19-I22 -> 18890.74 | J25: =J19-J22 -> 23895.25 | ... M25: =M19-M22 -> 25213.46
B26: EBIT Margins | C26: =C25/C7 -> 0.34328576 | D26: =D25/D7 -> 0.33475622 | E26: =E25/E7 -> 0.35177636 | F26: =F25/F7 -> 0.354591 | G26: =G25/G7 -> 0.35836109 | H26: =H25/H7 -> 0.31303265 | I26: =I25/I7 -> 0.31149944 | J26: =J25/J7 -> 0.33693707 | ... M26: =M25/M7 -> 0.31592362
B28: Interest | C28: =IFERROR('Data Sheet'!B27,0) -> 78.13 | D28: =IFERROR('Data Sheet'!C27,0) -> 49.03 | E28: =IFERROR('Data Sheet'!D27,0) -> 115.01 | F28: =IFERROR('Data Sheet'!E27,0) -> 71.4 | G28: =IFERROR('Data Sheet'!F27,0) -> 81.38 | H28: =IFERROR('Data Sheet'!G27,0) -> 57.97 | I28: =IFERROR('Data Sheet'!H27,0) -> 59.99 | J28: =IFERROR('Data Sheet'!I27,0) -> 77.77 | ... L28: =IFERROR('Data Sheet'!K27,0) -> 45.06 | M28: =IFERROR(SUM('Data Sheet'!H46:K46),0) -> 66.9
B29: Interest %Sales | C29: =C28/C7 -> 0.001993514 | D29: =D28/D7 -> 0.0011464286 | E29: =E28/E7 -> 0.0026470151 | F29: =F28/F7 -> 0.0014770505 | G29: =G28/G7 -> 0.0016477787 | H29: =H28/H7 -> 0.0011768778 | I29: =I28/I7 -> 0.00098920694 | J29: =J28/J7 -> 0.0010966027 | ... M29: =M28/M7 -> 0.00083825427
B31: Earning Before Tax | C31: =C25-C28 -> 13375.96 | D31: =D25-D28 -> 14267.69 | E31: =E25-E28 -> 15169.3 | F31: =F25-F28 -> 17069.38 | G31: =G25-G28 -> 17617.25 | H31: =H25-H28 -> 15361.22 | I31: =I25-I28 -> 18830.75 | J31: =J25-J28 -> 23817.48 | ... M31: =M25-M28 -> 25146.56
B32: EBT Margins | C32: =C31/C7 -> 0.34129225 | D32: =D31/D7 -> 0.33360979 | E32: =E31/E7 -> 0.34912935 | F32: =F31/F7 -> 0.35311395 | G32: =G31/G7 -> 0.35671331 | H32: =H31/H7 -> 0.31185577 | I32: =I31/I7 -> 0.31051023 | J32: =J31/J7 -> 0.33584046 | ... M32: =M31/M7 -> 0.31508537
B34: Tax | C34: =IFERROR('Data Sheet'!B29,0) -> 5358.21 | D34: =IFERROR('Data Sheet'!C29,0) -> 5549.09 | E34: =IFERROR('Data Sheet'!D29,0) -> 5916.43 | F34: =IFERROR('Data Sheet'!E29,0) -> 6313.92 | G34: =IFERROR('Data Sheet'!F29,0) -> 4441.79 | H34: =IFERROR('Data Sheet'!G29,0) -> 4555.29 | I34: =IFERROR('Data Sheet'!H29,0) -> 5237.34 | J34: =IFERROR('Data Sheet'!I29,0) -> 6438.4 | ... L34: =IFERROR('Data Sheet'!K29,0) -> 6890.47 | M34: =IFERROR(SUM('Data Sheet'!H48:K48),0) -> 6993.21
B35: Effective Tax Rate | C35: =C34/C31 -> 0.40058508 | D35: =D34/D31 -> 0.38892701 | E35: =E34/E31 -> 0.39002657 | F35: =F34/F31 -> 0.36989744 | G35: =G34/G31 -> 0.25212732 | H35: =H34/H31 -> 0.29654481 | I35: =I34/I31 -> 0.278127 | J35: =J34/J31 -> 0.27032247 | ... M35: =M34/M31 -> 0.27809808
B37: Net Profit | C37: =C31-C34 -> 8017.75 | D37: =D31-D34 -> 8718.6 | E37: =E31-E34 -> 9252.87 | F37: =F31-F34 -> 10755.46 | G37: =G31-G34 -> 13175.46 | H37: =H31-H34 -> 10805.93 | I37: =I31-I34 -> 13593.41 | J37: =J31-J34 -> 17379.08 | ... M37: =M31-M34 -> 18153.35
B38: Net Margins | C38: =C37/C7 -> 0.20457567 | D38: =D37/D7 -> 0.20385993 | E38: =E37/E7 -> 0.21295963 | F38: =F37/F7 -> 0.222498 | G38: =G37/G7 -> 0.26677614 | H38: =H37/H7 -> 0.21937656 | I38: =I37/I7 -> 0.22414895 | J38: =J37/J7 -> 0.24505524 | ... M38: =M37/M7 -> 0.22746073
B40: No of Equity Share | C40: =IFERROR('Data Sheet'!$B$6,0) -> 1252.9468 | D40: =IFERROR('Data Sheet'!$B$6,0) -> 1252.9468 | E40: =IFERROR('Data Sheet'!$B$6,0) -> 1252.9468 | F40: =IFERROR('Data Sheet'!$B$6,0) -> 1252.9468 | G40: =IFERROR('Data Sheet'!$B$6,0) -> 1252.9468 | H40: =IFERROR('Data Sheet'!$B$6,0) -> 1252.9468 | I40: =IFERROR('Data Sheet'!$B$6,0) -> 1252.9468 | J40: =IFERROR('Data Sheet'!$B$6,0) -> 1252.9468 | ... M40: =IFERROR('Data Sheet'!$B$6,0) -> 1252.9468
B42: Earnings Per Share | C42: =C37/C40 -> 6.3991147 | D42: =D37/D40 -> 6.958476 | E42: =E37/E40 -> 7.3848868 | F42: =F37/F40 -> 8.5841317 | G42: =G37/G40 -> 10.515579 | H42: =H37/H40 -> 8.6244128 | I42: =I37/I40 -> 10.849152 | J42: =J37/J40 -> 13.870565 | ... M42: =M37/M40 -> 14.488525
B43: EPS Growth | D43: =D42/C42-1 -> 0.087412304 | E43: =E42/D42-1 -> 0.061279334 | F43: =F42/E42-1 -> 0.16239178 | G43: =G42/F42-1 -> 0.225002 | H43: =H42/G42-1 -> -0.1798442 | I43: =I42/H42-1 -> 0.25795836 | J43: =J42/I42-1 -> 0.27849303 | K43: =K42/J42-1 -> 0.0024069168 | ... M43: =M42/L42-1 -> 0.051904668
B45: Dividend Per Share | C45: =IFERROR('Data Sheet'!B31/'Historical FS'!C40,0) -> 5.4592264 | D45: =IFERROR('Data Sheet'!C31/'Historical FS'!D40,0) -> 4.6051598 | E45: =IFERROR('Data Sheet'!D31/'Historical FS'!E40,0) -> 5.0163424 | F45: =IFERROR('Data Sheet'!E31/'Historical FS'!F40,0) -> 5.6256979 | G45: =IFERROR('Data Sheet'!F31/'Historical FS'!G40,0) -> 9.9577894 | H45: =IFERROR('Data Sheet'!G31/'Historical FS'!H40,0) -> 10.560672 | I45: =IFERROR('Data Sheet'!H31/'Historical FS'!I40,0) -> 11.310776 | J45: =IFERROR('Data Sheet'!I31/'Historical FS'!J40,0) -> 15.374476 | ... M45: =IFERROR('Data Sheet'!L31/'Historical FS'!M40,0) -> 0
B46: Dividend Payout Ratio | C46: =C45/C42 -> 0.85312214 | D46: =D45/D42 -> 0.66180579 | E46: =E45/E42 -> 0.6792714 | F46: =F45/F42 -> 0.65536016 | G46: =G45/G42 -> 0.94695593 | H46: =H45/H42 -> 1.2245091 | I46: =I45/I42 -> 1.0425493 | J46: =J45/J42 -> 1.1084246 | ... M46: =M45/M42 -> 0
B48: Retained Earnings | C48: =IFERROR(IF(C42>C45,1-C46,0),0) -> 0.14687786 | D48: =IFERROR(IF(D42>D45,1-D46,0),0) -> 0.33819421 | E48: =IFERROR(IF(E42>E45,1-E46,0),0) -> 0.3207286 | F48: =IFERROR(IF(F42>F45,1-F46,0),0) -> 0.34463984 | G48: =IFERROR(IF(G42>G45,1-G46,0),0) -> 0.053044068 | H48: =IFERROR(IF(H42>H45,1-H46,0),0) -> 0 | I48: =IFERROR(IF(I42>I45,1-I46,0),0) -> 0 | J48: =IFERROR(IF(J42>J45,1-J46,0),0) -> 0 | ... M48: =IFERROR(IF(M42>M45,1-M46,0),0) -> 1
A50: # | B50: Balance Sheet
B52: Equity Share Capital | C52: =IFERROR('Data Sheet'!B57,0) -> 804.72 | D52: =IFERROR('Data Sheet'!C57,0) -> 1214.74 | E52: =IFERROR('Data Sheet'!D57,0) -> 1220.43 | F52: =IFERROR('Data Sheet'!E57,0) -> 1225.86 | G52: =IFERROR('Data Sheet'!F57,0) -> 1229.22 | H52: =IFERROR('Data Sheet'!G57,0) -> 1230.88 | I52: =IFERROR('Data Sheet'!H57,0) -> 1232.33 | J52: =IFERROR('Data Sheet'!I57,0) -> 1242.8 | ... L52: =IFERROR('Data Sheet'!K57,0) -> 1251.41 | M52: 0
B53: Reserves | C53: =IFERROR('Data Sheet'!B58,0) -> 41874.8 | D53: =IFERROR('Data Sheet'!C58,0) -> 45198.19 | E53: =IFERROR('Data Sheet'!D58,0) -> 51289.68 | F53: =IFERROR('Data Sheet'!E58,0) -> 57915.01 | G53: =IFERROR('Data Sheet'!F58,0) -> 64044.04 | H53: =IFERROR('Data Sheet'!G58,0) -> 59116.46 | I53: =IFERROR('Data Sheet'!H58,0) -> 61223.24 | J53: =IFERROR('Data Sheet'!I58,0) -> 67912.46 | ... M53: =IFERROR('Data Sheet'!L58,0) -> 0
B54: Borrowings | C54: =IFERROR('Data Sheet'!B59,0) -> 83.78 | D54: =IFERROR('Data Sheet'!C59,0) -> 45.72 | E54: =IFERROR('Data Sheet'!D59,0) -> 35.92 | F54: =IFERROR('Data Sheet'!E59,0) -> 13.44 | G54: =IFERROR('Data Sheet'!F59,0) -> 277.45 | H54: =IFERROR('Data Sheet'!G59,0) -> 270.83 | I54: =IFERROR('Data Sheet'!H59,0) -> 249.44 | J54: =IFERROR('Data Sheet'!I59,0) -> 306.04 | ... M54: =IFERROR('Data Sheet'!L59,0) -> 0
B55: Other Liabilities | C55: =IFERROR('Data Sheet'!B60,0) -> 8888.04 | D55: =IFERROR('Data Sheet'!C60,0) -> 9439.67 | E55: =IFERROR('Data Sheet'!D60,0) -> 11694.85 | F55: =IFERROR('Data Sheet'!E60,0) -> 12584.73 | G55: =IFERROR('Data Sheet'!F60,0) -> 11760.04 | H55: =IFERROR('Data Sheet'!G60,0) -> 13142.59 | I55: =IFERROR('Data Sheet'!H60,0) -> 14491.01 | J55: =IFERROR('Data Sheet'!I60,0) -> 16369.66 | ... M55: =IFERROR('Data Sheet'!L60,0) -> 0
B56: Total Liabilities | C56: =SUM(C52:C55) -> 51651.34 | D56: =SUM(D52:D55) -> 55898.32 | E56: =SUM(E52:E55) -> 64240.88 | F56: =SUM(F52:F55) -> 71739.04 | G56: =SUM(G52:G55) -> 77310.75 | H56: =SUM(H52:H55) -> 73760.76 | I56: =SUM(I52:I55) -> 77196.02 | J56: =SUM(J52:J55) -> 85830.96 | ... M56: =SUM(M52:M55) -> 0
B58: Fixed Asset Net Block | C58: =IFERROR('Data Sheet'!B62,0) -> 15106.63 | D58: =IFERROR('Data Sheet'!C62,0) -> 15893.48 | E58: =IFERROR('Data Sheet'!D62,0) -> 16523.96 | F58: =IFERROR('Data Sheet'!E62,0) -> 19374.19 | G58: =IFERROR('Data Sheet'!F62,0) -> 21713.34 | H58: =IFERROR('Data Sheet'!G62,0) -> 23298.48 | I58: =IFERROR('Data Sheet'!H62,0) -> 24231.59 | J58: =IFERROR('Data Sheet'!I62,0) -> 25851.27 | ... M58: =IFERROR('Data Sheet'!L62,0) -> 0
B59: Capital Work in Progress | C59: =IFERROR('Data Sheet'!B63,0) -> 2559.72 | D59: =IFERROR('Data Sheet'!C63,0) -> 3729.89 | E59: =IFERROR('Data Sheet'!D63,0) -> 5508.33 | F59: =IFERROR('Data Sheet'!E63,0) -> 4136.42 | G59: =IFERROR('Data Sheet'!F63,0) -> 3256.46 | H59: =IFERROR('Data Sheet'!G63,0) -> 4011.29 | I59: =IFERROR('Data Sheet'!H63,0) -> 3225.54 | J59: =IFERROR('Data Sheet'!I63,0) -> 3003.3 | ... M59: =IFERROR('Data Sheet'!L63,0) -> 0
B60: Investments | C60: =IFERROR('Data Sheet'!B64,0) -> 11747.59 | D60: =IFERROR('Data Sheet'!C64,0) -> 17581.38 | E60: =IFERROR('Data Sheet'!D64,0) -> 22052.86 | F60: =IFERROR('Data Sheet'!E64,0) -> 25043.49 | G60: =IFERROR('Data Sheet'!F64,0) -> 28663.35 | H60: =IFERROR('Data Sheet'!G64,0) -> 24870.87 | I60: =IFERROR('Data Sheet'!H64,0) -> 24841.01 | J60: =IFERROR('Data Sheet'!I64,0) -> 29415.02 | ... M60: =IFERROR('Data Sheet'!L64,0) -> 0
B61: Other Assets | C61: =IFERROR('Data Sheet'!B65-SUM('Data Sheet'!B67:B69),0) -> 5194.82 | D61: =IFERROR('Data Sheet'!C65-SUM('Data Sheet'!C67:C69),0) -> 5135.78 | E61: =IFERROR('Data Sheet'!D65-SUM('Data Sheet'!D67:D69),0) -> 7078.75 | F61: =IFERROR('Data Sheet'!E65-SUM('Data Sheet'!E67:E69),0) -> 7138.07 | G61: =IFERROR('Data Sheet'!F65-SUM('Data Sheet'!F67:F69),0) -> 4958.45 | H61: =IFERROR('Data Sheet'!G65-SUM('Data Sheet'!G67:G69),0) -> 4022.24 | I61: =IFERROR('Data Sheet'!H65-SUM('Data Sheet'!H67:H69),0) -> 6917.41 | J61: =IFERROR('Data Sheet'!I65-SUM('Data Sheet'!I67:I69),0) -> 7953.85 | ... M61: =IFERROR('Data Sheet'!L65-SUM('Data Sheet'!L67:L69),0) -> 0
B62: Total Non Current Assets | C62: =SUM(C58:C61) -> 34608.76 | D62: =SUM(D58:D61) -> 42340.53 | E62: =SUM(E58:E61) -> 51163.9 | F62: =SUM(F58:F61) -> 55692.17 | G62: =SUM(G58:G61) -> 58591.6 | H62: =SUM(H58:H61) -> 56202.88 | I62: =SUM(I58:I61) -> 59215.55 | J62: =SUM(J58:J61) -> 66223.44 | ... M62: =SUM(M58:M61) -> 0
B64: Receivables | C64: =IFERROR('Data Sheet'!B67,0) -> 1917.18 | D64: =IFERROR('Data Sheet'!C67,0) -> 2474.29 | E64: =IFERROR('Data Sheet'!D67,0) -> 2682.29 | F64: =IFERROR('Data Sheet'!E67,0) -> 4035.28 | G64: =IFERROR('Data Sheet'!F67,0) -> 2562.48 | H64: =IFERROR('Data Sheet'!G67,0) -> 2501.7 | I64: =IFERROR('Data Sheet'!H67,0) -> 2461.9 | J64: =IFERROR('Data Sheet'!I67,0) -> 2956.17 | ... M64: =IFERROR('Data Sheet'!L67,0) -> 0
B65: Inventory | C65: =IFERROR('Data Sheet'!B68,0) -> 9062.1 | D65: =IFERROR('Data Sheet'!C68,0) -> 8116.1 | E65: =IFERROR('Data Sheet'!D68,0) -> 7495.09 | F65: =IFERROR('Data Sheet'!E68,0) -> 7859.56 | G65: =IFERROR('Data Sheet'!F68,0) -> 8879.33 | H65: =IFERROR('Data Sheet'!G68,0) -> 10397.16 | I65: =IFERROR('Data Sheet'!H68,0) -> 10864.15 | J65: =IFERROR('Data Sheet'!I68,0) -> 11771.16 | ... M65: =IFERROR('Data Sheet'!L68,0) -> 0
B66: Cash & Bank | C66: =IFERROR('Data Sheet'!B69,0) -> 6063.3 | D66: =IFERROR('Data Sheet'!C69,0) -> 2967.4 | E66: =IFERROR('Data Sheet'!D69,0) -> 2899.6 | F66: =IFERROR('Data Sheet'!E69,0) -> 4152.03 | G66: =IFERROR('Data Sheet'!F69,0) -> 7277.34 | H66: =IFERROR('Data Sheet'!G69,0) -> 4659.02 | I66: =IFERROR('Data Sheet'!H69,0) -> 4654.42 | J66: =IFERROR('Data Sheet'!I69,0) -> 4880.19 | ... M66: =IFERROR('Data Sheet'!L69,0) -> 0
B67: Total Current Assets | C67: =SUM(C64:C66) -> 17042.58 | D67: =SUM(D64:D66) -> 13557.79 | E67: =SUM(E64:E66) -> 13076.98 | F67: =SUM(F64:F66) -> 16046.87 | G67: =SUM(G64:G66) -> 18719.15 | H67: =SUM(H64:H66) -> 17557.88 | I67: =SUM(I64:I66) -> 17980.47 | J67: =SUM(J64:J66) -> 19607.52 | ... M67: =SUM(M64:M66) -> 0
B69: Total Assets | C69: =SUM(C67,C62) -> 51651.34 | D69: =SUM(D67,D62) -> 55898.32 | E69: =SUM(E67,E62) -> 64240.88 | F69: =SUM(F67,F62) -> 71739.04 | G69: =SUM(G67,G62) -> 77310.75 | H69: =SUM(H67,H62) -> 73760.76 | I69: =SUM(I67,I62) -> 77196.02 | J69: =SUM(J67,J62) -> 85830.96 | ... M69: =SUM(M67,M62) -> 0
B71: Check | C71: =C69=C56 -> TRUE | D71: =D69=D56 -> TRUE | E71: =E69=E56 -> TRUE | F71: =F69=F56 -> TRUE | G71: =G69=G56 -> TRUE | H71: =H69=H56 -> TRUE | I71: =I69=I56 -> TRUE | J71: =J69=J56 -> TRUE | ... L71: =L69=L56 -> TRUE | M71: -
A73: # | B73: Cash Flow Statement
B75: Cash from Operating Activity | C75: =IFERROR('Data Sheet'!B82,0) -> 9799.04 | D75: =IFERROR('Data Sheet'!C82,0) -> 10627.31 | E75: =IFERROR('Data Sheet'!D82,0) -> 13169.4 | F75: =IFERROR('Data Sheet'!E82,0) -> 12583.41 | G75: =IFERROR('Data Sheet'!F82,0) -> 14689.66 | H75: =IFERROR('Data Sheet'!G82,0) -> 12526.97 | I75: =IFERROR('Data Sheet'!H82,0) -> 15775.51 | J75: =IFERROR('Data Sheet'!I82,0) -> 18877.55 | ... M75: =IFERROR('Data Sheet'!L82,0) -> 0
B77: Cash From Investing Activity | C77: =IFERROR('Data Sheet'!B83,0) -> -3920.73 | D77: =IFERROR('Data Sheet'!C83,0) -> -3250.93 | E77: =IFERROR('Data Sheet'!D83,0) -> -7113.89 | F77: =IFERROR('Data Sheet'!E83,0) -> -5545.68 | G77: =IFERROR('Data Sheet'!F83,0) -> -6174.02 | H77: =IFERROR('Data Sheet'!G83,0) -> 5739.98 | I77: =IFERROR('Data Sheet'!H83,0) -> -2238.49 | J77: =IFERROR('Data Sheet'!I83,0) -> -5732.29 | ... M77: =IFERROR('Data Sheet'!L83,0) -> 0
B79: Cash from Financing Activity | C79: =IFERROR('Data Sheet'!B84,0) -> -5612.52 | D79: =IFERROR('Data Sheet'!C84,0) -> -7301.03 | E79: =IFERROR('Data Sheet'!D84,0) -> -6221.13 | F79: =IFERROR('Data Sheet'!E84,0) -> -6868.64 | G79: =IFERROR('Data Sheet'!F84,0) -> -8181.48 | H79: =IFERROR('Data Sheet'!G84,0) -> -18633.83 | I79: =IFERROR('Data Sheet'!H84,0) -> -13580.5 | J79: =IFERROR('Data Sheet'!I84,0) -> -13006.03 | ... M79: =IFERROR('Data Sheet'!L84,0) -> 0
B81: Net Cash Flow | C81: =SUM(C79,C77,C75) -> 265.79 | D81: =SUM(D79,D77,D75) -> 75.35 | E81: =SUM(E79,E77,E75) -> -165.62 | F81: =SUM(F79,F77,F75) -> 169.09 | G81: =SUM(G79,G77,G75) -> 334.16 | H81: =SUM(H79,H77,H75) -> -366.88 | I81: =SUM(I79,I77,I75) -> -43.48 | J81: =SUM(J79,J77,J75) -> 139.23 | ... M81: =SUM(M79,M77,M75) -> 0

Sheet Ratio Analysis
B2: ="Ratio Analysis "&"- "&'Data Sheet'!$B$1 -> Ratio Analysis - ITC LTD
B3: Years | C3: ='Data Sheet'!B16 -> 42460 | D3: ='Data Sheet'!C16 -> 42825 | E3: ='Data Sheet'!D16 -> 43190 | F3: ='Data Sheet'!E16 -> 43555 | G3: ='Data Sheet'!F16 -> 43921 | H3: ='Data Sheet'!G16 -> 44286 | I3: ='Data Sheet'!H16 -> 44651 | J3: ='Data Sheet'!I16 -> 45016 | ... L3: ='Data Sheet'!K16 -> 45747 | M3: Trend | N3: Mean | O3: Median
B4: Sales Growth | C4: ='Historical FS'!C8 -> - | D4: =IFERROR('Historical FS'!D8,0) -> 0.09123012 | E4: =IFERROR('Historical FS'!E8,0) -> 0.015931219 | F4: =IFERROR('Historical FS'!F8,0) -> 0.11256063 | G4: =IFERROR('Historical FS'!G8,0) -> 0.021682439 | H4: =IFERROR('Historical FS'!H8,0) -> -0.0026372963 | I4: =IFERROR('Historical FS'!I8,0) -> 0.23117498 | J4: =IFERROR('Historical FS'!J8,0) -> 0.16942152 | K4: =IFERROR('Historical FS'!K8,0) -> -0.042119724 | L4: =IFERROR('Historical FS'!L8,0) -> 0.10880596 | N4: =AVERAGE(D4:L4) -> 0.078449983 | O4: =MEDIAN(D4:L4) -> 0.09123012
B5: EBITDA Growth | C5: - | D5: =IFERROR('Historical FS'!D19/'Historical FS'!C19-1,0) -> 0.064550848 | E5: =IFERROR('Historical FS'!E19/'Historical FS'!D19-1,0) -> 0.067945268 | F5: =IFERROR('Historical FS'!F19/'Historical FS'!E19-1,0) -> 0.12207796 | G5: =IFERROR('Historical FS'!G19/'Historical FS'!F19-1,0) -> 0.043487783 | H5: =IFERROR('Historical FS'!H19/'Historical FS'!G19-1,0) -> -0.1178047 | I5: =IFERROR('Historical FS'!I19/'Historical FS'!H19-1,0) -> 0.20852129 | J5: =IFERROR('Historical FS'!J19/'Historical FS'!I19-1,0) -> 0.24637895 | K5: =IFERROR('Historical FS'!K19/'Historical FS'!J19-1,0) -> -0.020102893 | L5: =IFERROR('Historical FS'!L19/'Historical FS'!K19-1,0) -> 0.025882649 | N5: =AVERAGE(D5:L5) -> 0.07121524 | O5: =MEDIAN(D5:L5) -> 0.064550848
B6: EBIT Growth | C6: - | D6: =IFERROR('Historical FS'!D25/'Historical FS'!C25-1,0) -> 0.064116562 | E6: =IFERROR('Historical FS'!E25/'Historical FS'!D25-1,0) -> 0.067584614 | F6: =IFERROR('Historical FS'!F25/'Historical FS'!E25-1,0) -> 0.12146247 | G6: =IFERROR('Historical FS'!G25/'Historical FS'!F25-1,0) -> 0.032545193 | H6: =IFERROR('Historical FS'!H25/'Historical FS'!G25-1,0) -> -0.12879189 | I6: =IFERROR('Historical FS'!I25/'Historical FS'!H25-1,0) -> 0.22514477 | J6: =IFERROR('Historical FS'!J25/'Historical FS'!I25-1,0) -> 0.26491869 | K6: =IFERROR('Historical FS'!K25/'Historical FS'!J25-1,0) -> -0.0094483213 | L6: =IFERROR('Historical FS'!L25/'Historical FS'!K25-1,0) -> 0.022123426 | N6: =AVERAGE(D6:L6) -> 0.073295057 | O6: =MEDIAN(D6:L6) -> 0.064116562
B7: Net Profit Growth | C7: - | D7: =IFERROR('Historical FS'!D37/'Historical FS'!C37-1,0) -> 0.087412304 | E7: =IFERROR('Historical FS'!E37/'Historical FS'!D37-1,0) -> 0.061279334 | F7: =IFERROR('Historical FS'!F37/'Historical FS'!E37-1,0) -> 0.16239178 | G7: =IFERROR('Historical FS'!G37/'Historical FS'!F37-1,0) -> 0.225002 | H7: =IFERROR('Historical FS'!H37/'Historical FS'!G37-1,0) -> -0.1798442 | I7: =IFERROR('Historical FS'!I37/'Historical FS'!H37-1,0) -> 0.25795836 | J7: =IFERROR('Historical FS'!J37/'Historical FS'!I37-1,0) -> 0.27849303 | K7: =IFERROR('Historical FS'!K37/'Historical FS'!J37-1,0) -> 0.0024069168 | L7: =IFERROR('Historical FS'!L37/'Historical FS'!K37-1,0) -> -0.0093743668 | N7: =AVERAGE(D7:L7) -> 0.098413907 | O7: =MEDIAN(D7:L7) -> 0.087412304
B8: Dividend Growth | C8: - | D8: =IFERROR('Historical FS'!D45/'Historical FS'!C45-1,0) -> -0.15644462 | E8: =IFERROR('Historical FS'!E45/'Historical FS'!D45-1,0) -> 0.089287385 | F8: =IFERROR('Historical FS'!F45/'Historical FS'!E45-1,0) -> 0.12147406 | G8: =IFERROR('Historical FS'!G45/'Historical FS'!F45-1,0) -> 0.77005405 | H8: =IFERROR('Historical FS'!H45/'Historical FS'!G45-1,0) -> 0.060543835 | I8: =IFERROR('Historical FS'!I45/'Historical FS'!H45-1,0) -> 0.071028026 | J8: =IFERROR('Historical FS'!J45/'Historical FS'!I45-1,0) -> 0.35927687 | K8: =IFERROR('Historical FS'!K45/'Historical FS'!J45-1,0) -> -0.10885617 | L8: =IFERROR('Historical FS'!L45/'Historical FS'!K45-1,0) -> 0.046093953 | N8: =AVERAGE(D8:L8) -> 0.13916193 | O8: =MEDIAN(D8:L8) -> 0.071028026
B10: Gross Margin | C10: =IFERROR('Historical FS'!C14,0) -> 0.59884849 | D10: =IFERROR('Historical FS'!D14,0) -> 0.57169937 | E10: =IFERROR('Historical FS'!E14,0) -> 0.58096561 | F10: =IFERROR('Historical FS'!F14,0) -> 0.58547282 | G10: =IFERROR('Historical FS'!G14,0) -> 0.59434009 | H10: =IFERROR('Historical FS'!H14,0) -> 0.54487737 | I10: =IFERROR('Historical FS'!I14,0) -> 0.5191239 | J10: =IFERROR('Historical FS'!J14,0) -> 0.54080153 | ... L10: =IFERROR('Historical FS'!L14,0) -> 0.53136133 | N10: =AVERAGE(C10:L10) -> 0.56241429 | O10: =MEDIAN(C10:L10) -> 0.5641759
B11: EBITDA Margin | C11: =IFERROR('Historical FS'!C20,0) -> 0.370776 | D11: =IFERROR('Historical FS'!D20,0) -> 0.36171097 | E11: =IFERROR('Historical FS'!E20,0) -> 0.38022999 | F11: =IFERROR('Historical FS'!F20,0) -> 0.38348265 | G11: =IFERROR('Historical FS'!G20,0) -> 0.39166716 | H11: =IFERROR('Historical FS'!H20,0) -> 0.34644059 | I11: =IFERROR('Historical FS'!I20,0) -> 0.34006606 | J11: =IFERROR('Historical FS'!J20,0) -> 0.36244517 | ... L11: =IFERROR('Historical FS'!L20,0) -> 0.34304706 | N11: =AVERAGE(C11:L11) -> 0.36506416 | O11: =MEDIAN(C11:L11) -> 0.36661056
B12: EBIT Margin | C12: =IFERROR('Historical FS'!C26,0) -> 0.34328576 | D12: =IFERROR('Historical FS'!D26,0) -> 0.33475622 | E12: =IFERROR('Historical FS'!E26,0) -> 0.35177636 | F12: =IFERROR('Historical FS'!F26,0) -> 0.354591 | G12: =IFERROR('Historical FS'!G26,0) -> 0.35836109 | H12: =IFERROR('Historical FS'!H26,0) -> 0.31303265 | I12: =IFERROR('Historical FS'!I26,0) -> 0.31149944 | J12: =IFERROR('Historical FS'!J26,0) -> 0.33693707 | ... L12: =IFERROR('Historical FS'!L26,0) -> 0.32119035 | N12: =AVERAGE(C12:L12) -> 0.33738593 | O12: =MEDIAN(C12:L12) -> 0.34011142
B13: EBT Margin | C13: =IFERROR('Historical FS'!C32,0) -> 0.34129225 | D13: =IFERROR('Historical FS'!D32,0) -> 0.33360979 | E13: =IFERROR('Historical FS'!E32,0) -> 0.34912935 | F13: =IFERROR('Historical FS'!F32,0) -> 0.35311395 | G13: =IFERROR('Historical FS'!G32,0) -> 0.35671331 | H13: =IFERROR('Historical FS'!H32,0) -> 0.31185577 | I13: =IFERROR('Historical FS'!I32,0) -> 0.31051023 | J13: =IFERROR('Historical FS'!J32,0) -> 0.33584046 | ... L13: =IFERROR('Historical FS'!L32,0) -> 0.32059213 | N13: =AVERAGE(C13:L13) -> 0.33605108 | O13: =MEDIAN(C13:L13) -> 0.33856636
B14: Net Profit Margin | C14: =IFERROR('Historical FS'!C38,0) -> 0.20457567 | D14: =IFERROR('Historical FS'!D38,0) -> 0.20385993 | E14: =IFERROR('Historical FS'!E38,0) -> 0.21295963 | F14: =IFERROR('Historical FS'!F38,0) -> 0.222498 | G14: =IFERROR('Historical FS'!G38,0) -> 0.26677614 | H14: =IFERROR('Historical FS'!H38,0) -> 0.21937656 | I14: =IFERROR('Historical FS'!I38,0) -> 0.22414895 | J14: =IFERROR('Historical FS'!J38,0) -> 0.24505524 | ... L14: =IFERROR('Historical FS'!L38,0) -> 0.22911358 | N14: =AVERAGE(C14:L14) -> 0.22848102 | O14: =MEDIAN(C14:L14) -> 0.22332348
B16: Sales Expenses %sales | C16: =IFERROR('Historical FS'!C17,0) -> 0.22807249 | D16: =IFERROR('Historical FS'!D17,0) -> 0.2099884 | E16: =IFERROR('Historical FS'!E17,0) -> 0.20073562 | F16: =IFERROR('Historical FS'!F17,0) -> 0.20199017 | G16: =IFERROR('Historical FS'!G17,0) -> 0.20267293 | H16: =IFERROR('Historical FS'!H17,0) -> 0.19843678 | I16: =IFERROR('Historical FS'!I17,0) -> 0.17905783 | J16: =IFERROR('Historical FS'!J17,0) -> 0.17835636 | ... L16: =IFERROR('Historical FS'!L17,0) -> 0.18831427 | N16: =AVERAGE(C16:L16) -> 0.19735014 | O16: =MEDIAN(C16:L16) -> 0.1995862
B17: Depreciation %sales | C17: =IFERROR('Historical FS'!C23,0) -> 0.027490234 | D17: =IFERROR('Historical FS'!D23,0) -> 0.026954751 | E17: =IFERROR('Historical FS'!E23,0) -> 0.028453629 | F17: =IFERROR('Historical FS'!F23,0) -> 0.028891645 | G17: =IFERROR('Historical FS'!G23,0) -> 0.033306066 | H17: =IFERROR('Historical FS'!H23,0) -> 0.033407941 | I17: =IFERROR('Historical FS'!I23,0) -> 0.028566628 | J17: =IFERROR('Historical FS'!J23,0) -> 0.025508104 | ... L17: =IFERROR('Historical FS'!L23,0) -> 0.021856705 | N17: =AVERAGE(C17:L17) -> 0.027678233 | O17: =MEDIAN(C17:L17) -> 0.027971931
B18: Operating Income %Sales | C18: =IFERROR('Historical FS'!C14,0) -> 0.59884849 | D18: =IFERROR('Historical FS'!D14,0) -> 0.57169937 | E18: =IFERROR('Historical FS'!E14,0) -> 0.58096561 | F18: =IFERROR('Historical FS'!F14,0) -> 0.58547282 | G18: =IFERROR('Historical FS'!G14,0) -> 0.59434009 | H18: =IFERROR('Historical FS'!H14,0) -> 0.54487737 | I18: =IFERROR('Historical FS'!I14,0) -> 0.5191239 | J18: =IFERROR('Historical FS'!J14,0) -> 0.54080153 | ... L18: =IFERROR('Historical FS'!L14,0) -> 0.53136133 | N18: =AVERAGE(C18:L18) -> 0.56241429 | O18: =MEDIAN(C18:L18) -> 0.5641759
B20: Return on Capital Employed | C20: =IFERROR('Historical FS'!C25/SUM('Historical FS'!C52:C54),0) -> 0.31461767 | D20: =IFERROR('Historical FS'!D25/SUM('Historical FS'!D52:D54),0) -> 0.30816048 | E20: =IFERROR('Historical FS'!E25/SUM('Historical FS'!E52:E54),0) -> 0.29087469 | F20: =IFERROR('Historical FS'!F25/SUM('Historical FS'!F52:F54),0) -> 0.28976384 | G20: =IFERROR('Historical FS'!G25/SUM('Historical FS'!G52:G54),0) -> 0.26999906 | H20: =IFERROR('Historical FS'!H25/SUM('Historical FS'!H52:H54),0) -> 0.25436581 | I20: =IFERROR('Historical FS'!I25/SUM('Historical FS'!I52:I54),0) -> 0.30126365 | J20: =IFERROR('Historical FS'!J25/SUM('Historical FS'!J52:J54),0) -> 0.3440081 | ... L20: =IFERROR('Historical FS'!L25/SUM('Historical FS'!L52:L54),0) -> 0.34406984 | N20: =AVERAGE(C20:L20) -> 0.30335159 | O20: =MEDIAN(C20:L20) -> 0.30471206
B21: Retained Earnings% | C21: =IFERROR('Historical FS'!C48,0) -> 0.14687786 | D21: =IFERROR('Historical FS'!D48,0) -> 0.33819421 | E21: =IFERROR('Historical FS'!E48,0) -> 0.3207286 | F21: =IFERROR('Historical FS'!F48,0) -> 0.34463984 | G21: =IFERROR('Historical FS'!G48,0) -> 0.053044068 | H21: =IFERROR('Historical FS'!H48,0) -> 0 | I21: =IFERROR('Historical FS'!I48,0) -> 0 | J21: =IFERROR('Historical FS'!J48,0) -> 0 | ... L21: =IFERROR('Historical FS'!L48,0) -> 0 | N21: =AVERAGE(C21:L21) -> 0.12180906 | O21: =MEDIAN(C21:L21) -> 0.03382504
B22: Return on Equity% | C22: =IFERROR('Historical FS'!C37/SUM('Historical FS'!C52:C53),0) -> 0.18785942 | D22: =IFERROR('Historical FS'!D37/SUM('Historical FS'!D52:D53),0) -> 0.18784852 | E22: =IFERROR('Historical FS'!E37/SUM('Historical FS'!E52:E53),0) -> 0.17621121 | F22: =IFERROR('Historical FS'!F37/SUM('Historical FS'!F52:F53),0) -> 0.18186171 | G22: =IFERROR('Historical FS'!G37/SUM('Historical FS'!G52:G53),0) -> 0.2018508 | H22: =IFERROR('Historical FS'!H37/SUM('Historical FS'!H52:H53),0) -> 0.17906224 | I22: =IFERROR('Historical FS'!I37/SUM('Historical FS'!I52:I53),0) -> 0.21764928 | J22: =IFERROR('Historical FS'!J37/SUM('Historical FS'!J52:J53),0) -> 0.25130525 | ... L22: =IFERROR('Historical FS'!L37/SUM('Historical FS'!L52:L53),0) -> 0.24643135 | N22: =AVERAGE(C22:L22) -> 0.20638955 | O22: =MEDIAN(C22:L22) -> 0.19485511
B23: Self Sustained Growth Rate | C23: =IFERROR(C21*C22,0) -> 0.027592391 | D23: =IFERROR(D21*D22,0) -> 0.063529279 | E23: =IFERROR(E21*E22,0) -> 0.056515974 | F23: =IFERROR(F21*F22,0) -> 0.062676792 | G23: =IFERROR(G21*G22,0) -> 0.010706988 | H23: =IFERROR(H21*H22,0) -> 0 | I23: =IFERROR(I21*I22,0) -> 0 | J23: =IFERROR(J21*J22,0) -> 0 | ... L23: =IFERROR(L21*L22,0) -> 0 | N23: =AVERAGE(C23:L23) -> 0.022443654 | O23: =MEDIAN(C23:L23) -> 0.0070610516
B24: Interest Coverage Ratio | C24: =IFERROR('Historical FS'!C25/'Historical FS'!C28,0) -> 172.20133 | D24: =IFERROR('Historical FS'!D25/'Historical FS'!D28,0) -> 291.99918 | E24: =IFERROR('Historical FS'!E25/'Historical FS'!E28,0) -> 132.89549 | F24: =IFERROR('Historical FS'!F25/'Historical FS'!F28,0) -> 240.06695 | G24: =IFERROR('Historical FS'!G25/'Historical FS'!G28,0) -> 217.48132 | H24: =IFERROR('Historical FS'!H25/'Historical FS'!H28,0) -> 265.98568 | I24: =IFERROR('Historical FS'!I25/'Historical FS'!I28,0) -> 314.89815 | J24: =IFERROR('Historical FS'!J25/'Historical FS'!J28,0) -> 307.25537 | ... L24: =IFERROR('Historical FS'!L25/'Historical FS'!L28,0) -> 536.90923 | N24: =AVERAGE(C24:L24) -> 308.48955 | O24: =MEDIAN(C24:L24) -> 278.99243
B26: Debtor Turnover Ratio | C26: =IFERROR('Historical FS'!C7/'Raw FS'!E14,0) -> 16.755921 | D26: =IFERROR('Historical FS'!D7/'Raw FS'!F14,0) -> 16.084092 | E26: =IFERROR('Historical FS'!E7/'Raw FS'!G14,0) -> 12.428186 | F26: =IFERROR('Historical FS'!F7/'Raw FS'!H14,0) -> 13.77196 | G26: =IFERROR('Historical FS'!G7/'Raw FS'!I14,0) -> 13.605427 | H26: =IFERROR('Historical FS'!H7/'Raw FS'!J14,0) -> 11.404828 | I26: =IFERROR('Historical FS'!I7/'Raw FS'!K14,0) -> 13.729803 | J26: =IFERROR('Historical FS'!J7/'Raw FS'!L14,0) -> 15.221942 | ... L26: =IFERROR('Historical FS'!L7/'Raw FS'!N14,0) -> 15.669511 | N26: =AVERAGE(C26:L26) -> 14.283006 | O26: =MEDIAN(C26:L26) -> 13.965173
B27: Creditor Turnover Ratio | C27: =IFERROR('Historical FS'!C7/'Historical FS'!C64,0) -> 20.442577 | D27: =IFERROR('Historical FS'!D7/'Historical FS'!D64,0) -> 17.284797 | E27: =IFERROR('Historical FS'!E7/'Historical FS'!E64,0) -> 16.19845 | F27: =IFERROR('Historical FS'!F7/'Historical FS'!F64,0) -> 11.979238 | G27: =IFERROR('Historical FS'!G7/'Historical FS'!G64,0) -> 19.273399 | H27: =IFERROR('Historical FS'!H7/'Historical FS'!H64,0) -> 19.689591 | I27: =IFERROR('Historical FS'!I7/'Historical FS'!I64,0) -> 24.633226 | J27: =IFERROR('Historical FS'!J7/'Historical FS'!J64,0) -> 23.990173 | ... L27: =IFERROR('Historical FS'!L7/'Historical FS'!L64,0) -> 15.959451 | N27: =AVERAGE(C27:L27) -> 18.632497 | O27: =MEDIAN(C27:L27) -> 18.279098
B28: Inventory Turnover | C28: =IFERROR('Historical FS'!C7/'Historical FS'!C65,0) -> 4.3248364 | D28: =IFERROR('Historical FS'!D7/'Historical FS'!D65,0) -> 5.2694767 | E28: =IFERROR('Historical FS'!E7/'Historical FS'!E65,0) -> 5.7969871 | F28: =IFERROR('Historical FS'!F7/'Historical FS'!F65,0) -> 6.1504181 | G28: =IFERROR('Historical FS'!G7/'Historical FS'!G65,0) -> 5.5620976 | H28: =IFERROR('Historical FS'!H7/'Historical FS'!H65,0) -> 4.737587 | I28: =IFERROR('Historical FS'!I7/'Historical FS'!I65,0) -> 5.5820787 | J28: =IFERROR('Historical FS'!J7/'Historical FS'!J65,0) -> 6.0248123 | ... L28: =IFERROR('Historical FS'!L7/'Historical FS'!L65,0) -> 4.8168218 | N28: =AVERAGE(C28:L28) -> 5.3064983 | O28: =MEDIAN(C28:L28) -> 5.4157872
B29: Fixed Asset Turnover | C29: =IFERROR('Historical FS'!C7/'Historical FS'!C58,0) -> 2.5943642 | D29: =IFERROR('Historical FS'!D7/'Historical FS'!D58,0) -> 2.6908896 | E29: =IFERROR('Historical FS'!E7/'Historical FS'!E58,0) -> 2.6294508 | F29: =IFERROR('Historical FS'!F7/'Historical FS'!F58,0) -> 2.4950504 | G29: =IFERROR('Historical FS'!G7/'Historical FS'!G58,0) -> 2.2745326 | H29: =IFERROR('Historical FS'!H7/'Historical FS'!H58,0) -> 2.1141916 | I29: =IFERROR('Historical FS'!I7/'Historical FS'!I58,0) -> 2.5027058 | J29: =IFERROR('Historical FS'!J7/'Historical FS'!J58,0) -> 2.743348 | ... L29: =IFERROR('Historical FS'!L7/'Historical FS'!L58,0) -> 3.4308292 | N29: =AVERAGE(C29:L29) -> 2.5917181 | O29: =MEDIAN(C29:L29) -> 2.548535
B30: Capital Turnover Ratio | C30: =IFERROR('Historical FS'!C7/SUM('Historical FS'!C52:C53),0) -> 0.91828821 | D30: =IFERROR('Historical FS'!D7/SUM('Historical FS'!D52:D53),0) -> 0.92145874 | E30: =IFERROR('Historical FS'!E7/SUM('Historical FS'!E52:E53),0) -> 0.82743952 | F30: =IFERROR('Historical FS'!F7/SUM('Historical FS'!F52:F53),0) -> 0.81736336 | G30: =IFERROR('Historical FS'!G7/SUM('Historical FS'!G52:G53),0) -> 0.7566299 | H30: =IFERROR('Historical FS'!H7/SUM('Historical FS'!H52:H53),0) -> 0.81623233 | I30: =IFERROR('Historical FS'!I7/SUM('Historical FS'!I52:I53),0) -> 0.97100291 | J30: =IFERROR('Historical FS'!J7/SUM('Historical FS'!J52:J53),0) -> 1.0255045 | ... L30: =IFERROR('Historical FS'!L7/SUM('Historical FS'!L52:L53),0) -> 1.075586 | N30: =AVERAGE(C30:L30) -> 0.90412579 | O30: =MEDIAN(C30:L30) -> 0.91502033
B32: (in days)
B33: Debtor Days | C33: =IFERROR(365/C26,0) -> 21.783344 | D33: =IFERROR(365/D26,0) -> 22.69323 | E33: =IFERROR(365/E26,0) -> 29.368726 | F33: =IFERROR(365/F26,0) -> 26.503126 | G33: =IFERROR(365/G26,0) -> 26.82753 | H33: =IFERROR(365/H26,0) -> 32.003991 | I33: =IFERROR(365/I26,0) -> 26.584504 | J33: =IFERROR(365/J26,0) -> 23.978543 | ... L33: =IFERROR(365/L26,0) -> 23.293643 | N33: =AVERAGE(C33:L33) -> 25.881641 | O33: =MEDIAN(C33:L33) -> 26.14145
B34: Payable Days | C34: =IFERROR(365/C27,0) -> 17.854892 | D34: =IFERROR(365/D27,0) -> 21.116823 | E34: =IFERROR(365/E27,0) -> 22.53302 | F34: =IFERROR(365/F27,0) -> 30.469383 | G34: =IFERROR(365/G27,0) -> 18.938019 | H34: =IFERROR(365/H27,0) -> 18.537714 | I34: =IFERROR(365/I27,0) -> 14.817385 | J34: =IFERROR(365/J27,0) -> 15.214563 | ... L34: =IFERROR(365/L27,0) -> 22.870462 | N34: =AVERAGE(C34:L34) -> 20.398309 | O34: =MEDIAN(C34:L34) -> 20.027421
B35: Inventory Days | C35: =IFERROR(365/C28,0) -> 84.396256 | D35: =IFERROR(365/D28,0) -> 69.26684 | E35: =IFERROR(365/E28,0) -> 62.963742 | F35: =IFERROR(365/F28,0) -> 59.345559 | G35: =IFERROR(365/G28,0) -> 65.622725 | H35: =IFERROR(365/H28,0) -> 77.04344 | I35: =IFERROR(365/I28,0) -> 65.387828 | J35: =IFERROR(365/J28,0) -> 60.5828 | ... L35: =IFERROR(365/L28,0) -> 75.776106 | N35: =AVERAGE(C35:L35) -> 69.642907 | O35: =MEDIAN(C35:L35) -> 67.444782
B36: Cash Conversion Days | C36: =SUM(C33,C35)-C34 -> 88.324708 | D36: =SUM(D33,D35)-D34 -> 70.843247 | E36: =SUM(E33,E35)-E34 -> 69.799447 | F36: =SUM(F33,F35)-F34 -> 55.379302 | G36: =SUM(G33,G35)-G34 -> 73.512236 | H36: =SUM(H33,H35)-H34 -> 90.509718 | I36: =SUM(I33,I35)-I34 -> 77.154947 | J36: =SUM(J33,J35)-J34 -> 69.34678 | ... L36: =SUM(L33,L35)-L34 -> 76.199288 | N36: =AVERAGE(C36:L36) -> 75.126239 | O36: =MEDIAN(C36:L36) -> 74.855762
B38: CFO/Sales | C38: =IFERROR('Historical FS'!C75/'Historical FS'!C7,0) -> 0.2500259 | D38: =IFERROR('Historical FS'!D75/'Historical FS'!D7,0) -> 0.24848974 | E38: =IFERROR('Historical FS'!E75/'Historical FS'!E7,0) -> 0.3031006 | F38: =IFERROR('Historical FS'!F75/'Historical FS'!F7,0) -> 0.26031277 | G38: =IFERROR('Historical FS'!G75/'Historical FS'!G7,0) -> 0.2974356 | H38: =IFERROR('Historical FS'!H75/'Historical FS'!H7,0) -> 0.25431625 | I38: =IFERROR('Historical FS'!I75/'Historical FS'!I7,0) -> 0.26013076 | J38: =IFERROR('Historical FS'!J75/'Historical FS'!J7,0) -> 0.26618455 | ... L38: =IFERROR('Historical FS'!L75/'Historical FS'!L7,0) -> 0.2340183 | N38: =AVERAGE(C38:L38) -> 0.26268979 | O38: =MEDIAN(C38:L38) -> 0.2572235
B39: CFO/Total Assets | C39: =IFERROR('Historical FS'!C75/'Historical FS'!C69,0) -> 0.18971512 | D39: =IFERROR('Historical FS'!D75/'Historical FS'!D69,0) -> 0.19011859 | E39: =IFERROR('Historical FS'!E75/'Historical FS'!E69,0) -> 0.20500031 | F39: =IFERROR('Historical FS'!F75/'Historical FS'!F69,0) -> 0.17540533 | G39: =IFERROR('Historical FS'!G75/'Historical FS'!G69,0) -> 0.19000799 | H39: =IFERROR('Historical FS'!H75/'Historical FS'!H69,0) -> 0.16983244 | I39: =IFERROR('Historical FS'!I75/'Historical FS'!I69,0) -> 0.20435652 | J39: =IFERROR('Historical FS'!J75/'Historical FS'!J69,0) -> 0.2199387 | ... L39: =IFERROR('Historical FS'!L75/'Historical FS'!L69,0) -> 0.20030113 | N39: =AVERAGE(C39:L39) -> 0.19319036 | O39: =MEDIAN(C39:L39) -> 0.19006329
B40: CFO/Total Debt | C40: =IFERROR('Historical FS'!C75/'Historical FS'!C54,0) -> 116.96157 | D40: =IFERROR('Historical FS'!D75/'Historical FS'!D54,0) -> 232.44335 | E40: =IFERROR('Historical FS'!E75/'Historical FS'!E54,0) -> 366.6314 | F40: =IFERROR('Historical FS'!F75/'Historical FS'!F54,0) -> 936.26562 | G40: =IFERROR('Historical FS'!G75/'Historical FS'!G54,0) -> 52.945251 | H40: =IFERROR('Historical FS'!H75/'Historical FS'!H54,0) -> 46.253997 | I40: =IFERROR('Historical FS'!I75/'Historical FS'!I54,0) -> 63.243706 | J40: =IFERROR('Historical FS'!J75/'Historical FS'!J54,0) -> 61.683277 | ... L40: =IFERROR('Historical FS'!L75/'Historical FS'!L54,0) -> 61.949251 | N40: =AVERAGE(C40:L40) -> 199.4993 | O40: =MEDIAN(C40:L40) -> 62.596479

Sheet Forecast
B2: ='Data Sheet'!B1&" - "&'Data Sheet'!A17&" Forecast" -> ITC LTD - Sales Forecast | G2: ='Data Sheet'!B1&" - "&'Historical FS'!B19&" Forecast" -> ITC LTD - EBITDA Forecast | L2: ='Data Sheet'!B1&" - "&'Historical FS'!B42&" Forecast" -> ITC LTD - Earnings Per Share Forecast
B3: Year Weight | C3: Year | D3: Sales | E3: Sales Growth | G3: Year Weight | H3: Year | I3: EBITDA | J3: EBITDA Growth | L3: Year Weight | M3: Year | N3: EPS | O3: EPS Growth
B4: 1 | C4: {=TRANSPOSE('Data Sheet'!B16:K16)} -> 42460 | D4: {=TRANSPOSE('Historical FS'!C7:L7)} -> 39192.1 | G4: 1 | H4: {=TRANSPOSE('Data Sheet'!B16:K16)} -> 42460 | I4: {=TRANSPOSE('Historical FS'!C19:L19)} -> 14531.49 | L4: 1 | M4: {=TRANSPOSE('Data Sheet'!B16:K16)} -> 42460 | N4: {=TRANSPOSE('Historical FS'!C42:L42)} -> 6.3991147
B5: 2 | C5: 42825 | D5: 42767.6 | E5: =IFERROR(D5/D4-1,0) -> 0.09123012 | G5: 2 | H5: 42825 | I5: 15469.51 | J5: =IFERROR(I5/I4-1,0) -> 0.064550848 | L5: 2 | M5: 42825 | N5: 6.958476 | O5: =IFERROR(N5/N4-1,0) -> 0.087412304
B6: 3 | C6: 43190 | D6: 43448.94 | E6: =IFERROR(D6/D5-1,0) -> 0.015931219 | G6: 3 | H6: 43190 | I6: 16520.59 | J6: =IFERROR(I6/I5-1,0) -> 0.067945268 | L6: 3 | M6: 43190 | N6: 7.3848868 | O6: =IFERROR(N6/N5-1,0) -> 0.061279334
B7: 4 | C7: 43555 | D7: 48339.58 | E7: =IFERROR(D7/D6-1,0) -> 0.11256063 | G7: 4 | H7: 43555 | I7: 18537.39 | J7: =IFERROR(I7/I6-1,0) -> 0.12207796 | L7: 4 | M7: 43555 | N7: 8.5841317 | O7: =IFERROR(N7/N6-1,0) -> 0.16239178
B8: 5 | C8: 43921 | D8: 49387.7 | E8: =IFERROR(D8/D7-1,0) -> 0.021682439 | G8: 5 | H8: 43921 | I8: 19343.54 | J8: =IFERROR(I8/I7-1,0) -> 0.043487783 | L8: 5 | M8: 43921 | N8: 10.515579 | O8: =IFERROR(N8/N7-1,0) -> 0.225002
B9: 6 | C9: 44286 | D9: 49257.45 | E9: =IFERROR(D9/D8-1,0) -> -0.0026372963 | G9: 6 | H9: 44286 | I9: 17064.78 | J9: =IFERROR(I9/I8-1,0) -> -0.1178047 | L9: 6 | M9: 44286 | N9: 8.6244128 | O9: =IFERROR(N9/N8-1,0) -> -0.1798442
B10: 7 | C10: 44651 | D10: 60644.54 | E10: =IFERROR(D10/D9-1,0) -> 0.23117498 | G10: 7 | H10: 44651 | I10: 20623.15 | J10: =IFERROR(I10/I9-1,0) -> 0.20852129 | L10: 7 | M10: 44651 | N10: 10.849152 | O10: =IFERROR(N10/N9-1,0) -> 0.25795836
B11: 8 | C11: 45016 | D11: 70919.03 | E11: =IFERROR(D11/D10-1,0) -> 0.16942152 | G11: 8 | H11: 45016 | I11: 25704.26 | J11: =IFERROR(I11/I10-1,0) -> 0.24637895 | L11: 8 | M11: 45016 | N11: 13.870565 | O11: =IFERROR(N11/N10-1,0) -> 0.27849303
B12: 9 | C12: 45382 | D12: 67931.94 | E12: =IFERROR(D12/D11-1,0) -> -0.042119724 | G12: 9 | H12: 45382 | I12: 25187.53 | J12: =IFERROR(I12/I11-1,0) -> -0.020102893 | L12: 9 | M12: 45382 | N12: 13.903951 | O12: =IFERROR(N12/N11-1,0) -> 0.0024069168
B13: 10 | C13: 45747 | D13: 75323.34 | E13: =IFERROR(D13/D12-1,0) -> 0.10880596 | G13: 10 | H13: 45747 | I13: 25839.45 | J13: =IFERROR(I13/I12-1,0) -> 0.025882649 | L13: 10 | M13: 45747 | N13: 13.77361 | O13: =IFERROR(N13/N12-1,0) -> -0.0093743668
B14: 11 | C14: =C13+365 -> 46112 | D14: =FORECAST(B14,$D$4:$D$13,$B$4:$B$13) -> 77236.776 | E14: =IFERROR(D14/D13-1,0) -> 0.025402963 | G14: 11 | H14: =H13+365 -> 46112 | I14: =FORECAST(G14,$I$4:$I$13,$G$4:$G$13) -> 27205.324 | J14: =IFERROR(I14/I13-1,0) -> 0.052860026 | L14: 11 | M14: =M13+365 -> 46112 | N14: =FORECAST(L14,$N$4:$N$13,$L$4:$L$13) -> 15.163757 | O14: =IFERROR(N14/N13-1,0) -> 0.10092829
B15: 12 | C15: =C14+365 -> 46477 | D15: =FORECAST(B15,$D$4:$D$13,$B$4:$B$13) -> 81330.513 | E15: =IFERROR(D15/D14-1,0) -> 0.053002434 | G15: 12 | H15: =H14+365 -> 46477 | I15: =FORECAST(G15,$I$4:$I$13,$G$4:$G$13) -> 28536.807 | J15: =IFERROR(I15/I14-1,0) -> 0.048941991 | L15: 12 | M15: =M14+365 -> 46477 | N15: =FORECAST(L15,$N$4:$N$13,$L$4:$L$13) -> 16.086915 | O15: =IFERROR(N15/N14-1,0) -> 0.06087924
B16: 13 | C16: =C15+365 -> 46842 | D16: =FORECAST(B16,$D$4:$D$13,$B$4:$B$13) -> 85424.25 | E16: =IFERROR(D16/D15-1,0) -> 0.050334578 | G16: 13 | H16: =H15+365 -> 46842 | I16: =FORECAST(G16,$I$4:$I$13,$G$4:$G$13) -> 29868.289 | J16: =IFERROR(I16/I15-1,0) -> 0.046658434 | L16: 13 | M16: =M15+365 -> 46842 | N16: =FORECAST(L16,$N$4:$N$13,$L$4:$L$13) -> 17.010073 | O16: =IFERROR(N16/N15-1,0) -> 0.057385646
B17: 14 | C17: =C16+365 -> 47207 | D17: =FORECAST(B17,$D$4:$D$13,$B$4:$B$13) -> 89517.987 | E17: =IFERROR(D17/D16-1,0) -> 0.047922423 | G17: 14 | H17: =H16+365 -> 47207 | I17: =FORECAST(G17,$I$4:$I$13,$G$4:$G$13) -> 31199.772 | J17: =IFERROR(I17/I16-1,0) -> 0.044578473 | L17: 14 | M17: =M16+365 -> 47207 | N17: =FORECAST(L17,$N$4:$N$13,$L$4:$L$13) -> 17.933231 | O17: =IFERROR(N17/N16-1,0) -> 0.054271255
B18: 15 | C18: =C17+365 -> 47572 | D18: =FORECAST(B18,$D$4:$D$13,$B$4:$B$13) -> 93611.724 | E18: =IFERROR(D18/D17-1,0) -> 0.045730888 | G18: 15 | H18: =H17+365 -> 47572 | I18: =FORECAST(G18,$I$4:$I$13,$G$4:$G$13) -> 32531.255 | J18: =IFERROR(I18/I17-1,0) -> 0.04267604 | L18: 15 | M18: =M17+365 -> 47572 | N18: =FORECAST(L18,$N$4:$N$13,$L$4:$L$13) -> 18.856389 | O18: =IFERROR(N18/N17-1,0) -> 0.051477506

Sheet WACC
B2: ="Weighted Average Cost of Capital"&" - "&'Data Sheet'!B1 -> Weighted Average Cost of Capital - ITC LTD
B4: All figures are in INR unless stated otherwise.
B6: Peer comps
G7: Debt / | H7: Debt / | I7: Levered | J7: Unlevered
B8: Name of the comp | C8: Country | D8: Total Debt | E8: Total Equity | F8: Tax rate 1 | G8: Equity | H8: Capital | I8: Beta 2 | J8: Beta 3
B10: ='Peer Comps'!C5 -> ITC | C10: India | D10: =IFERROR('Peer Comps'!F5,0) -> 362.97 | E10: =IFERROR('Peer Comps'!E5,0) -> 387348.51 | F10: =IFERROR('Peer Comps'!I12,0) -> 0.27862226 | G10: =IFERROR(D10/E10,0) -> 0.00093706311 | H10: =IFERROR(D10/(D10+E10),0) -> 0.00093618585 | I10: =IFERROR('Peer Comps'!H5,0) -> 0.515 | J10: =IFERROR(I10/(1+(1-F10)*G10),0) -> 0.51465211
B11: ='Peer Comps'!C4 -> Hind. Unilever | C11: India | D11: =IFERROR('Peer Comps'!F4,0) -> 1775 | E11: =IFERROR('Peer Comps'!E4,0) -> 540705.54 | F11: =IFERROR('Peer Comps'!I13,0) -> 0.2592 | G11: =IFERROR(D11/E11,0) -> 0.0032827479 | H11: =IFERROR(D11/(D11+E11),0) -> 0.0032720068 | I11: =IFERROR('Peer Comps'!H4,0) -> 0.584 | J11: =IFERROR(I11/(1+(1-F11)*G11),0) -> 0.58258324
B12: ='Peer Comps'!C6 -> Nestle India | C12: India | D12: =IFERROR('Peer Comps'!F6,0) -> 444.16 | E12: =IFERROR('Peer Comps'!E6,0) -> 265881.4 | F12: =IFERROR('Peer Comps'!I14,0) -> 0.25904 | G12: =IFERROR(D12/E12,0) -> 0.0016705193 | H12: =IFERROR(D12/(D12+E12),0) -> 0.0016677333 | I12: =IFERROR('Peer Comps'!H6,0) -> 0.751 | J12: =IFERROR(I12/(1+(1-F12)*G12),0) -> 0.75007157
B13: ='Peer Comps'!C7 -> Varun Beverages | C13: India | D13: =IFERROR('Peer Comps'!F7,0) -> 2508.18 | E13: =IFERROR('Peer Comps'!E7,0) -> 164118.16 | F13: =IFERROR('Peer Comps'!I15,0) -> 0.25 | G13: =IFERROR(D13/E13,0) -> 0.015282769 | H13: =IFERROR(D13/(D13+E13),0) -> 0.015052722 | I13: =IFERROR('Peer Comps'!H7,0) -> 1.16 | J13: =IFERROR(I13/(1+(1-F13)*G13),0) -> 1.1468547
B14: ='Peer Comps'!C8 -> Britannia Inds. | C14: India | D14: =IFERROR('Peer Comps'!F8,0) -> 2196.3 | E14: =IFERROR('Peer Comps'!E8,0) -> 140725.16 | F14: =IFERROR('Peer Comps'!I16,0) -> 0.25878 | G14: =IFERROR(D14/E14,0) -> 0.015607017 | H14: =IFERROR(D14/(D14+E14),0) -> 0.015367181 | I14: =IFERROR('Peer Comps'!H8,0) -> 0.51 | J14: =IFERROR(I14/(1+(1-F14)*G14),0) -> 0.50416767
E16: Average | F16: =AVERAGE(F10:F14) -> 0.26112845 | G16: =AVERAGE(G10:G14) -> 0.0073560234 | H16: =AVERAGE(H10:H14) -> 0.0072591659 | I16: =AVERAGE(I10:I14) -> 0.704 | J16: =AVERAGE(J10:J14) -> 0.69966585
E17: Median | F17: =MEDIAN(F10:F14) -> 0.25904 | G17: =MEDIAN(G10:G14) -> 0.0032827479 | H17: =MEDIAN(H10:H14) -> 0.0032720068 | I17: =MEDIAN(I10:I14) -> 0.584 | J17: =MEDIAN(J10:J14) -> 0.58258324
B20: Cost of Debt | G20: Cost of Equity
B22: Pre-Tax Cost of Debt | E22: ='Data Sheet'!K27/WACC!D10 -> 0.12414249 | G22: Risk free Rate | J22: 0.06891
B23: Tax Rate | E23: =F17 -> 0.25904 | G23: Equity Risk Premium | J23: =IFERROR('Return on Market'!F7-WACC!J22,0) -> 0.095382308
B24: Post -Tax Cost of Debt | E24: =E22*(1-E23) -> 0.09198462 | G24: Levered Beta 4 | J24: =J33 -> 0.58400031
G25: Cost of Equity | J25: =J22+(J23*J24) -> 0.1246133
B28: Capital Structure | G28: Capital Structure
D30: Current | E30: Target | G30: Comps Median Unlevered Beta | J30: =J17 -> 0.58258324
B31: Total Debt | C31: =D10 -> 362.97 | D31: =C31/$C$33 -> 0.00093618585 | E31: =H17 -> 0.0032720068 | G31: Target Debt / Equity | J31: =E35 -> 0.0032827479
B32: Market Capitalisation | C32: =E10 -> 387348.51 | D32: =C32/$C$33 -> 0.99906381 | E32: =IFERROR(E33-E31,0) -> 0.99672799 | G32: Tax Rate | J32: =E23 -> 0.25904
B33: Total Capital | C33: =IFERROR(C32+C31,0) -> 387711.48 | D33: =C33/$C$33 -> 1 | E33: =D33 -> 1 | G33: Levered Beta | J33: =J30*(1+(1-J32)*J31) -> 0.58400031
B35: Debt / Equity | D35: =D31/D32 -> 0.00093706311 | E35: =E31/E32 -> 0.0032827479
G36: Weighted Average Cost of Capital
B37: Notes:
B38: 1.Tax rate considered as marginal tax rate of the country. | G38: Cost of Equity | J38: =J25 -> 0.1246133
B39: 2.Levered beta is based on 5 year monthly data | G39: Equity Weight | J39: =E32 -> 0.99672799
B40: 3.Unlevered beta = Levered beta / (1+(1-tax_rate)*Debt / Equity)
B41: 4.Levered beta = Unlevered beta * (1+(1-tax_rate)*Debt / Equity) | G41: Cost of Debt | J41: =E24 -> 0.09198462
G42: Debt Weight | J42: =E31 -> 0.0032720068
G44: WACC | J44: =(J38*J39)+(J41*J42) -> 0.12450654

Sheet Intrinsic Growth
A2: # | B2: Calculation of ROIC | F2: ='Data Sheet'!G16 -> 44286 | G2: ='Data Sheet'!H16 -> 44651 | H2: ='Data Sheet'!I16 -> 45016 | I2: ='Data Sheet'!J16 -> 45382 | J2: ='Data Sheet'!K16 -> 45747
B4: Current assets
B5: ='Raw FS'!B37 -> Inventories | F5: =IFERROR('Raw FS'!J37,0) -> 10397 | G5: =IFERROR('Raw FS'!K37,0) -> 10864 | H5: =IFERROR('Raw FS'!L37,0) -> 11771 | I5: =IFERROR('Raw FS'!M37,0) -> 14153 | J5: =IFERROR('Raw FS'!N37,0) -> 15638
B6: ='Raw FS'!B38 -> Trade receivables | F6: =IFERROR('Raw FS'!J38,0) -> 2502 | G6: =IFERROR('Raw FS'!K38,0) -> 2462 | H6: =IFERROR('Raw FS'!L38,0) -> 2956 | I6: =IFERROR('Raw FS'!M38,0) -> 4026 | J6: =IFERROR('Raw FS'!N38,0) -> 4720
B7: ='Raw FS'!B40 -> Loans n Advances | F7: =IFERROR('Raw FS'!J40,0) -> 7 | G7: =IFERROR('Raw FS'!K40,0) -> 11 | H7: =IFERROR('Raw FS'!L40,0) -> 13 | I7: =IFERROR('Raw FS'!M40,0) -> 31 | J7: =IFERROR('Raw FS'!N40,0) -> 10
B8: ='Raw FS'!B41 -> Other asset items | F8: =IFERROR('Raw FS'!J41,0) -> 4015 | G8: =IFERROR('Raw FS'!K41,0) -> 6906 | H8: =IFERROR('Raw FS'!L41,0) -> 7941 | I8: =IFERROR('Raw FS'!M41,0) -> 4531 | J8: =IFERROR('Raw FS'!N41,0) -> 5858
B9: Total Current Assets | F9: =SUM(F5:F8) -> 16921 | G9: =SUM(G5:G8) -> 20243 | H9: =SUM(H5:H8) -> 22681 | I9: =SUM(I5:I8) -> 22741 | J9: =SUM(J5:J8) -> 26226
B11: Current Liabilities
B12: ='Raw FS'!B14 -> Trade Payables | F12: ='Raw FS'!J14 -> 4319 | G12: ='Raw FS'!K14 -> 4417 | H12: ='Raw FS'!L14 -> 4659 | I12: ='Raw FS'!M14 -> 4798 | J12: ='Raw FS'!N14 -> 4807
B13: ='Raw FS'!B9 -> Short term Borrowings | F13: ='Raw FS'!J9 -> 4 | G13: ='Raw FS'!K9 -> 1 | H13: ='Raw FS'!L9 -> 35 | I13: ='Raw FS'!M9 -> 10 | J13: ='Raw FS'!N9 -> 91
B14: ='Raw FS'!B10 -> Lease Liabilities | F14: ='Raw FS'!J10 -> 261 | G14: ='Raw FS'!K10 -> 244 | H14: ='Raw FS'!L10 -> 267 | I14: ='Raw FS'!M10 -> 292 | J14: ='Raw FS'!N10 -> 193
B15: ='Raw FS'!B15 -> Advance from Customers | F15: ='Raw FS'!J15 -> 811 | G15: ='Raw FS'!K15 -> 1278 | H15: ='Raw FS'!L15 -> 1295 | I15: ='Raw FS'!M15 -> 886 | J15: ='Raw FS'!N15 -> 1264
B16: ='Raw FS'!B16 -> Other liability items | F16: ='Raw FS'!J16 -> 7666 | G16: ='Raw FS'!K16 -> 8429 | H16: ='Raw FS'!L16 -> 10032 | I16: ='Raw FS'!M16 -> 10877 | J16: ='Raw FS'!N16 -> 11249
B17: Total Current Liabilites | F17: =SUM(F12:F16) -> 13061 | G17: =SUM(G12:G16) -> 14369 | H17: =SUM(H12:H16) -> 16288 | I17: =SUM(I12:I16) -> 16863 | J17: =SUM(J12:J16) -> 17604
A19: # | B19: Net Working Capital | F19: =F9-F17 -> 3860 | G19: =G9-G17 -> 5874 | H19: =H9-H17 -> 6393 | I19: =I9-I17 -> 5878 | J19: =J9-J17 -> 8622
B21: Non Current Assets
B22: ='Raw FS'!B20 -> Land | F22: =IFERROR('Raw FS'!J20,0) -> 2889 | G22: =IFERROR('Raw FS'!K20,0) -> 2829 | H22: =IFERROR('Raw FS'!L20,0) -> 2830 | I22: =IFERROR('Raw FS'!M20,0) -> 2865 | J22: =IFERROR('Raw FS'!N20,0) -> 1588
B23: ='Raw FS'!B21 -> Building | F23: =IFERROR('Raw FS'!J21,0) -> 8387 | G23: =IFERROR('Raw FS'!K21,0) -> 9100 | H23: =IFERROR('Raw FS'!L21,0) -> 9789 | I23: =IFERROR('Raw FS'!M21,0) -> 10944 | J23: =IFERROR('Raw FS'!N21,0) -> 7550
B24: ='Raw FS'!B22 -> Plant Machinery | F24: =IFERROR('Raw FS'!J22,0) -> 15307 | G24: =IFERROR('Raw FS'!K22,0) -> 16912 | H24: =IFERROR('Raw FS'!L22,0) -> 18480 | I24: =IFERROR('Raw FS'!M22,0) -> 20718 | J24: =IFERROR('Raw FS'!N22,0) -> 19423
B25: ='Raw FS'!B23 -> Equipments | F25: =IFERROR('Raw FS'!J23,0) -> 41 | G25: =IFERROR('Raw FS'!K23,0) -> 44 | H25: =IFERROR('Raw FS'!L23,0) -> 44 | I25: =IFERROR('Raw FS'!M23,0) -> 53 | J25: =IFERROR('Raw FS'!N23,0) -> 63
B26: ='Raw FS'!B24 -> Furniture n fittings | F26: =IFERROR('Raw FS'!J24,0) -> 833 | G26: =IFERROR('Raw FS'!K24,0) -> 907 | H26: =IFERROR('Raw FS'!L24,0) -> 1000 | I26: =IFERROR('Raw FS'!M24,0) -> 1068 | J26: =IFERROR('Raw FS'!N24,0) -> 282
B27: ='Raw FS'!B25 -> Railway sidings | F27: =IFERROR('Raw FS'!J25,0) -> 2 | G27: =IFERROR('Raw FS'!K25,0) -> 2 | H27: =IFERROR('Raw FS'!L25,0) -> 2 | I27: =IFERROR('Raw FS'!M25,0) -> 2 | J27: =IFERROR('Raw FS'!N25,0) -> 2
B28: ='Raw FS'!B26 -> Vehicles | F28: =IFERROR('Raw FS'!J26,0) -> 180 | G28: =IFERROR('Raw FS'!K26,0) -> 179 | H28: =IFERROR('Raw FS'!L26,0) -> 189 | I28: =IFERROR('Raw FS'!M26,0) -> 192 | J28: =IFERROR('Raw FS'!N26,0) -> 141
B29: ='Raw FS'!B27 -> Intangible Assets | F29: =IFERROR('Raw FS'!J27,0) -> 2734 | G29: =IFERROR('Raw FS'!K27,0) -> 2744 | H29: =IFERROR('Raw FS'!L27,0) -> 3490 | I29: =IFERROR('Raw FS'!M27,0) -> 3505 | J29: =IFERROR('Raw FS'!N27,0) -> 3622
B30: ='Raw FS'!B28 -> Other fixed assets | F30: =IFERROR('Raw FS'!J28,0) -> 716 | G30: =IFERROR('Raw FS'!K28,0) -> 719 | H30: =IFERROR('Raw FS'!L28,0) -> 786 | I30: =IFERROR('Raw FS'!M28,0) -> 841 | J30: =IFERROR('Raw FS'!N28,0) -> 967
B32: Gross Block | F32: =SUM(F22:F30) -> 31089 | G32: =SUM(G22:G30) -> 33436 | H32: =SUM(H22:H30) -> 36610 | I32: =SUM(I22:I30) -> 40188 | J32: =SUM(J22:J30) -> 33638
B33: Accumulated Depreciation | F33: =IFERROR(-'Raw FS'!J30,0) -> -7790 | G33: =IFERROR(-'Raw FS'!K30,0) -> -9204 | H33: =IFERROR(-'Raw FS'!L30,0) -> -10757 | I33: =IFERROR(-'Raw FS'!M30,0) -> -12368 | J33: =IFERROR(-'Raw FS'!N30,0) -> -11683
A34: # | B34: Net Non Current Assets | F34: =SUM(F32:F33) -> 23299 | G34: =SUM(G32:G33) -> 24232 | H34: =SUM(H32:H33) -> 25853 | I34: =SUM(I32:I33) -> 27820 | J34: =SUM(J32:J33) -> 21955
B36: Invested Capital | F36: =F34+F19 -> 27159 | G36: =G34+G19 -> 30106 | H36: =H34+H19 -> 32246 | I36: =I34+I19 -> 33698 | J36: =J34+J19 -> 30577
B37: NOPAT | F37: =IFERROR('Historical FS'!H25*(1-'Historical FS'!H35),0) -> 10846.709 | G37: =IFERROR('Historical FS'!I25*(1-'Historical FS'!I35),0) -> 13636.715 | H37: =IFERROR('Historical FS'!J25*(1-'Historical FS'!J35),0) -> 17435.827 | I37: =IFERROR('Historical FS'!K25*(1-'Historical FS'!K35),0) -> 17449.743 | J37: =IFERROR('Historical FS'!L25*(1-'Historical FS'!L35),0) -> 17289.802
A39: # | B39: ROIC | F39: =F37/F36 -> 0.39937808 | G39: =G37/G36 -> 0.45295672 | H39: =H37/H36 -> 0.54071286 | I39: =I37/I36 -> 0.51782726 | J39: =J37/J36 -> 0.56545124
A42: # | B42: Calculation of Reinvestment Rate | F42: ='Data Sheet'!G16 -> 44286 | G42: ='Data Sheet'!H16 -> 44651 | H42: ='Data Sheet'!I16 -> 45016 | I42: ='Data Sheet'!J16 -> 45382 | J42: ='Data Sheet'!K16 -> 45747
B44: Net CAPEX | F44: =IFERROR(SUM('Raw FS'!J57:J58),0) -> -1834 | G44: =IFERROR(SUM('Raw FS'!K57:K58),0) -> -2009 | H44: =IFERROR(SUM('Raw FS'!L57:L58),0) -> -2694 | I44: =IFERROR(SUM('Raw FS'!M57:M58),0) -> -3456 | J44: =IFERROR(SUM('Raw FS'!N57:N58),0) -> -2104
B45: Change in Working Capital | G45: =G19-F19 -> 2014 | H45: =H19-G19 -> 519 | I45: =I19-H19 -> -515 | J45: =J19-I19 -> 2744
B47: EBIT | F47: =F37 -> 10846.709 | G47: =G37 -> 13636.715 | H47: =H37 -> 17435.827 | I47: =I37 -> 17449.743 | J47: =J37 -> 17289.802
B48: Marginal Tax Rate | F48: ='Historical FS'!H35 -> 0.29654481 | G48: ='Historical FS'!I35 -> 0.278127 | H48: ='Historical FS'!J35 -> 0.27032247 | I48: ='Historical FS'!K35 -> 0.26277456 | J48: ='Historical FS'!L35 -> 0.28534247
B49: EBIT(1-T) | F49: =F47*(1-F48) -> 7630.174 | G49: =G47*(1-G48) -> 9843.9765 | H49: =H47*(1-H48) -> 12722.531 | I49: =I47*(1-I48) -> 12864.394 | J49: =J47*(1-J48) -> 12356.287
B51: Reinvestment | G51: =SUM(G44:G45) -> 5 | H51: =SUM(H44:H45) -> -2175 | I51: =SUM(I44:I45) -> -3971 | J51: =SUM(J44:J45) -> 640
B53: Reinvestment Rate | G53: =G51/G49 -> 0.00050792482 | H53: =H51/H49 -> -0.17095655 | I53: =I51/I49 -> -0.30868146 | J53: =J51/J49 -> 0.051795493
H55: 4 Year Average | J55: =AVERAGE(G53:J53) -> -0.10683365
H56: 4 Year Median | J56: =MEDIAN(G53:J53) -> -0.085224311
A59: # | B59: Calculation of Growth Rate | F59: ='Data Sheet'!G16 -> 44286 | G59: ='Data Sheet'!H16 -> 44651 | H59: ='Data Sheet'!I16 -> 45016 | I59: ='Data Sheet'!J16 -> 45382 | J59: ='Data Sheet'!K16 -> 45747
B61: Reinvestment | G61: =G53 -> 0.00050792482 | H61: =H53 -> -0.17095655 | I61: =I53 -> -0.30868146 | J61: =J53 -> 0.051795493
B62: ROIC | G62: =G39 -> 0.45295672 | H62: =H39 -> 0.54071286 | I62: =I39 -> 0.51782726 | J62: =J39 -> 0.56545124
B64: Intrinsic Growth | G64: =G61*G62 -> 0.00023006796 | H64: =H61*H62 -> -0.092438404 | I64: =I61*I62 -> -0.15984367 | J64: =J61*J62 -> 0.029287825
H66: 4 Year Average | J66: =AVERAGE(G64:J64) -> -0.055691045
H67: 4 Year Median | J67: =MEDIAN(G64:J64) -> -0.046104168

Sheet DCF
B2: Calculation of PV of FCFF | F2: ='Data Sheet'!K16 -> 45747 | G2: =F2+365 -> 46112 | H2: =G2+365 -> 46477 | I2: =H2+366 -> 46843 | J2: =I2+365 -> 47208 | K2: =J2+365 -> 47573
B4: EBIT | F4: =IFERROR('Historical FS'!L25,0) -> 24193.13 | G4: =F4*(1+$E$14) -> 25730.179 | H4: =G4*(1+$E$14) -> 27364.88 | I4: =H4*(1+$E$14) -> 29103.438 | J4: =I4*(1+$E$14) -> 30952.451 | K4: =J4*(1+$E$14) -> 32918.936
B5: Tax Rate | F5: ='Peer Comps'!J12 -> 0.278127 | G5: =F5 -> 0.278127 | H5: =G5 -> 0.278127 | I5: =H5 -> 0.278127 | J5: =I5 -> 0.278127 | K5: =J5 -> 0.278127
B6: EBIT(1-T) | F6: =F4*(1-F5) -> 17464.367 | G6: =G4*(1-G5) -> 18573.921 | H6: =H4*(1-H5) -> 19753.968 | I6: =I4*(1-I5) -> 21008.986 | J6: =J4*(1-J5) -> 22343.739 | K6: =K4*(1-K5) -> 23763.291
B7: Less:Reinvestment Rate | F7: ='Intrinsic Growth'!J53 -> 0.051795493 | G7: =F7+(($L$7-$F$7)/5) -> 0.065436394 | H7: =G7+(($L$7-$F$7)/5) -> 0.079077296 | I7: =H7+(($L$7-$F$7)/5) -> 0.092718197 | J7: =I7+(($L$7-$F$7)/5) -> 0.1063591 | K7: =J7+(($L$7-$F$7)/5) -> 0.12 | L7: 0.12
B8: Free Cash Flow to Firm (FCFF) | F8: =F6*(1-F7) -> 16559.792 | G8: =G6*(1-G7) -> 17358.511 | H8: =H6*(1-H7) -> 18191.878 | I8: =I6*(1-I7) -> 19061.071 | J8: =J6*(1-J7) -> 19967.279 | K8: =K6*(1-K7) -> 20911.696
B9: Mid year convention | G9: 0.5 | H9: =G9+1 -> 1.5 | I9: =H9+1 -> 2.5 | J9: =I9+1 -> 3.5 | K9: =J9+1 -> 4.5
B10: Discounting Factor | G10: =1/(1+$E$16)^G9 -> 0.94301588 | H10: =1/(1+$E$16)^H9 -> 0.83860418 | I10: =1/(1+$E$16)^I9 -> 0.74575305 | J10: =1/(1+$E$16)^J9 -> 0.6631825 | K10: =1/(1+$E$16)^K9 -> 0.58975424
B12: PV of FCFF | G12: =G8*G10 -> 16369.352 | H12: =H8*H10 -> 15255.785 | I12: =I8*I10 -> 14214.852 | J12: =J8*J10 -> 13241.95 | K12: =K8*K10 -> 12332.762
B14: Expected Growth | E14: =Growth_assumptions!G20 -> 0.063532454
B15: Terminal Growth | E15: =Growth_assumptions!G30 -> 0.037373738
B16: WACC | E16: =WACC!J44 -> 0.12450654
B18: Calculation of Terminal Value | G18: Senstivity Analysis
G19: =E37 -> 177.16029 | H19: 0.11 | I19: 0.1245 | J19: 0.13 | K19: 0.14
B20: FCFF( | E20: =K8*(1+E15) -> 21693.245 | G20: 0.02 | H20: 180.02155 | I20: 156.05134 | J20: 148.61439 | K20: 136.84172
B21: WACC | E21: =E16 -> 0.12450654 | G21: 0.0374 | H21: 210.86738 | I21: 177.21123 | J21: 167.20217 | K21: 151.75284
B22: Terminal Growth Rate | E22: =E15 -> 0.037373738 | G22: 0.05 | H22: 244.37232 | I22: 198.70411 | J22: 185.70984 | K22: 166.14979
G23: 0.06 | H23: 282.98278 | I23: 221.73881 | J23: 205.14079 | K23: 180.80382
B24: Terminal Value | E24: =E20/(E21-E22) -> 248967.61 | G24: 0.07 | H24: 340.89847 | I24: 253.22661 | J24: 231.04873 | K24: 199.64472
B26: Calculation of Equity Value Per Share
B28: PV of FCFF | E28: =SUM(G12:K12) -> 71414.7
B29: PV of Terminal Value | E29: =E24*K10 -> 146829.71
B30: Value of Operating Asset | E30: =SUM(E28:E29) -> 218244.41
B32: Add:Cash | E32: ='Raw FS'!N39 -> 4012
B33: Less:Debt | E33: =SUM('Raw FS'!N9,'Raw FS'!N10) -> 284
B34: Value of Equity | E34: =E30+E32-E33 -> 221972.41
B35: No of Shares | E35: ='Data Sheet'!B6 -> 1252.9468
B37: Equity Value Per Share | E37: =E34/E35 -> 177.16029
B39: Share Price | E39: ='Data Sheet'!B8 -> 308.4
B40: Discount/Premium | E40: =E39/E37 -> 1.7407965

Sheet Football Field Analysis
L2: Football Field Analysis - Data Table
M3: Open Low | N3: Low | O3: Open High | P3: High
L4: Comps | M4: ='Relative Valuation'!$N$33 -> 444.12647 | N4: ='Relative Valuation'!$N$33 -> 444.12647 | O4: ='Relative Valuation'!$P$33 -> 769.46141 | P4: ='Relative Valuation'!$P$33 -> 769.46141
L5: DCF Bear | M5: =DCF!$K$20 -> 136.84172 | N5: =DCF!$K$20 -> 136.84172 | O5: =DCF!$K$24 -> 199.64472 | P5: =DCF!$K$24 -> 199.64472
L6: DCF Base | M6: =DCF!$I$20 -> 156.05134 | N6: =DCF!$I$20 -> 156.05134 | O6: =DCF!$I$24 -> 253.22661 | P6: =DCF!$I$24 -> 253.22661
L7: DCF Bull | M7: =DCF!$H$20 -> 180.02155 | N7: =DCF!$H$20 -> 180.02155 | O7: =DCF!$H$24 -> 340.89847 | P7: =DCF!$H$24 -> 340.89847
L8: 52W H/L | M8: 287 | N8: 287 | O8: 444.2 | P8: 444.2

Sheet Relative Valuation
B2: Amount in Crores
B3: Comparable Companies Valuation
D5: Market Data | J5: Financials | N5: Valuation
B6: Company | C6: Ticker | D6: Share Price | E6: Shares Outstanding | F6: Equity Value | G6: Net Debt | H6: Enterprise Value | J6: Revenue | K6: EBITDA | L6: Net Income | N6: EV/ Revenue | O6: EV/ EBITDA | P6: P/E
B8: ='RV Data'!C3 -> ITC | C8: ='RV Data'!D3 -> ITC | D8: =IFERROR('RV Data'!E3,0) -> 305 | E8: =IFERROR('RV Data'!F3,0) -> 1252.95 | F8: =E8*D8 -> 382149.75 | G8: =IFERROR('RV Data'!H3,0) -> -3649.39 | H8: =F8+G8 -> 378500.36 | J8: =IFERROR('RV Data'!L3,0) -> 75323.34 | K8: =IFERROR('RV Data'!M3,0) -> 28612.68 | L8: =IFERROR('RV Data'!N3,0) -> 17257.6 | N8: =$H8/J8 -> 5.0250077 | O8: =$H8/K8 -> 13.228413 | P8: =F8/L8 -> 22.143853
B9: ='RV Data'!C4 -> Hind. Unilever | C9: ='RV Data'!D4 -> HINDUNILVR | D9: =IFERROR('RV Data'!E4,0) -> 2231.5 | E9: =IFERROR('RV Data'!F4,0) -> 234.96 | F9: =E9*D9 -> 524313.24 | G9: =IFERROR('RV Data'!H4,0) -> -5779 | H9: =F9+G9 -> 518534.24 | J9: =IFERROR('RV Data'!L4,0) -> 64544 | K9: =IFERROR('RV Data'!M4,0) -> 16265 | L9: =IFERROR('RV Data'!N4,0) -> 14540 | N9: =$H9/J9 -> 8.0338101 | O9: =$H9/K9 -> 31.880371 | P9: =F9/L9 -> 36.060058
B10: ='RV Data'!C5 -> Nestle India | C10: ='RV Data'!D5 -> NESTLEIND | D10: =IFERROR('RV Data'!E5,0) -> 1286.4 | E10: =IFERROR('RV Data'!F5,0) -> 192.83 | F10: =E10*D10 -> 248056.51 | G10: =IFERROR('RV Data'!H5,0) -> 381.2 | H10: =F10+G10 -> 248437.71 | J10: =IFERROR('RV Data'!L5,0) -> 21910.69 | K10: =IFERROR('RV Data'!M5,0) -> 6005.29 | L10: =IFERROR('RV Data'!N5,0) -> 3315.9 | N10: =$H10/J10 -> 11.338653 | O10: =$H10/K10 -> 41.369811 | P10: =F10/L10 -> 74.8082
B11: ='RV Data'!C6 -> Varun Beverages | C11: ='RV Data'!D6 -> VBL | D11: =IFERROR('RV Data'!E6,0) -> 466.55 | E11: =IFERROR('RV Data'!F6,0) -> 338.21 | F11: =E11*D11 -> 157791.88 | G11: =IFERROR('RV Data'!H6,0) -> 509.69 | H11: =F11+G11 -> 158301.57 | J11: =IFERROR('RV Data'!L6,0) -> 21685.37 | K11: =IFERROR('RV Data'!M6,0) -> 6605.66 | L11: =IFERROR('RV Data'!N6,0) -> 3062.04 | N11: =$H11/J11 -> 7.2999246 | O11: =$H11/K11 -> 23.964534 | P11: =F11/L11 -> 51.531618
B12: ='RV Data'!C7 -> Britannia Inds. | C12: ='RV Data'!D7 -> BRITANNIA | D12: =IFERROR('RV Data'!E7,0) -> 5700 | E12: =IFERROR('RV Data'!F7,0) -> 24.09 | F12: =E12*D12 -> 137313 | G12: =IFERROR('RV Data'!H7,0) -> 1883.82 | H12: =F12+G12 -> 139196.82 | J12: =IFERROR('RV Data'!L7,0) -> 18864.86 | K12: =IFERROR('RV Data'!M7,0) -> 3813.85 | L12: =IFERROR('RV Data'!N7,0) -> 2416.46 | N12: =$H12/J12 -> 7.3786299 | O12: =$H12/K12 -> 36.497718 | P12: =F12/L12 -> 56.824032
B13: ='RV Data'!C8 -> Godrej Consumer | C13: ='RV Data'!D8 -> GODREJCP | D13: =IFERROR('RV Data'!E8,0) -> 1104.8 | E13: =IFERROR('RV Data'!F8,0) -> 102.32 | F13: =E13*D13 -> 113043.14 | G13: =IFERROR('RV Data'!H8,0) -> 3630.43 | H13: =F13+G13 -> 116673.57 | J13: =IFERROR('RV Data'!L8,0) -> 15184.02 | K13: =IFERROR('RV Data'!M8,0) -> 3331.5 | L13: =IFERROR('RV Data'!N8,0) -> 1821.6 | N13: =$H13/J13 -> 7.6839708 | O13: =$H13/K13 -> 35.021332 | P13: =F13/L13 -> 62.057058
B14: ='RV Data'!C9 -> Tata Consumer | C14: ='RV Data'!D9 -> TATACONSUM | D14: =IFERROR('RV Data'!E9,0) -> 1120.4 | E14: =IFERROR('RV Data'!F9,0) -> 98.96 | F14: =E14*D14 -> 110874.78 | G14: =IFERROR('RV Data'!H9,0) -> -241.75 | H14: =F14+G14 -> 110633.03 | J14: =IFERROR('RV Data'!L9,0) -> 19465.03 | K14: =IFERROR('RV Data'!M9,0) -> 3234.93 | L14: =IFERROR('RV Data'!N9,0) -> 1471.5 | N14: =$H14/J14 -> 5.6836817 | O14: =$H14/K14 -> 34.199514 | P14: =F14/L14 -> 75.348137
B15: ='RV Data'!C10 -> Marico | C15: ='RV Data'!D10 -> MARICO | D15: =IFERROR('RV Data'!E10,0) -> 760.7 | E15: =IFERROR('RV Data'!F10,0) -> 129.81 | F15: =E15*D15 -> 98746.467 | G15: =IFERROR('RV Data'!H10,0) -> -202 | H15: =F15+G15 -> 98544.467 | J15: =IFERROR('RV Data'!L10,0) -> 13008 | K15: =IFERROR('RV Data'!M10,0) -> 2459 | L15: =IFERROR('RV Data'!N10,0) -> 1750 | N15: =$H15/J15 -> 7.5756817 | O15: =$H15/K15 -> 40.075017 | P15: =F15/L15 -> 56.426553
B16: ='RV Data'!C11 -> United Spirits | C16: ='RV Data'!D11 -> MCDOWELL-N | D16: =IFERROR('RV Data'!E11,0) -> 1307.7 | E16: =IFERROR('RV Data'!F11,0) -> 72.74 | F16: =E16*D16 -> 95122.098 | G16: =IFERROR('RV Data'!H11,0) -> -1618 | H16: =F16+G16 -> 93504.098 | J16: =IFERROR('RV Data'!L11,0) -> 12919 | K16: =IFERROR('RV Data'!M11,0) -> 2646 | L16: =IFERROR('RV Data'!N11,0) -> 1720 | N16: =$H16/J16 -> 7.2377195 | O16: =$H16/K16 -> 35.337906 | P16: =F16/L16 -> 55.303545
B17: ='RV Data'!C12 -> Dabur India | C17: ='RV Data'!D12 -> DABUR | D17: =IFERROR('RV Data'!E12,0) -> 441.7 | E17: =IFERROR('RV Data'!F12,0) -> 177.37 | F17: =E17*D17 -> 78344.329 | G17: =IFERROR('RV Data'!H12,0) -> 723.42 | H17: =F17+G17 -> 79067.749 | J17: =IFERROR('RV Data'!L12,0) -> 12984.69 | K17: =IFERROR('RV Data'!M12,0) -> 2879.69 | L17: =IFERROR('RV Data'!N12,0) -> 1819.42 | N17: =$H17/J17 -> 6.0893059 | O17: =$H17/K17 -> 27.457035 | P17: =F17/L17 -> 43.060057
B19: High | N19: =MAX(N8:N17) -> 11.338653 | O19: =MAX(O8:O17) -> 41.369811 | P19: =MAX(P8:P17) -> 75.348137
B20: 75th Percentile | N20: =QUARTILE(N8:N17,3) -> 7.6568985 | O20: =QUARTILE(O8:O17,3) -> 36.207765 | P20: =QUARTILE(P8:P17,3) -> 60.748801
B21: Average | N21: =AVERAGE(N8:N17) -> 7.3346385 | O21: =AVERAGE(O8:O17) -> 31.903165 | P21: =AVERAGE(P8:P17) -> 53.356311
B22: Median | N22: =MEDIAN(N8:N17) -> 7.3392772 | O22: =MEDIAN(O8:O17) -> 34.610423 | P22: =MEDIAN(P8:P17) -> 55.865049
B23: 25th Percentile | N23: =QUARTILE(N8:N17,1) -> 6.3764093 | O23: =QUARTILE(O8:O17,1) -> 28.562869 | P23: =QUARTILE(P8:P17,1) -> 45.177947
B24: Low | N24: =MIN(N8:N17) -> 5.0250077 | O24: =MIN(O8:O17) -> 13.228413 | P24: =MIN(P8:P17) -> 22.143853
A26: # | B26: ITC Comparabel Valuation | N26: EV/ Revenue | O26: EV/ EBITDA | P26: P/E
B28: Implied Enterprise Value | N28: =N22*J8 -> 552818.87 | O28: =O22*K8 -> 990296.95 | P28: =P30+P29 -> 960447.28
B29: Net Debt | N29: =$G$8 -> -3649.39 | O29: =$G$8 -> -3649.39 | P29: =$G$8 -> -3649.39
B30: Implied Market Value | N30: =N28-N29 -> 556468.26 | O30: =O28-O29 -> 993946.34 | P30: =P22*L8 -> 964096.67
B31: Shares Outstanding | N31: =$E$8 -> 1252.95 | O31: =$E$8 -> 1252.95 | P31: =$E$8 -> 1252.95
B33: Implied Value per share | N33: =N30/N31 -> 444.12647 | O33: =O30/O31 -> 793.28492 | P33: =P30/P31 -> 769.46141
B35: Source: TheValuationSchool, Screener.in.
N36: =IF(N33>$D$8,"Undervalued","Overvalued") -> Undervalued | O36: =IF(O33>$D$8,"Undervalued","Overvalued") -> Undervalued | P36: =IF(P33>$D$8,"Undervalued","Overvalued") -> Undervalued

Sheet VAR HIstorical
A2: # | B2: Date | C2: Adj Close | D2: Returns | E2: Sorted Returns | F2: ="Calculation of Value at Risk"&" - "&'Data Sheet'!B1 -> Calculation of Value at Risk - ITC LTD
B3: 36220 | C3: 9.737114 | D3: =(C3-C4)/C4 -> 2.8076479 | E3: 0.16459627
B4: 35097 | C4: 2.5572517 | D4: =(C4-C5)/C5 -> -0.8435459 | E4: 0.11463642 | G4: Mean | K4: =AVERAGE(E3:E7604) -> 0.00082303972
B5: 38372 | C5: 16.34506 | D5: =(C5-C6)/C6 -> -0.58878287 | E5: 0.11161702 | G5: Std Deviation | K5: =_xlfn.STDEV.S(E3:E7604) -> 0.019893407
B6: 39951 | C6: 39.748005 | D6: =(C6-C7)/C7 -> 12.711448 | E6: 0.11126005 | G6: Min | K6: =MIN(E3:E7604) -> -0.12814318
B7: 35103 | C7: 2.8988919 | D7: =(C7-C8)/C8 -> -0.63941457 | E7: 0.10512431 | G7: Max | K7: =MAX(E3:E7604) -> 0.16459627
B8: 36676 | C8: 8.0394039 | D8: =(C8-C9)/C9 -> -0.94487487 | E8: 0.10238594 | G8: CMP | K8: 309.65
B9: 42430 | C9: 145.83919 | D9: =(C9-C10)/C10 -> 19.159993 | E9: 0.10045679
B10: 35963 | C10: 7.2340894 | D10: =(C10-C11)/C11 -> 0.16567124 | E10: 0.098662623 | G10: Percentile | H10: Confidence | I10: Var | J10: Stock Price | K10: VAR(INR)
B11: 35732 | C11: 6.2059431 | D11: =(C11-C12)/C12 -> -0.41010169 | E11: 0.097512695 | G11: 0.05 | H11: =1-G11 -> 0.95 | I11: =-_xlfn.PERCENTILE.INC($E$3:$E$7604,G11) -> 0.028278457 | J11: =$K$8*(1-I11) -> 300.89358 | K11: =$K$8-J11 -> 8.7564242
B12: 38125 | C12: 10.520361 | D12: =(C12-C13)/C13 -> 0.1526339 | E12: 0.095013486 | G12: 0.01 | H12: =1-G12 -> 0.99 | I12: =-_xlfn.PERCENTILE.INC($E$3:$E$7604,G12) -> 0.054985914 | J12: =$K$8*(1-I12) -> 292.62361 | K12: =$K$8-J12 -> 17.026388
B13: 36781 | C13: 9.1272354 | D13: =(C13-C14)/C14 -> -0.70719775 | E13: 0.090723969 | G13: 0.005 | H13: =1-G13 -> 0.995 | I13: =-_xlfn.PERCENTILE.INC($E$3:$E$7604,G13) -> 0.069878652 | J13: =$K$8*(1-I13) -> 288.01208 | K13: =$K$8-J13 -> 21.637924
B14: 39288 | C14: 31.172012 | D14: =(C14-C15)/C15 -> 0.2276458 | E14: 0.09001343
B15: 38616 | C15: 25.391699 | D15: =(C15-C16)/C16 -> -0.35776637 | E15: 0.089863162
B16: 39937 | C16: 39.536545 | D16: =(C16-C17)/C17 -> 0.36012909 | E16: 0.089825182
B17: 38877 | C17: 29.06823 | D17: =(C17-C18)/C18 -> -0.7725616 | E17: 0.08702956
B18: 43910 | C18: 127.80704 | D18: =(C18-C19)/C19 -> 2.3164284 | E18: 0.084337314
B19: 39402 | C19: 38.537556 | D19: =(C19-C20)/C20 -> -0.43863404 | E19: 0.082607881
B20: 40602 | C20: 68.649612 | D20: =(C20-C21)/C21 -> 14.027703 | E20: 0.08125384
B21: 35489 | C21: 4.5682039 | D21: =(C21-C22)/C22 -> -0.36401478 | E21: 0.080207896
B22: 36515 | C22: 7.1828775 | D22: =(C22-C23)/C23 -> -0.19888383 | E22: 0.080056204
B23: 36565 | C23: 8.9660873 | D23: =(C23-C24)/C24 -> -0.098923332 | E23: 0.080052284
B24: 36535 | C24: 9.9504156 | D24: =(C24-C25)/C25 -> 0.25424999 | E24: 0.080042635
B25: 36591 | C25: 7.9333591 | D25: =(C25-C26)/C26 -> 0.029498904 | E25: 0.08003271
... B7604: 42065 | C7604: 150.72881 | D7604: =(C7604-C7605)/C7605 -> 55.455008 | E7604: -0.12814318
B7605: 35065 | C7605: 2.6698925

Sheet VAR Monte Carlo
A2: # | B2: Date | C2: Adj Close | D2: Returns | E2: Sorted Returns | G2: Replication | H2: Simulated Return | J2: ="Calculation of Value at Risk"&" - "&'Data Sheet'!B1 -> Calculation of Value at Risk - ITC LTD
B3: 36220 | C3: 9.737114 | D3: =(C3-C4)/C4 -> 2.8076479 | E3: 0.16459627 | G3: 1 | H3: =_xlfn.NORM.INV(RAND(),N$5,N$6) -> -0.0071629974
B4: 35097 | C4: 2.5572517 | D4: =(C4-C5)/C5 -> -0.8435459 | E4: 0.11463642 | G4: 2 | H4: =_xlfn.NORM.INV(RAND(),N$5,N$6) -> -0.03157181 | J4: Historical Approach
B5: 38372 | C5: 16.34506 | D5: =(C5-C6)/C6 -> -0.58878287 | E5: 0.11161702 | G5: 3 | H5: =_xlfn.NORM.INV(RAND(),N$5,N$6) -> 0.0079238336 | J5: Mean | N5: =AVERAGE(E3:E7604) -> 0.00082303972
B6: 39951 | C6: 39.748005 | D6: =(C6-C7)/C7 -> 12.711448 | E6: 0.11126005 | G6: 4 | H6: =_xlfn.NORM.INV(RAND(),N$5,N$6) -> 0.024727917 | J6: Std Deviation | N6: =_xlfn.STDEV.S(E3:E7604) -> 0.019893407
B7: 35103 | C7: 2.8988919 | D7: =(C7-C8)/C8 -> -0.63941457 | E7: 0.10512431 | G7: 5 | H7: =_xlfn.NORM.INV(RAND(),N$5,N$6) -> 0.0093201364 | J7: Min | N7: =MIN(E3:E7604) -> -0.12814318
B8: 36676 | C8: 8.0394039 | D8: =(C8-C9)/C9 -> -0.94487487 | E8: 0.10238594 | G8: 6 | H8: =_xlfn.NORM.INV(RAND(),N$5,N$6) -> 0.028687367 | J8: Max | N8: =MAX(E3:E7604) -> 0.16459627
B9: 42430 | C9: 145.83919 | D9: =(C9-C10)/C10 -> 19.159993 | E9: 0.10045679 | G9: 7 | H9: =_xlfn.NORM.INV(RAND(),N$5,N$6) -> 0.00031593311 | J9: CMP | N9: 309.65
B10: 35963 | C10: 7.2340894 | D10: =(C10-C11)/C11 -> 0.16567124 | E10: 0.098662623 | G10: 8 | H10: =_xlfn.NORM.INV(RAND(),N$5,N$6) -> 0.0052102368
B11: 35732 | C11: 6.2059431 | D11: =(C11-C12)/C12 -> -0.41010169 | E11: 0.097512695 | G11: 9 | H11: =_xlfn.NORM.INV(RAND(),N$5,N$6) -> -0.013958038 | J11: Monte Carlo Simulation
B12: 38125 | C12: 10.520361 | D12: =(C12-C13)/C13 -> 0.1526339 | E12: 0.095013486 | G12: 10 | H12: =_xlfn.NORM.INV(RAND(),N$5,N$6) -> 0.015683966 | J12: Mean | N12: =AVERAGE(H3:H10002) -> 0.00089350402
B13: 36781 | C13: 9.1272354 | D13: =(C13-C14)/C14 -> -0.70719775 | E13: 0.090723969 | G13: 11 | H13: =_xlfn.NORM.INV(RAND(),N$5,N$6) -> 0.016846398 | J13: Std Deviation | N13: =_xlfn.STDEV.S(H3:H10002) -> 0.019743873
B14: 39288 | C14: 31.172012 | D14: =(C14-C15)/C15 -> 0.2276458 | E14: 0.09001343 | G14: 12 | H14: =_xlfn.NORM.INV(RAND(),N$5,N$6) -> 0.0080065341 | J14: Min | N14: =MIN(H3:H10002) -> -0.081261339
B15: 38616 | C15: 25.391699 | D15: =(C15-C16)/C16 -> -0.35776637 | E15: 0.089863162 | G15: 13 | H15: =_xlfn.NORM.INV(RAND(),N$5,N$6) -> -0.015258814 | J15: Max | N15: =MAX(H3:H10002) -> 0.076169529
B16: 39937 | C16: 39.536545 | D16: =(C16-C17)/C17 -> 0.36012909 | E16: 0.089825182 | G16: 14 | H16: =_xlfn.NORM.INV(RAND(),N$5,N$6) -> -0.0077924754 | J16: CMP | N16: 309.65
B17: 38877 | C17: 29.06823 | D17: =(C17-C18)/C18 -> -0.7725616 | E17: 0.08702956 | G17: 15 | H17: =_xlfn.NORM.INV(RAND(),N$5,N$6) -> 0.012382722
B18: 43910 | C18: 127.80704 | D18: =(C18-C19)/C19 -> 2.3164284 | E18: 0.084337314 | G18: 16 | H18: =_xlfn.NORM.INV(RAND(),N$5,N$6) -> -0.0038541557 | J18: Percentile | K18: Confidence | L18: Var | M18: Stock Price | N18: VAR(INR)
B19: 39402 | C19: 38.537556 | D19: =(C19-C20)/C20 -> -0.43863404 | E19: 0.082607881 | G19: 17 | H19: =_xlfn.NORM.INV(RAND(),N$5,N$6) -> 0.0016918037 | J19: 0.05 | K19: =1-J19 -> 0.95 | L19: =-_xlfn.PERCENTILE.INC($H$3:$H$10002,J19) -> 0.031328451 | M19: =$N$9*(1-L19) -> 299.94915 | N19: =$N$9-M19 -> 9.7008548
B20: 40602 | C20: 68.649612 | D20: =(C20-C21)/C21 -> 14.027703 | E20: 0.08125384 | G20: 18 | H20: =_xlfn.NORM.INV(RAND(),N$5,N$6) -> -0.016864602 | J20: 0.01 | K20: =1-J20 -> 0.99 | L20: =-_xlfn.PERCENTILE.INC($H$3:$H$10002,J20) -> 0.044886518 | M20: =$N$9*(1-L20) -> 295.75089 | N20: =$N$9-M20 -> 13.89911
B21: 35489 | C21: 4.5682039 | D21: =(C21-C22)/C22 -> -0.36401478 | E21: 0.080207896 | G21: 19 | H21: =_xlfn.NORM.INV(RAND(),N$5,N$6) -> 0.022690625 | J21: 0.005 | K21: =1-J21 -> 0.995 | L21: =-_xlfn.PERCENTILE.INC($H$3:$H$10002,J21) -> 0.049462913 | M21: =$N$9*(1-L21) -> 294.33381 | N21: =$N$9-M21 -> 15.316191
B22: 36515 | C22: 7.1828775 | D22: =(C22-C23)/C23 -> -0.19888383 | E22: 0.080056204 | G22: 20 | H22: =_xlfn.NORM.INV(RAND(),N$5,N$6) -> 0.00077075299
B23: 36565 | C23: 8.9660873 | D23: =(C23-C24)/C24 -> -0.098923332 | E23: 0.080052284 | G23: 21 | H23: =_xlfn.NORM.INV(RAND(),N$5,N$6) -> -0.021238831
B24: 36535 | C24: 9.9504156 | D24: =(C24-C25)/C25 -> 0.25424999 | E24: 0.080042635 | G24: 22 | H24: =_xlfn.NORM.INV(RAND(),N$5,N$6) -> 0.014207491
B25: 36591 | C25: 7.9333591 | D25: =(C25-C26)/C26 -> 0.029498904 | E25: 0.08003271 | G25: 23 | H25: =_xlfn.NORM.INV(RAND(),N$5,N$6) -> -0.007020769
B26: 36528 | C26: 7.7060394 | D26: =(C26-C27)/C27 -> -0.26316866 | E26: 0.080030563 | G26: 24 | H26: =_xlfn.NORM.INV(RAND(),N$5,N$6) -> 0.0034598824
B27: 36567 | C27: 10.458349 | D27: =(C27-C28)/C28 -> 0.34812466 | E27: 0.080029144 | G27: 25 | H27: =_xlfn.NORM.INV(RAND(),N$5,N$6) -> -0.014547922
B28: 36516 | C28: 7.7577019 | D28: =(C28-C29)/C29 -> 0.28583032 | E28: 0.080027027 | G28: 26 | H28: =_xlfn.NORM.INV(RAND(),N$5,N$6) -> -0.015735996
B29: 36642 | C29: 6.0332236 | D29: =(C29-C30)/C30 -> -0.42534 | E29: 0.08002317 | G29: 27 | H29: =_xlfn.NORM.INV(RAND(),N$5,N$6) -> 0.0062551663
B30: 36266 | C30: 10.498771 | D30: =(C30-C31)/C31 -> 0.25140219 | E30: 0.080021866 | G30: 28 | H30: =_xlfn.NORM.INV(RAND(),N$5,N$6) -> -0.0016821895
B31: 36159 | C31: 8.3896055 | D31: =(C31-C32)/C32 -> -0.12891274 | E31: 0.080013998 | G31: 29 | H31: =_xlfn.NORM.INV(RAND(),N$5,N$6) -> 0.0080662494
B32: 36447 | C32: 9.6311884 | D32: =(C32-C33)/C33 -> 0.045392926 | E32: 0.080009757 | G32: 30 | H32: =_xlfn.NORM.INV(RAND(),N$5,N$6) -> 0.02208824
B33: 36532 | C33: 9.2129841 | D33: =(C33-C34)/C34 -> 0.080007531 | E33: 0.080007531 | G33: 31 | H33: =_xlfn.NORM.INV(RAND(),N$5,N$6) -> 0.016917906
... B7604: 42065 | C7604: 150.72881 | D7604: =(C7604-C7605)/C7605 -> 55.455008 | E7604: -0.12814318 | G7604: 7602 | H7604: =_xlfn.NORM.INV(RAND(),N$5,N$6) -> -0.0067503142
B7605: 35065 | C7605: 2.6698925 | G7605: 7603 | H7605: =_xlfn.NORM.INV(RAND(),N$5,N$6) -> 0.010951998
G7606: 7604 | H7606: =_xlfn.NORM.INV(RAND(),N$5,N$6) -> -0.0082459508
G7607: 7605 | H7607: =_xlfn.NORM.INV(RAND(),N$5,N$6) -> 0.0056220764
G7608: 7606 | H7608: =_xlfn.NORM.INV(RAND(),N$5,N$6) -> 0.011227402
G7609: 7607 | H7609: =_xlfn.NORM.INV(RAND(),N$5,N$6) -> -0.012497044
G7610: 7608 | H7610: =_xlfn.NORM.INV(RAND(),N$5,N$6) -> -0.0020889112
G7611: 7609 | H7611: =_xlfn.NORM.INV(RAND(),N$5,N$6) -> 0.023673705
G7612: 7610 | H7612: =_xlfn.NORM.INV(RAND(),N$5,N$6) -> 0.011114009
G7613: 7611 | H7613: =_xlfn.NORM.INV(RAND(),N$5,N$6) -> -0.028866835
G7614: 7612 | H7614: =_xlfn.NORM.INV(RAND(),N$5,N$6) -> 0.011147632
G7615: 7613 | H7615: =_xlfn.NORM.INV(RAND(),N$5,N$6) -> 0.0063637743
G7616: 7614 | H7616: =_xlfn.NORM.INV(RAND(),N$5,N$6) -> -0.022018544
G7617: 7615 | H7617: =_xlfn.NORM.INV(RAND(),N$5,N$6) -> -0.0078667995
... G10002: 10000 | H10002: =_xlfn.NORM.INV(RAND(),N$5,N$6) -> -0.023387423

Sheet Segment_Data
A2: # | B2: Segment Revenue External ( Crores) | FY18 to FY25
B4: Segment | C4: =Raw_seg_data!C3 -> FY18 | D4: =Raw_seg_data!D3 -> FY19 | E4: =Raw_seg_data!E3 -> FY20 | F4: =Raw_seg_data!F3 -> FY21 | G4: =Raw_seg_data!G3 -> FY22 | H4: =Raw_seg_data!H3 -> FY23 | I4: =Raw_seg_data!I3 -> FY24 | J4: =Raw_seg_data!J3 -> FY25 | K4: CAGR
B5: FMCG Cigarettes | C5: =IFERROR(Raw_seg_data!C6,0) -> 24848.09 | D5: =IFERROR(Raw_seg_data!D6,0) -> 22913.27 | E5: =IFERROR(Raw_seg_data!E6,0) -> 23679.13 | F5: =IFERROR(Raw_seg_data!F6,0) -> 22557.32 | G5: =IFERROR(Raw_seg_data!G6,0) -> 26158.31 | H5: =IFERROR(Raw_seg_data!H6,0) -> 31267.46 | I5: =IFERROR(Raw_seg_data!I6,0) -> 33667.97 | J5: =IFERROR(Raw_seg_data!J6,0) -> 35893.57 | K5: =IFERROR((J5/C5)^(1/7)-1,0) -> 0.05394431
B6: YOY% Growth | D6: =IFERROR(D5/C5-1,0) -> -0.077865945 | E6: =IFERROR(E5/D5-1,0) -> 0.0334243 | F6: =IFERROR(F5/E5-1,0) -> -0.047375474 | G6: =IFERROR(G5/F5-1,0) -> 0.15963732 | H6: =IFERROR(H5/G5-1,0) -> 0.19531652 | I6: =IFERROR(I5/H5-1,0) -> 0.076773425 | J6: =IFERROR(J5/I5-1,0) -> 0.066104372
B7: FMCG Others | C7: =IFERROR(Raw_seg_data!C19,0) -> 11339.31 | D7: =IFERROR(Raw_seg_data!D19,0) -> 12517.07 | E7: =IFERROR(Raw_seg_data!E19,0) -> 12843.99 | F7: =IFERROR(Raw_seg_data!F19,0) -> 14737.06 | G7: =IFERROR(Raw_seg_data!G19,0) -> 15993.12 | H7: =IFERROR(Raw_seg_data!H19,0) -> 19109.33 | I7: =IFERROR(Raw_seg_data!I19,0) -> 20992.48 | J7: =IFERROR(Raw_seg_data!J19,0) -> 22005.27 | K7: =IFERROR((J7/C7)^(1/7)-1,0) -> 0.099345736
B8: YOY% Growth | D8: =IFERROR(D7/C7-1,0) -> 0.10386523 | E8: =IFERROR(E7/D7-1,0) -> 0.026117933 | F8: =IFERROR(F7/E7-1,0) -> 0.14738956 | G8: =IFERROR(G7/F7-1,0) -> 0.085231383 | H8: =IFERROR(H7/G7-1,0) -> 0.19484691 | I8: =IFERROR(I7/H7-1,0) -> 0.098546103 | J8: =IFERROR(J7/I7-1,0) -> 0.048245372
B9: Hotels | C9: =IFERROR(Raw_seg_data!C32,0) -> 1480.02 | D9: =IFERROR(Raw_seg_data!D32,0) -> 1728.15 | E9: =IFERROR(Raw_seg_data!E32,0) -> 1911.59 | F9: =IFERROR(Raw_seg_data!F32,0) -> 659.76 | G9: =IFERROR(Raw_seg_data!G32,0) -> 1341.02 | H9: =IFERROR(Raw_seg_data!H32,0) -> 2672.79 | I9: =IFERROR(Raw_seg_data!I32,0) -> 3085.49 | J9: =IFERROR(Raw_seg_data!J32,0) -> 0 | K9: N/A-Demerged
B10: YOY% Growth | D10: =IFERROR(D9/C9-1,0) -> 0.16765314 | E10: =IFERROR(E9/D9-1,0) -> 0.10614819 | F10: =IFERROR(F9/E9-1,0) -> -0.65486323 | G10: =IFERROR(G9/F9-1,0) -> 1.0325876 | H10: =IFERROR(H9/G9-1,0) -> 0.99310227 | I10: =IFERROR(I9/H9-1,0) -> 0.15440794 | J10: =IFERROR(J9/I9-1,0) -> -1
B11: Agri Business | C11: =IFERROR(Raw_seg_data!C43,0) -> 4474.22 | D11: =IFERROR(Raw_seg_data!D43,0) -> 6075.3 | E11: =IFERROR(Raw_seg_data!E43,0) -> 5912.54 | F11: =IFERROR(Raw_seg_data!F43,0) -> 8001.87 | G11: =IFERROR(Raw_seg_data!G43,0) -> 12192.01 | H11: =IFERROR(Raw_seg_data!H43,0) -> 12361.62 | I11: =IFERROR(Raw_seg_data!I43,0) -> 8523.79 | J11: =IFERROR(Raw_seg_data!J43,0) -> 12244 | K11: =IFERROR((J11/C11)^(1/7)-1,0) -> 0.15467031
B12: YOY% Growth | D12: =IFERROR(D11/C11-1,0) -> 0.35784561 | E12: =IFERROR(E11/D11-1,0) -> -0.026790447 | F12: =IFERROR(F11/E11-1,0) -> 0.35337266 | G12: =IFERROR(G11/F11-1,0) -> 0.5236451 | H12: =IFERROR(H11/G11-1,0) -> 0.01391157 | I12: =IFERROR(I11/H11-1,0) -> -0.31046335 | J12: =IFERROR(J11/I11-1,0) -> 0.43645022
B13: Paperboards Paper Pack. | C13: =IFERROR(Raw_seg_data!C56,0) -> 3695.41 | D13: =IFERROR(Raw_seg_data!D56,0) -> 4230.4 | E13: =IFERROR(Raw_seg_data!E56,0) -> 4498.98 | F13: =IFERROR(Raw_seg_data!F56,0) -> 4549.83 | G13: =IFERROR(Raw_seg_data!G56,0) -> 6203.79 | H13: =IFERROR(Raw_seg_data!H56,0) -> 7233.69 | I13: =IFERROR(Raw_seg_data!I56,0) -> 6474.74 | J13: =IFERROR(Raw_seg_data!J56,0) -> 6575.88 | K13: =IFERROR((J13/C13)^(1/7)-1,0) -> 0.08581514
B14: YOY% Growth | D14: =IFERROR(D13/C13-1,0) -> 0.14477149 | E14: =IFERROR(E13/D13-1,0) -> 0.063488086 | F14: =IFERROR(F13/E13-1,0) -> 0.011302562 | G14: =IFERROR(G13/F13-1,0) -> 0.36352127 | H14: =IFERROR(H13/G13-1,0) -> 0.16601142 | I14: =IFERROR(I13/H13-1,0) -> -0.10491879 | J14: =IFERROR(J13/I13-1,0) -> 0.015620704
B15: Others / Infotech | C15: =IFERROR(Raw_seg_data!C69,0) -> 1525.46 | D15: =IFERROR(Raw_seg_data!D69,0) -> 1884.24 | E15: =IFERROR(Raw_seg_data!E69,0) -> 2122.27 | F15: =IFERROR(Raw_seg_data!F69,0) -> 2329.31 | G15: =IFERROR(Raw_seg_data!G69,0) -> 2729.98 | H15: =IFERROR(Raw_seg_data!H69,0) -> 3181.69 | I15: =IFERROR(Raw_seg_data!I69,0) -> 3691.55 | J15: =IFERROR(Raw_seg_data!J69,0) -> 4224.04 | K15: =IFERROR((J15/C15)^(1/7)-1,0) -> 0.15661708
B16: YOY% Growth | D16: =IFERROR(D15/C15-1,0) -> 0.23519463 | E16: =IFERROR(E15/D15-1,0) -> 0.12632679 | F16: =IFERROR(F15/E15-1,0) -> 0.097555919 | G16: =IFERROR(G15/F15-1,0) -> 0.17201231 | H16: =IFERROR(H15/G15-1,0) -> 0.16546275 | I16: =IFERROR(I15/H15-1,0) -> 0.16024817 | J16: =IFERROR(J15/I15-1,0) -> 0.14424564
A19: # | B19: Segment EBIT (Crores) | FY18 to FY25
B21: Segment | C21: =Raw_seg_data!C3 -> FY18 | D21: =Raw_seg_data!D3 -> FY19 | E21: =Raw_seg_data!E3 -> FY20 | F21: =Raw_seg_data!F3 -> FY21 | G21: =Raw_seg_data!G3 -> FY22 | H21: =Raw_seg_data!H3 -> FY23 | I21: =Raw_seg_data!I3 -> FY24 | J21: =Raw_seg_data!J3 -> FY25 | K21: CAGR
B22: FMCG Cigarettes | C22: =IFERROR(Raw_seg_data!C7,0) -> 14128.12 | D22: =IFERROR(Raw_seg_data!D7,0) -> 15411.77 | E22: =IFERROR(Raw_seg_data!E7,0) -> 15838.46 | F22: =IFERROR(Raw_seg_data!F7,0) -> 13498.36 | G22: =IFERROR(Raw_seg_data!G7,0) -> 15768.45 | H22: =IFERROR(Raw_seg_data!H7,0) -> 18882.59 | I22: =IFERROR(Raw_seg_data!I7,0) -> 20071.04 | J22: =IFERROR(Raw_seg_data!J7,0) -> 21091.35 | K22: =IFERROR((J22/C22)^(1/7)-1,0) -> 0.058912318
B23: YOY% Growth | D23: =IFERROR(D22/C22-1,0) -> 0.090857807 | E23: =IFERROR(E22/D22-1,0) -> 0.027685983 | F23: =IFERROR(F22/E22-1,0) -> -0.14774795 | G23: =IFERROR(G22/F22-1,0) -> 0.16817524 | H23: =IFERROR(H22/G22-1,0) -> 0.19749183 | I23: =IFERROR(I22/H22-1,0) -> 0.062938929 | J23: =IFERROR(J22/I22-1,0) -> 0.050834934
B24: EBIT Margin% | C24: =IFERROR(C22/C5,0) -> 0.56857972 | D24: =IFERROR(D22/D5,0) -> 0.67261329 | E24: =IFERROR(E22/E5,0) -> 0.66887846 | F24: =IFERROR(F22/F5,0) -> 0.59840265 | G24: =IFERROR(G22/G5,0) -> 0.60280844 | H24: =IFERROR(H22/H5,0) -> 0.60390547 | I24: =IFERROR(I22/I5,0) -> 0.59614643 | J24: =IFERROR(J22/J5,0) -> 0.58760803
B25: FMCG Others | C25: =IFERROR(Raw_seg_data!C20,0) -> 170.46 | D25: =IFERROR(Raw_seg_data!D20,0) -> 325.55 | E25: =IFERROR(Raw_seg_data!E20,0) -> 424.94 | F25: =IFERROR(Raw_seg_data!F20,0) -> 837.99 | G25: =IFERROR(Raw_seg_data!G20,0) -> 934.93 | H25: =IFERROR(Raw_seg_data!H20,0) -> 1386.49 | I25: =IFERROR(Raw_seg_data!I20,0) -> 1789.91 | J25: =IFERROR(Raw_seg_data!J20,0) -> 1590.23 | K25: =IFERROR((J25/C25)^(1/7)-1,0) -> 0.37577752
B26: YOY% Growth | D26: =IFERROR(D25/C25-1,0) -> 0.90983222 | E26: =IFERROR(E25/D25-1,0) -> 0.30529873 | F26: =IFERROR(F25/E25-1,0) -> 0.97201958 | G26: =IFERROR(G25/F25-1,0) -> 0.11568157 | H26: =IFERROR(H25/G25-1,0) -> 0.48298803 | I26: =IFERROR(I25/H25-1,0) -> 0.29096495 | J26: =IFERROR(J25/I25-1,0) -> -0.11155868
B27: EBIT Margin% | C27: =IFERROR(C25/C7,0) -> 0.015032661 | D27: =IFERROR(D25/D7,0) -> 0.026008483 | E27: =IFERROR(E25/E7,0) -> 0.033084735 | F27: =IFERROR(F25/F7,0) -> 0.056862766 | G27: =IFERROR(G25/G7,0) -> 0.058458262 | H27: =IFERROR(H25/H7,0) -> 0.072555657 | I27: =IFERROR(I25/I7,0) -> 0.085264342 | J27: =IFERROR(J25/J7,0) -> 0.072265871
B28: Hotels | C28: =IFERROR(Raw_seg_data!C33,0) -> 145 | D28: =IFERROR(Raw_seg_data!D33,0) -> 185.69 | E28: =IFERROR(Raw_seg_data!E33,0) -> 154 | F28: =IFERROR(Raw_seg_data!F33,0) -> -563.87 | G28: =IFERROR(Raw_seg_data!G33,0) -> 185.23 | H28: =IFERROR(Raw_seg_data!H33,0) -> 557.31 | I28: =IFERROR(Raw_seg_data!I33,0) -> 764.94 | J28: =IFERROR(Raw_seg_data!J33,0) -> 0 | K28: N/A-Demerged
B29: YOY% Growth | D29: =IFERROR(D28/C28-1,0) -> 0.28062069 | E29: =IFERROR(E28/D28-1,0) -> -0.17066078 | F29: =IFERROR(F28/E28-1,0) -> -4.6614935 | G29: =IFERROR(G28/F28-1,0) -> -1.3284977 | H29: =IFERROR(H28/G28-1,0) -> 2.0087459 | I29: =IFERROR(I28/H28-1,0) -> 0.37255746 | J29: =IFERROR(J28/I28-1,0) -> -1
B30: EBIT Margin% | C30: =IFERROR(C28/C11,0) -> 0.032407883 | D30: =IFERROR(D28/D11,0) -> 0.030564746 | E30: =IFERROR(E28/E11,0) -> 0.026046335 | F30: =IFERROR(F28/F11,0) -> -0.070467278 | G30: =IFERROR(G28/G11,0) -> 0.015192737 | H30: =IFERROR(H28/H11,0) -> 0.045083897 | I30: =IFERROR(I28/I11,0) -> 0.08974177 | J30: =IFERROR(J28/J11,0) -> 0
B31: Agri Business | C31: =IFERROR(Raw_seg_data!C44,0) -> 841.49 | D31: =IFERROR(Raw_seg_data!D44,0) -> 793.38 | E31: =IFERROR(Raw_seg_data!E44,0) -> 829.74 | F31: =IFERROR(Raw_seg_data!F44,0) -> 918.24 | G31: =IFERROR(Raw_seg_data!G44,0) -> 1086.22 | H31: =IFERROR(Raw_seg_data!H44,0) -> 1380.21 | I31: =IFERROR(Raw_seg_data!I44,0) -> 1278.33 | J31: =IFERROR(Raw_seg_data!J44,0) -> 1540.3 | K31: =IFERROR((J31/C31)^(1/7)-1,0) -> 0.090204702
B32: YOY% Growth | D32: =IFERROR(D31/C31-1,0) -> -0.057172397 | E32: =IFERROR(E31/D31-1,0) -> 0.045829237 | F32: =IFERROR(F31/E31-1,0) -> 0.10665992 | G32: =IFERROR(G31/F31-1,0) -> 0.18293692 | H32: =IFERROR(H31/G31-1,0) -> 0.2706542 | I32: =IFERROR(I31/H31-1,0) -> -0.073814854 | J32: =IFERROR(J31/I31-1,0) -> 0.20493143
B33: EBIT Margin% | C33: =IFERROR(C31/C11,0) -> 0.18807524 | D33: =IFERROR(D31/D11,0) -> 0.13059108 | E33: =IFERROR(E31/E11,0) -> 0.14033563 | F33: =IFERROR(F31/F11,0) -> 0.11475318 | G33: =IFERROR(G31/G11,0) -> 0.089092775 | H33: =IFERROR(H31/H11,0) -> 0.11165284 | I33: =IFERROR(I31/I11,0) -> 0.14997202 | J33: =IFERROR(J31/J11,0) -> 0.12580039
B34: Paperboards Paper Pack. | C34: =IFERROR(Raw_seg_data!C57,0) -> 1042.16 | D34: =IFERROR(Raw_seg_data!D57,0) -> 1239.23 | E34: =IFERROR(Raw_seg_data!E57,0) -> 1305.33 | F34: =IFERROR(Raw_seg_data!F57,0) -> 1098.68 | G34: =IFERROR(Raw_seg_data!G57,0) -> 1700 | H34: =IFERROR(Raw_seg_data!H57,0) -> 2293.95 | I34: =IFERROR(Raw_seg_data!I57,0) -> 1372.34 | J34: =IFERROR(Raw_seg_data!J57,0) -> 883.11 | K34: =IFERROR((J34/C34)^(1/7)-1,0) -> -0.023379645
B35: YOY% Growth | D35: =IFERROR(D34/C34-1,0) -> 0.18909764 | E35: =IFERROR(E34/D34-1,0) -> 0.053339574 | F35: =IFERROR(F34/E34-1,0) -> -0.15831246 | G35: =IFERROR(G34/F34-1,0) -> 0.54731132 | H35: =IFERROR(H34/G34-1,0) -> 0.34938235 | I35: =IFERROR(I34/H34-1,0) -> -0.4017568 | J35: =IFERROR(J34/I34-1,0) -> -0.35649329
B36: EBIT Margin% | C36: =IFERROR(C34/C13,0) -> 0.28201472 | D36: =IFERROR(D34/D13,0) -> 0.29293447 | E36: =IFERROR(E34/E13,0) -> 0.2901391 | F36: =IFERROR(F34/F13,0) -> 0.24147715 | G36: =IFERROR(G34/G13,0) -> 0.27402604 | H36: =IFERROR(H34/H13,0) -> 0.31712031 | I36: =IFERROR(I34/I13,0) -> 0.21195291 | J36: =IFERROR(J34/J13,0) -> 0.13429533
B37: Others / Infotech | C37: =IFERROR(Raw_seg_data!C70,0) -> 126.81 | D37: =IFERROR(Raw_seg_data!D70,0) -> 172.45 | E37: =IFERROR(Raw_seg_data!E70,0) -> 290.95 | F37: =IFERROR(Raw_seg_data!F70,0) -> 558.69 | G37: =IFERROR(Raw_seg_data!G70,0) -> 723.73 | H37: =IFERROR(Raw_seg_data!H70,0) -> 534.62 | I37: =IFERROR(Raw_seg_data!I70,0) -> 642.7 | J37: =IFERROR(Raw_seg_data!J70,0) -> 670.73 | K37: =IFERROR((J37/C37)^(1/7)-1,0) -> 0.26865061
B38: YOY% Growth | D38: =IFERROR(D37/C37-1,0) -> 0.35990852 | E38: =IFERROR(E37/D37-1,0) -> 0.6871557 | F38: =IFERROR(F37/E37-1,0) -> 0.92022684 | G38: =IFERROR(G37/F37-1,0) -> 0.29540532 | H38: =IFERROR(H37/G37-1,0) -> -0.2612991 | I38: =IFERROR(I37/H37-1,0) -> 0.20216228 | J38: =IFERROR(J37/I37-1,0) -> 0.043612883
B39: EBIT Margin% | C39: =IFERROR(C37/C15,0) -> 0.083129023 | D39: =IFERROR(D37/D15,0) -> 0.091522311 | E39: =IFERROR(E37/E15,0) -> 0.13709377 | F39: =IFERROR(F37/F15,0) -> 0.23985215 | G39: =IFERROR(G37/G15,0) -> 0.26510451 | H39: =IFERROR(H37/H15,0) -> 0.1680302 | I39: =IFERROR(I37/I15,0) -> 0.17410031 | J39: =IFERROR(J37/J15,0) -> 0.15878874

Sheet Segment_valuation
B2: Implied Enterprise Value Per Segment
B4: Segment | C4: Base Used | D4: Metric | E4: FY25 Value (Rs.Cr.) | F4: Multiple | G4: Implied EV (Rs.Cr.) | H4: Weight X
B6: =Raw_seg_data!B5 -> FMCG Ciggarettes | C6: EBIT | D6: =Peer_data!$E$2 -> EV/EBIT | E6: =IFERROR(Raw_seg_data!J7,0) -> 21091.35 | F6: =IFERROR(Peer_data!E9,0) -> 16.255 | G6: =E6*F6 -> 342839.89 | H6: =G6/$G$12 -> 0.73283301
B7: =Raw_seg_data!B18 -> FMCG Others | C7: EBIT | D7: =Peer_data!$E$2 -> EV/EBIT | E7: =IFERROR(Raw_seg_data!J20,0) -> 1590.23 | F7: =IFERROR(Peer_data!E19,0) -> 37.84 | G7: =E7*F7 -> 60174.303 | H7: =G7/$G$12 -> 0.12862481
B8: =Raw_seg_data!B31 -> Hotel | C8: Stake 1 | D8: 40% Mkt Cap | E8: 33469 | F8: 0.4 | G8: =E8*F8 -> 13387.6 | H8: =G8/$G$12 -> 0.028616492
B9: =Raw_seg_data!B42 -> Agri Business | C9: EBIT | D9: =Peer_data!$E$2 -> EV/EBIT | E9: =IFERROR(Raw_seg_data!J44,0) -> 1540.3 | F9: =IFERROR(Peer_data!E29,0) -> 19.15 | G9: =E9*F9 -> 29496.745 | H9: =G9/$G$12 -> 0.063050388
B10: =Raw_seg_data!B55 -> Paperboards Paper Pack. | C10: EBIT | D10: =Peer_data!$E$2 -> EV/EBIT | E10: =IFERROR(Raw_seg_data!J57,0) -> 883.11 | F10: =IFERROR(Peer_data!E38,0) -> 11.875 | G10: =E10*F10 -> 10486.931 | H10: =G10/$G$12 -> 0.022416205
B11: =Raw_seg_data!B68 -> Others/Infotech | C11: EBIT | D11: =Peer_data!$E$2 -> EV/EBIT | E11: =IFERROR(Raw_seg_data!J70,0) -> 670.73 | F11: =IFERROR(Peer_data!E47,0) -> 17.06 | G11: =E11*F11 -> 11442.654 | H11: =G11/$G$12 -> 0.024459098
F12: Total EV | G12: =SUM(G6:G11) -> 467828.13 | H12: =G12/$G$12 -> 1
B14: Enterprise Value to Equity Value Per Share
B16: Total Segment Enterprise Value | G16: =G12 -> 467828.13
B18: Corporate Unallocated Costs 2 | G18: 1300
B20: Adjusted Total Enterprise Value | G20: =G16-G18 -> 466528.13
B22: Total Debt | G22: =IFERROR('Data Sheet'!K59,0) -> 284.54
B23: Cash and Cash Equivalents | G23: =IFERROR('Data Sheet'!K69,0) -> 4012.36
B25: Equity Value | G25: =G20+G23-G22 -> 470255.95
B26: / Shares Outstanding | G26: ='Data Sheet'!B6 -> 1252.9468
B28: Value Per Share (Rs.) | G28: =G25/G26 -> 375.31998
B31: Notes:
B32: 1. ITC's Stake in ITC Hotels taken from the screener.com
B33: 2.Corporate Unallocated cost took from the annual FS FY25

Sheet DU Point Analysis
B2: ITC LTD.
B3: =CONCATENATE(" ( ",VLOOKUP(B2,'List of Stocks'!B2:D5442,3,TRUE)," | ","BSE Code: ",VLOOKUP('DU Point Analysis'!B2,'List of Stocks'!B2:D5442,2,TRUE)," )") -> ( ITC | BSE Code: 500875 )
B4: =CONCATENATE(" INR ",'Data Sheet'!B8) -> INR 308.4
B5: 52 Week ( High-INR-444.20 & Low-INR-287 )
B7: About the Company
B8: ITC Limited is an Indian conglomerate, headquartered in Kolkata.It has a presence across six business segments, namely FMCG, agribusiness, information technology, paper products, and packaging.It generates a plurality of its revenue from tobacco products.In terms of market capitalization, ITC is the second-largest FMCG company in India and the third-largest tobacco company in the world.
B13: Financial Summary
B56: Return on Equity
C57: ='Historical FS'!F3 -> 43555 | D57: ='Historical FS'!G3 -> 43921 | E57: ='Historical FS'!H3 -> 44286 | F57: ='Historical FS'!I3 -> 44651 | G57: ='Historical FS'!J3 -> 45016 | H57: ='Historical FS'!K3 -> 45382 | I57: ='Historical FS'!L3 -> 45747
B58: Net Profit | C58: ='Data Sheet'!E30 -> 12592.33 | D58: ='Data Sheet'!F30 -> 15306.23 | E58: ='Data Sheet'!G30 -> 13161.19 | F58: ='Data Sheet'!H30 -> 15242.66 | G58: ='Data Sheet'!I30 -> 19191.66 | H58: ='Data Sheet'!J30 -> 20458.78 | I58: ='Data Sheet'!K30 -> 34746.63
B59: Average Shareholders Equity | C59: =(('Data Sheet'!E57+'Data Sheet'!E58)+('Data Sheet'!D57+'Data Sheet'!D58)/2) -> 85395.925 | D59: =(('Data Sheet'!F57+'Data Sheet'!F58)+('Data Sheet'!E57+'Data Sheet'!E58)/2) -> 94843.695 | E59: =(('Data Sheet'!G57+'Data Sheet'!G58)+('Data Sheet'!F57+'Data Sheet'!F58)/2) -> 92983.97 | F59: =(('Data Sheet'!H57+'Data Sheet'!H58)+('Data Sheet'!G57+'Data Sheet'!G58)/2) -> 92629.24 | G59: =(('Data Sheet'!I57+'Data Sheet'!I58)+('Data Sheet'!H57+'Data Sheet'!H58)/2) -> 100383.05 | H59: =(('Data Sheet'!J57+'Data Sheet'!J58)+('Data Sheet'!I57+'Data Sheet'!I58)/2) -> 109084.63 | I59: =(('Data Sheet'!K57+'Data Sheet'!K58)+('Data Sheet'!J57+'Data Sheet'!J58)/2) -> 107283.55
B60: Return on Equity | C60: =C58/C59 -> 0.14745821 | D60: =D58/D59 -> 0.16138374 | E60: =E58/E59 -> 0.14154257 | F60: =F58/F59 -> 0.1645556 | G60: =G58/G59 -> 0.19118428 | H60: =H58/H59 -> 0.18754961 | I60: =I58/I59 -> 0.32387659
B62: ROE- DU Pont Equation
C63: =C57 -> 43555 | D63: =D57 -> 43921 | E63: =E57 -> 44286 | F63: =F57 -> 44651 | G63: =G57 -> 45016 | H63: =H57 -> 45382 | I63: =I57 -> 45747
B64: Net Profit | C64: =C58 -> 12592.33 | D64: =D58 -> 15306.23 | E64: =E58 -> 13161.19 | F64: =F58 -> 15242.66 | G64: =G58 -> 19191.66 | H64: =H58 -> 20458.78 | I64: =I58 -> 34746.63
B65: Revenue | C65: ='Data Sheet'!E17 -> 48339.58 | D65: ='Data Sheet'!F17 -> 49387.7 | E65: ='Data Sheet'!G17 -> 49257.45 | F65: ='Data Sheet'!H17 -> 60644.54 | G65: ='Data Sheet'!I17 -> 70919.03 | H65: ='Data Sheet'!J17 -> 67931.94 | I65: ='Data Sheet'!K17 -> 75323.34
B66: Net Profit Margin (A) | C66: =C64/C65 -> 0.2604973 | D66: =D64/D65 -> 0.30991988 | E66: =E64/E65 -> 0.26719187 | F66: =F64/F65 -> 0.25134431 | G66: =G64/G65 -> 0.27061368 | H66: =H64/H65 -> 0.30116584 | I66: =I64/I65 -> 0.46129964
B68: Revenue | C68: =C65 -> 48339.58 | D68: =D65 -> 49387.7 | E68: =E65 -> 49257.45 | F68: =F65 -> 60644.54 | G68: =G65 -> 70919.03 | H68: =H65 -> 67931.94 | I68: =I65 -> 75323.34
B69: Average Total Asset | C69: =('Data Sheet'!E66+'Data Sheet'!D66)/2 -> 67989.96 | D69: =('Data Sheet'!F66+'Data Sheet'!E66)/2 -> 74524.895 | E69: =('Data Sheet'!G66+'Data Sheet'!F66)/2 -> 75535.755 | F69: =('Data Sheet'!H66+'Data Sheet'!G66)/2 -> 75478.39 | G69: =('Data Sheet'!I66+'Data Sheet'!H66)/2 -> 81513.49 | H69: =('Data Sheet'!J66+'Data Sheet'!I66)/2 -> 88792.465 | I69: =('Data Sheet'!K66+'Data Sheet'!J66)/2 -> 89878.335
B70: Asset Turnover Ratio (B) | C70: =C68/C69 -> 0.71098115 | D70: =D68/D69 -> 0.6627007 | E70: =E68/E69 -> 0.65210773 | F70: =F68/F69 -> 0.80346891 | G70: =G68/G69 -> 0.87002814 | H70: =H68/H69 -> 0.76506424 | I70: =I68/I69 -> 0.83805892
B72: Average Total Asset | C72: =C69 -> 67989.96 | D72: =D69 -> 74524.895 | E72: =E69 -> 75535.755 | F72: =F69 -> 75478.39 | G72: =G69 -> 81513.49 | H72: =H69 -> 88792.465 | I72: =I69 -> 89878.335
B73: Average Shareholders Equity | C73: =C59 -> 85395.925 | D73: =D59 -> 94843.695 | E73: =E59 -> 92983.97 | F73: =F59 -> 92629.24 | G73: =G59 -> 100383.05 | H73: =H59 -> 109084.63 | I73: =I59 -> 107283.55
B74: =CONCATENATE("Equity Multiplier"," (","C",")") -> Equity Multiplier (C) | C74: =C72/C73 -> 0.79617335 | D74: =D72/D73 -> 0.78576541 | E74: =E72/E73 -> 0.81235244 | F74: =F72/F73 -> 0.8148441 | G74: =G72/G73 -> 0.81202448 | H74: =H72/H73 -> 0.81397778 | I74: =I72/I73 -> 0.83776436
B76: Return on Equity (A*B*C) | C76: =C66*C70*C74 -> 0.14745821 | D76: =D66*D70*D74 -> 0.16138374 | E76: =E66*E70*E74 -> 0.14154257 | F76: =F66*F70*F74 -> 0.1645556 | G76: =G66*G70*G74 -> 0.19118428 | H76: =H66*H70*H74 -> 0.18754961 | I76: =I66*I70*I74 -> 0.32387659
B78: Return on Asset
C79: =C63 -> 43555 | D79: =D63 -> 43921 | E79: =E63 -> 44286 | F79: =F63 -> 44651 | G79: =G63 -> 45016 | H79: =H63 -> 45382 | I79: =I63 -> 45747
B80: Net Profit | C80: =C64 -> 12592.33 | D80: =D64 -> 15306.23 | E80: =E64 -> 13161.19 | F80: =F64 -> 15242.66 | G80: =G64 -> 19191.66 | H80: =H64 -> 20458.78 | I80: =I64 -> 34746.63
B81: Average Total Asset | C81: =C69 -> 67989.96 | D81: =D69 -> 74524.895 | E81: =E69 -> 75535.755 | F81: =F69 -> 75478.39 | G81: =G69 -> 81513.49 | H81: =H69 -> 88792.465 | I81: =I69 -> 89878.335
B82: Return on Asset | C82: =C80/C81 -> 0.18520867 | D82: =D80/D81 -> 0.20538412 | E82: =E80/E81 -> 0.17423788 | F82: =F80/F81 -> 0.20194734 | G82: =G80/G81 -> 0.23544152 | H82: =H80/H81 -> 0.23041122 | I82: =I80/I81 -> 0.38659628
B84: ROA- DU Pont Equation
C85: =C79 -> 43555 | D85: =D79 -> 43921 | E85: =E79 -> 44286 | F85: =F79 -> 44651 | G85: =G79 -> 45016 | H85: =H79 -> 45382 | I85: =I79 -> 45747
B86: Net Profit | C86: =C80 -> 12592.33 | D86: =D80 -> 15306.23 | E86: =E80 -> 13161.19 | F86: =F80 -> 15242.66 | G86: =G80 -> 19191.66 | H86: =H80 -> 20458.78 | I86: =I80 -> 34746.63
B87: Revenue | C87: =C68 -> 48339.58 | D87: =D68 -> 49387.7 | E87: =E68 -> 49257.45 | F87: =F68 -> 60644.54 | G87: =G68 -> 70919.03 | H87: =H68 -> 67931.94 | I87: =I68 -> 75323.34
B88: Net Profit Margin (A) | C88: =C86/C87 -> 0.2604973 | D88: =D86/D87 -> 0.30991988 | E88: =E86/E87 -> 0.26719187 | F88: =F86/F87 -> 0.25134431 | G88: =G86/G87 -> 0.27061368 | H88: =H86/H87 -> 0.30116584 | I88: =I86/I87 -> 0.46129964
B90: Revenue | C90: =C87 -> 48339.58 | D90: =D87 -> 49387.7 | E90: =E87 -> 49257.45 | F90: =F87 -> 60644.54 | G90: =G87 -> 70919.03 | H90: =H87 -> 67931.94 | I90: =I87 -> 75323.34
B91: Average Total Asset | C91: =C69 -> 67989.96 | D91: =D69 -> 74524.895 | E91: =E69 -> 75535.755 | F91: =F69 -> 75478.39 | G91: =G69 -> 81513.49 | H91: =H69 -> 88792.465 | I91: =I69 -> 89878.335
B92: Asset Turnover Ratio (B) | C92: =C90/C91 -> 0.71098115 | D92: =D90/D91 -> 0.6627007 | E92: =E90/E91 -> 0.65210773 | F92: =F90/F91 -> 0.80346891 | G92: =G90/G91 -> 0.87002814 | H92: =H90/H91 -> 0.76506424 | I92: =I90/I91 -> 0.83805892
B94: Return on Asset (A*B) | C94: =C92*C88 -> 0.18520867 | D94: =D92*D88 -> 0.20538412 | E94: =E92*E88 -> 0.17423788 | F94: =F92*F88 -> 0.20194734 | G94: =G92*G88 -> 0.23544152 | H94: =H92*H88 -> 0.23041122 | I94: =I92*I88 -> 0.38659628

Sheet Altman Z Score
B2: ITC LTD.
B3: =CONCATENATE(" ( ",VLOOKUP(B2,'List of Stocks'!B2:D5442,3,TRUE)," | ","BSE Code: ",VLOOKUP('Altman Z Score'!B2,'List of Stocks'!B2:D5442,2,TRUE)," )") -> ( ITC | BSE Code: 500875 )
B4: =CONCATENATE(" INR ",'Data Sheet'!B8) -> INR 308.4
B5: 52 Week ( High-INR-444.20 & Low-INR-287 )
B7: Altman's Z Score
B8: The Altman Z-score, developed by Edward Altman in 1968, is a bankruptcy prediction model that combines five financial ratios- covering liquidity, profitability, leverage, solvency, and asset efficiency ,into a single weighted score using Multiple Discriminant Analysis. A score above 2.99 indicates financial safety, below 1.81 signals distress, and 1.81–2.99 is a grey zone, with the model proven to be approximately 72% accurate two years before bankruptcy.
B13: Financial Summary
B59: Working Capital / Total Asset
C60: ='Historical FS'!F3 -> 43555 | D60: ='Historical FS'!G3 -> 43921 | E60: ='Historical FS'!H3 -> 44286 | F60: ='Historical FS'!I3 -> 44651 | G60: ='Historical FS'!J3 -> 45016 | H60: ='Historical FS'!K3 -> 45382 | I60: ='Historical FS'!L3 -> 45747
B61: Working Capital | C61: =SUM('Raw FS'!H37:H41)-SUM('Raw FS'!H14:H16,'Raw FS'!H9:H10) -> 10942 | D61: =SUM('Raw FS'!I37:I41)-SUM('Raw FS'!I14:I16,'Raw FS'!I9:I10) -> 12024 | E61: =SUM('Raw FS'!J37:J41)-SUM('Raw FS'!J14:J16,'Raw FS'!J9:J10) -> 8519 | F61: =SUM('Raw FS'!K37:K41)-SUM('Raw FS'!K14:K16,'Raw FS'!K9:K10) -> 10528 | G61: =SUM('Raw FS'!L37:L41)-SUM('Raw FS'!L14:L16,'Raw FS'!L9:L10) -> 11273 | H61: =SUM('Raw FS'!M37:M41)-SUM('Raw FS'!M14:M16,'Raw FS'!M9:M10) -> 13096 | I61: =SUM('Raw FS'!N37:N41)-SUM('Raw FS'!N14:N16,'Raw FS'!N9:N10) -> 12634
B62: Total Asset | C62: ='Data Sheet'!E66 -> 71739.04 | D62: ='Data Sheet'!F66 -> 77310.75 | E62: ='Data Sheet'!G66 -> 73760.76 | F62: ='Data Sheet'!H66 -> 77196.02 | G62: ='Data Sheet'!I66 -> 85830.96 | H62: ='Data Sheet'!J66 -> 91753.97 | I62: ='Data Sheet'!K66 -> 88002.7
B63: Working Capital / Total Asset (A) | C63: =C61/C62 -> 0.15252504 | D63: =D61/D62 -> 0.15552818 | E63: =E61/E62 -> 0.11549501 | F63: =F61/F62 -> 0.13638009 | G63: =G61/G62 -> 0.13133955 | H63: =H61/H62 -> 0.14272952 | I63: =I61/I62 -> 0.14356378
B65: Retained Earnings / Total Asset
C66: =C60 -> 43555 | D66: =D60 -> 43921 | E66: =E60 -> 44286 | F66: =F60 -> 44651 | G66: =G60 -> 45016 | H66: =H60 -> 45382 | I66: =I60 -> 45747
B67: Retained Earnings | C67: ='Data Sheet'!E58 -> 57915.01 | D67: ='Data Sheet'!F58 -> 64044.04 | E67: ='Data Sheet'!G58 -> 59116.46 | F67: ='Data Sheet'!H58 -> 61223.24 | G67: ='Data Sheet'!I58 -> 67912.46 | H67: ='Data Sheet'!J58 -> 73258.53 | I67: ='Data Sheet'!K58 -> 68778.64
B68: Total Assets | C68: =C62 -> 71739.04 | D68: =D62 -> 77310.75 | E68: =E62 -> 73760.76 | F68: =F62 -> 77196.02 | G68: =G62 -> 85830.96 | H68: =H62 -> 91753.97 | I68: =I62 -> 88002.7
B69: Retained Earnings / Total Assets (B) | C69: =C67/C68 -> 0.80730116 | D69: =D67/D68 -> 0.8283976 | E69: =E67/E68 -> 0.80146219 | F69: =F67/F68 -> 0.79308804 | G69: =G67/G68 -> 0.791235 | H69: =H67/H68 -> 0.79842355 | I69: =I67/I68 -> 0.78155148
B71: EBIT / Total Asset
C72: =C66 -> 43555 | D72: =D66 -> 43921 | E72: =E66 -> 44286 | F72: =F66 -> 44651 | G72: =G66 -> 45016 | H72: =H66 -> 45382 | I72: =I66 -> 45747
B73: EBIT | C73: ='Historical FS'!F25 -> 17140.78 | D73: ='Historical FS'!G25 -> 17698.63 | E73: ='Historical FS'!H25 -> 15419.19 | F73: ='Historical FS'!I25 -> 18890.74 | G73: ='Historical FS'!J25 -> 23895.25 | H73: ='Historical FS'!K25 -> 23669.48 | I73: ='Historical FS'!L25 -> 24193.13
B74: Total Assets | C74: =C68 -> 71739.04 | D74: =D68 -> 77310.75 | E74: =E68 -> 73760.76 | F74: =F68 -> 77196.02 | G74: =G68 -> 85830.96 | H74: =H68 -> 91753.97 | I74: =I68 -> 88002.7
B75: EBIT / Total Asset (C) | C75: =C73/C74 -> 0.23893239 | D75: =D73/D74 -> 0.22892845 | E75: =E73/E74 -> 0.20904326 | F75: =F73/F74 -> 0.24471132 | G75: =G73/G74 -> 0.27839896 | H75: =H73/H74 -> 0.25796682 | I75: =I73/I74 -> 0.2749135
B77: Market Cap / Long Term Liabilities
C78: =C72 -> 43555 | D78: =D72 -> 43921 | E78: =E72 -> 44286 | F78: =F72 -> 44651 | G78: =G72 -> 45016 | H78: =H72 -> 45382 | I78: =I72 -> 45747
B79: Market Cap | C79: =('Data Sheet'!E70*'Data Sheet'!E90)/10000000 -> 341574.51 | D79: =('Data Sheet'!F70*'Data Sheet'!F90)/10000000 -> 197843.46 | E79: =('Data Sheet'!G70*'Data Sheet'!G90)/10000000 -> 252109.75 | F79: =('Data Sheet'!H70*'Data Sheet'!H90)/10000000 -> 289547.22 | G79: =('Data Sheet'!I70*'Data Sheet'!I90)/10000000 -> 446774.81 | H79: =('Data Sheet'!J70*'Data Sheet'!J90)/10000000 -> 501298.16 | I79: =('Data Sheet'!K70*'Data Sheet'!K90)/10000000 -> 512766.06
B80: Long Term Liabilities | C80: ='Data Sheet'!E61 -> 71739.04 | D80: ='Data Sheet'!F61 -> 77310.75 | E80: ='Data Sheet'!G61 -> 73760.76 | F80: ='Data Sheet'!H61 -> 77196.02 | G80: ='Data Sheet'!I61 -> 85830.96 | H80: ='Data Sheet'!J61 -> 91753.97 | I80: ='Data Sheet'!K61 -> 88002.7
B81: Market Cap / Long Term Liabilities (D) | C81: =C79/C80 -> 4.7613477 | D81: =D79/D80 -> 2.5590679 | E81: =E79/E80 -> 3.4179386 | F81: =F79/F80 -> 3.750805 | G81: =G79/G80 -> 5.2052873 | H81: =H79/H80 -> 5.4635037 | I81: =I79/I80 -> 5.8267082
B83: Sales / Total Assets
C84: =C66 -> 43555 | D84: =D66 -> 43921 | E84: =E66 -> 44286 | F84: =F66 -> 44651 | G84: =G66 -> 45016 | H84: =H66 -> 45382 | I84: =I66 -> 45747
B85: Sales | C85: ='Data Sheet'!E17 -> 48339.58 | D85: ='Data Sheet'!F17 -> 49387.7 | E85: ='Data Sheet'!G17 -> 49257.45 | F85: ='Data Sheet'!H17 -> 60644.54 | G85: ='Data Sheet'!I17 -> 70919.03 | H85: ='Data Sheet'!J17 -> 67931.94 | I85: ='Data Sheet'!K17 -> 75323.34
B86: Total Assets | C86: =C74 -> 71739.04 | D86: =D74 -> 77310.75 | E86: =E74 -> 73760.76 | F86: =F74 -> 77196.02 | G86: =G74 -> 85830.96 | H86: =H74 -> 91753.97 | I86: =I74 -> 88002.7
B87: Sales / Total Assets (E) | C87: =C85/C86 -> 0.6738253 | D87: =D85/D86 -> 0.6388206 | E87: =E85/E86 -> 0.6678002 | F87: =F85/F86 -> 0.78559154 | G87: =G85/G86 -> 0.82626397 | H87: =H85/H86 -> 0.74037058 | I87: =I85/I86 -> 0.85592078
B89: Altman's Z Score
C90: =C84 -> 43555 | D90: =D84 -> 43921 | E90: =E84 -> 44286 | F90: =F84 -> 44651 | G90: =G84 -> 45016 | H90: =H84 -> 45382 | I90: =I84 -> 45747
B91: Final Score | C91: =(C63*1.2)+(C69*1.4)+(C75*3.3)+(C81*0.6)+(C87*1) -> 5.6323624 | D91: =(D63*1.2)+(D69*1.4)+(D75*3.3)+(D81*0.6)+(D87*1) -> 4.2761157 | E91: =(E63*1.2)+(E69*1.4)+(E75*3.3)+(E81*0.6)+(E87*1) -> 4.6690472 | F91: =(F63*1.2)+(F69*1.4)+(F75*3.3)+(F81*0.6)+(F87*1) -> 5.1176013 | G91: =(G63*1.2)+(G69*1.4)+(G75*3.3)+(G81*0.6)+(G87*1) -> 6.1334894 | H91: =(H63*1.2)+(H69*1.4)+(H75*3.3)+(H81*0.6)+(H87*1) -> 6.1588317 | I91: =(I63*1.2)+(I69*1.4)+(I75*3.3)+(I81*0.6)+(I87*1) -> 6.5256089
B92: Financial Stability | C92: =IF(C91<1.81,"Distressed",IF(1.81<C91<2.99,"Gray Zone",IF(C91>2.99,"Safe Zone",0))) -> Safe Zone | D92: =IF(D91<1.81,"Distressed",IF(1.81<D91<2.99,"Gray Zone",IF(D91>2.99,"Safe Zone",0))) -> Safe Zone | E92: =IF(E91<1.81,"Distressed",IF(1.81<E91<2.99,"Gray Zone",IF(E91>2.99,"Safe Zone",0))) -> Safe Zone | F92: =IF(F91<1.81,"Distressed",IF(1.81<F91<2.99,"Gray Zone",IF(F91>2.99,"Safe Zone",0))) -> Safe Zone | G92: =IF(G91<1.81,"Distressed",IF(1.81<G91<2.99,"Gray Zone",IF(G91>2.99,"Safe Zone",0))) -> Safe Zone | H92: =IF(H91<1.81,"Distressed",IF(1.81<H91<2.99,"Gray Zone",IF(H91>2.99,"Safe Zone",0))) -> Safe Zone | I92: =IF(I91<1.81,"Distressed",IF(1.81<I91<2.99,"Gray Zone",IF(I91>2.99,"Safe Zone",0))) -> Safe Zone

Sheet Data>

Sheet List of Stocks
B2: COMPANY_NAME | C2: BSE | D2: NSE | E2: Industry
B3: 20 MICRONS LTD | C3: 533022 | D3: 20MICRONS | E3: Mining
B4: 21ST CENTURY MANAGEMENT SERVICES LTD | C4: 526921 | D4: 21STCENMGM | E4: Other Financial Services
B5: 3I INFOTECH LTD | C5: 532628 | D5: 3IINFOTECH | E5: IT Consulting & Software
B6: 3M (INDIA) LTD | C6: 523395 | D6: 3M(INDIA) | E6: Diversified
B7: 3M INDIA LTD | C7: 523395 | D7: 3MINDIA | E7: Diversified
B8: 3P LAND HOLDINGS LTD | C8: 516092 | D8: 3PLAND | E8: Paper & Paper Products
B9: 5PAISA CAPITAL LTD | C9: 540776 | D9: 5PAISA | E9: Other Financial Services
B10: 63 MOONS TECHNOLOGIES LTD | C10: 526881 | D10: 63MOONS | E10: IT Consulting & Software
B11: 7NR RETAIL LTD | C11: 540615 | D11: Not Listed | E11: Specialty Retail
B12: 7SEAS ENTERTAINMENT LTD | C12: 540874 | D12: Not Listed | E12: Movies & Entertainment
B13: 8K MILES SOFTWARE SERVICES LTD | C13: 512161 | D13: 8KMILES | E13: Internet Software & Services
B14: A & M FEBCON LTD | C14: 540697 | D14: Not Listed | E14: Industrial Machinery
B15: A AND M JUMBO BAGS LTD | C15: Not Listed | D15: AMJUMBO | E15: SME
B16: A INFRASTRUCTURE LTD | C16: 539620 | D16: Not Listed | E16: Cement & Cement Products
B17: A K SPINTEX LTD | C17: 539300 | D17: Not Listed | E17: Textiles
B18: A K CAPITAL SERVICES LTD | C18: 530499 | D18: Not Listed | E18: Finance (including NBFCs)
B19: A.F. Enterprises Ltd | C19: 538351 | D19: AFEL | E19: Investment Companies
B20: A-1 ACID LTD | C20: 542012 | D20: Not Listed | E20: Comm.Trading & Distribution
B21: A2Z INFRA ENGINEERING LTD | C21: 533292 | D21: A2ZINFRA | E21: Utilities:Non-Elec.
B22: AADHAAR VENTURES (INDIA) LTD | C22: 531611 | D22: Not Listed | E22: Finance (including NBFCs)
B23: AADHAAR VENTURES INDIA LTD | C23: 531611 | D23: Not Listed | E23: Finance (including NBFCs)
B24: AAKASH EXPLORATION SERVICES LTD | C24: Not Listed | D24: AAKASH | E24: SME
B25: AANANDA LAKSHMI SPINNING MILLS LTD | C25: 539096 | D25: Not Listed | E25: Textiles
B26: AANCHAL ISPAT LTD | C26: 538812 | D26: Not Listed | E26: Iron & Steel/Interm.Products
B27: AAR COMMERCIAL COMPANY LTD | C27: 539632 | D27: Not Listed | E27: Distributors
B28: Aar Shyam India Investment Company Ltd | C28: 542377 | D28: AARSHYAM | E28: Finance (including NBFCs)
B29: AAREY DRUGS & PHARMACEUTICALS LTD | C29: 524412 | D29: Not Listed | E29: Pharmaceuticals
B30: AARON INDUSTRIES LTD | C30: Not Listed | D30: AARON | E30: SME
B31: Aartech Solonics Ltd | C31: 542580 | D31: AARTECH | E31: Heavy Electrical Equipment
B32: AARTI DRUGS LTD | C32: 524348 | D32: AARTIDRUGS | E32: Pharmaceuticals
B33: AARTI INDUSTRIES LTD | C33: 524208 | D33: AARTIIND | E33: Commodity Chemicals
B34: AARV INFRATEL LTD | C34: 526488 | D34: Not Listed | E34: Textiles
B35: AARVEE DENIMS & EXPORTS LTD | C35: 514274 | D35: AARVEEDEN | E35: Textiles
B36: AARVI ENCON LTD | C36: Not Listed | D36: AARVI | E36: SME
B37: AASHEE INFOTECH LTD | C37: 519319 | D37: Not Listed | E37: Internet Software & Services
B38: AASWA TRADING & EXPORTS LTD | C38: 512038 | D38: Not Listed | E38: Comm.Trading & Distribution
B39: AAVAS FINANCIERS LTD | C39: 541988 | D39: AAVAS | E39: Housing Finance
B40: AAYUSH FOOD AND HERBS LTD | C40: 539528 | D40: Not Listed | E40: Packaged Foods
B41: ABAN OFFSHORE LTD | C41: 523204 | D41: ABAN | E41: Exploration & Production
B42: ABANS ENTERPRISES LTD | C42: 512165 | D42: Not Listed | E42: Comm.Trading & Distribution
B43: ABB INDIA LTD | C43: 500002 | D43: ABB | E43: Heavy Electrical Equipment
B44: ABBOTT (INDIA) LTD | C44: 500488 | D44: ABBOT(INDIA) | E44: Pharmaceuticals
B45: ABBOTT INDIA LTD | C45: 500488 | D45: ABBOTINDIA | E45: Pharmaceuticals
B46: ABC (INDIA) LTD | C46: 520123 | D46: Not Listed | E46: Surface Transportation
B47: ABC GAS INTERNATIONAL LTD | C47: 513119 | D47: Not Listed | E47: Copper
B48: ABC INDIA LTD | C48: 520123 | D48: Not Listed | E48: Surface Transportation
... B56: ABIRAMI FINANCIAL SERVICES INDIA LTD | C56: 511756 | D56: Not Listed | E56: Finance (including NBFCs)
B57: ABM INTERNATIONAL LTD | C57: Not Listed | D57: ABMINTLTD | E57: Others
B58: ABM KNOWLEDGEWARE LTD | C58: 531161 | D58: Not Listed | E58: IT Software Products
B59: ACC LTD | C59: 500410 | D59: ACC | E59: Cement & Cement Products
B60: ACCEL LTD | C60: 517494 | D60: Not Listed | E60: Storage Media & Peripherals
B61: ACCELYA KALE SOLUTIONS LTD | C61: 532268 | D61: ACCELYA | E61: IT Consulting & Software
B62: ACCORD SYNERGY LTD | C62: Not Listed | D62: ACCORD | E62: SME
B63: ACCURACY SHIPPING LTD | C63: Not Listed | D63: ACCURACY | E63: SME
B64: ACE EDUTREND LTD | C64: 530093 | D64: Not Listed | E64: Education
B65: ACE INTEGRATED SOLUTIONS LTD | C65: Not Listed | D65: ACEINTEG | E65: SME
B66: ACE MEN ENGG WORKS LTD | C66: 539661 | D66: Not Listed | E66: Distributors
B67: ACE SOFTWARE EXPORTS LTD | C67: 531525 | D67: Not Listed | E67: IT Software Products
B68: Achal Investments Ltd | C68: 538570 | D68: ACHAL | E68: Other Financial Services
B69: ACI INFOCOM LTD | C69: 517356 | D69: Not Listed | E69: Storage Media & Peripherals
B70: ACKNIT INDUSTRIES LTD | C70: 530043 | D70: Not Listed | E70: Other Apparels & Accessories
B71: ACME RESOURCES LTD | C71: 539391 | D71: Not Listed | E71: Finance (including NBFCs)
B72: ACROW INDIA LTD. | C72: 513149 | D72: ACROW | E72: Iron &amp; Steel Products
B73: ACRYSIL LTD | C73: 524091 | D73: Not Listed | E73: Plastic Products
B74: ACTION CONSTRUCTION EQUIPMENT LTD | C74: 532762 | D74: ACE | E74: Transport Related Services
B75: ACTION FINANCIAL SERVICES (INDIA) LTD | C75: 511706 | D75: Not Listed | E75: Other Financial Services
B76: ACTION FINANCIAL SERVICES INDIA LTD | C76: 511706 | D76: Not Listed | E76: Other Financial Services
B77: ACTIVE CLOTHING CO LTD | C77: 541144 | D77: Not Listed | E77: Other Apparels & Accessories
... B135: AGRI-TECH INDIA LTD | C135: 537292 | D135: AGRITECH | E135: Other Agricultural Products
B136: AGRO PHOS (INDIA) LTD | C136: Not Listed | D136: AGROPHOS | E136: SME
B137: AGRO PHOS INDIA LTD | C137: Not Listed | D137: AGROPHOS | E137: SME
B138: AGRO TECH FOODS LTD | C138: 500215 | D138: ATFL | E138: Other Agricultural Products
B139: AHIMSA INDUSTRIES LTD | C139: Not Listed | D139: AHIMSA | E139: SME
B140: AHLADA ENGINEERS LTD | C140: Not Listed | D140: AHLADA | E140: SME
B141: AHLUWALIA CONTRACTS (INDIA) LTD | C141: 532811 | D141: AHLUCONT | E141: Realty
B142: AHLUWALIA CONTRACTS INDIA LTD | C142: 532811 | D142: AHLUCONT | E142: Realty
B143: AHMEDABAD STEELCRAFT LTD | C143: 522273 | D143: Not Listed | E143: Iron & Steel/Interm.Products
B144: AI CHAMPDANY INDUSTRIES LTD | C144: 532806 | D144: Not Listed | E144: Jute & Jute Products
B145: AIA ENGINEERING LTD | C145: 532683 | D145: AIAENG | E145: Other Industrial Goods
B146: AIMCO PESTICIDES LTD | C146: 524288 | D146: Not Listed | E146: Agrochemicals
B147: AIRAN LTD | C147: Not Listed | D147: AIRAN | E147: SME
B148: AIRO LAM LTD | C148: Not Listed | D148: AIROLAM | E148: SME
B149: AISHWARYA TELECOM LTD | C149: 532975 | D149: Not Listed | E149: Telecom Equipment
B150: AJANTA PHARMA LTD | C150: 532331 | D150: AJANTPHARM | E150: Pharmaceuticals
B151: AJANTA SOYA LTD | C151: 519216 | D151: Not Listed | E151: Edible Oils
B152: AJCON GLOBAL SERVICES LTD | C152: 511692 | D152: Not Listed | E152: Other Financial Services
B153: AJEL LTD | C153: 530713 | D153: Not Listed | E153: IT Consulting & Software
B154: AJMERA REALTY & INFRA (INDIA) LTD | C154: 513349 | D154: AJMERA | E154: Realty
B155: AJMERA REALTY & INFRA INDIA LTD | C155: 513349 | D155: AJMERA | E155: Realty
B156: AJOONI BIOTECH LTD | C156: Not Listed | D156: AJOONI | E156: SME
B157: AJWA FUN WORLD & RESORT LTD | C157: 526628 | D157: Not Listed | E157: Other Leisure Facilities
B158: AKAR AUTO INDUSTRIES LTD | C158: 530621 | D158: Not Listed | E158: Industrial Machinery
B159: AKASH INFRA PROJECTS LTD | C159: Not Listed | D159: AKASH | E159: SME
B160: AKASHDEEP METAL INDUSTRIES LTD | C160: 538778 | D160: Not Listed | E160: Finance (including NBFCs)
B161: AKG EXIM LTD | C161: Not Listed | D161: AKG | E161: SME
B162: AKI (INDIA) LTD | C162: 542020 | D162: Not Listed | E162: Other Apparels & Accessories
B163: AKI INDIA LTD | C163: 542020 | D163: Not Listed | E163: Other Apparels & Accessories
B164: AKM LACE AND EMBROTEX LTD | C164: 540718 | D164: Not Listed | E164: Textiles
B165: AKME STAR HOUSING FINANCE LTD | C165: 539017 | D165: Not Listed | E165: Housing Finance
...

Sheet Raw_seg_data
B2: Segment Reporting Schedule
B3: Years | C3: FY18 | D3: FY19 | E3: FY20 | F3: FY21 | G3: FY22 | H3: FY23 | I3: FY24 | J3: FY25
B5: FMCG Ciggarettes
B6: A. External Revenue (Rs Cr) | C6: 24848.09 | D6: 22913.27 | E6: 23679.13 | F6: 22557.32 | G6: 26158.31 | H6: 31267.46 | I6: 33667.97 | J6: 35893.57
B7: B. Segment EBIT (Rs Cr) | C7: 14128.12 | D7: 15411.77 | E7: 15838.46 | F7: 13498.36 | G7: 15768.45 | H7: 18882.59 | I7: 20071.04 | J7: 21091.35
B8: C. EBIT Margin % | C8: 0.569 | D8: 0.673 | E8: 0.669 | F8: 0.598 | G8: 0.603 | H8: 0.604 | I8: 0.596 | J8: 0.588
B9: D. Segment Assets (Rs Cr) | C9: 8508.42 | D9: 8863.69 | E9: 7483.78 | F9: 7257.6 | G9: 7193.11 | H9: 7913.36 | I9: 9751.86 | J9: 10584.67
B10: E. Segment Liabilities (Rs Cr) | C10: 4756.35 | D10: 4888.65 | E10: 4148.85 | F10: 4624.33 | G10: 4855.07 | H10: 5239.34 | I10: 5442.84 | J10: 5729.56
B11: F. Net Segment Assets (Rs Cr) | C11: 3752.07 | D11: 3975.04 | E11: 3334.93 | F11: 2633.27 | G11: 2338.04 | H11: 2674.02 | I11: 4309.02 | J11: 4855.11
B12: G. Capital Expenditure (Rs Cr) | C12: 96.23 | D12: 171.38 | E12: 138.91 | F12: 98.9 | G12: 151.46 | H12: 185.07 | I12: 544.32 | J12: 330.23
B13: H. Depreciation & Amort. (Rs Cr) | C13: 295.15 | D13: 285.61 | E13: 312.37 | F13: 299.09 | G13: 297.05 | H13: 303.74 | I13: 291.59 | J13: 297.55
B14: I. EBITDA (Rs Cr) | C14: 14423.27 | D14: 15697.38 | E14: 16150.83 | F14: 13797.45 | G14: 16065.5 | H14: 19186.33 | I14: 20362.63 | J14: 21388.9
B15: J. Revenue CAGR (FY18-FY25) | J15: 0.0539
B16: K. EBIT CAGR (FY18-FY25) | J16: 0.0589
B18: FMCG Others
B19: A. External Revenue (Rs Cr) | C19: 11339.31 | D19: 12517.07 | E19: 12843.99 | F19: 14737.06 | G19: 15993.12 | H19: 19109.33 | I19: 20992.48 | J19: 22005.27
B20: B. Segment EBIT (Rs Cr) | C20: 170.46 | D20: 325.55 | E20: 424.94 | F20: 837.99 | G20: 934.93 | H20: 1386.49 | I20: 1789.91 | J20: 1590.23
B21: C. EBIT Margin % | C21: 0.015 | D21: 0.026 | E21: 0.033 | F21: 0.057 | G21: 0.058 | H21: 0.073 | I21: 0.085 | J21: 0.072
B22: D. Segment Assets (Rs Cr) | C22: 7760.11 | D22: 8224.57 | E22: 8809.78 | F22: 11517.32 | G22: 11546.19 | H22: 12059.55 | I22: 12592.81 | J22: 13016.19
B23: E. Segment Liabilities (Rs Cr) | C23: 1909.42 | D23: 2020.85 | E23: 2122.96 | F23: 2523 | G23: 2258.59 | H23: 2338.08 | I23: 2491.34 | J23: 2432.7
B24: F. Net Segment Assets (Rs Cr) | C24: 5850.69 | D24: 6203.72 | E24: 6686.82 | F24: 8994.32 | G24: 9287.6 | H24: 9721.47 | I24: 10101.47 | J24: 10583.49
B25: G. Capital Expenditure (Rs Cr) | C25: 835.85 | D25: 1324.87 | E25: 859.85 | F25: 478.42 | G25: 339 | H25: 418.77 | I25: 675.67 | J25: 530.42
B26: H. Depreciation & Amort. (Rs Cr) | C26: 301.97 | D26: 383.81 | E26: 497.68 | F26: 491.95 | G26: 534.01 | H26: 588.03 | I26: 567.89 | J26: 590.28
B27: I. EBITDA (Rs Cr) | C27: 472.43 | D27: 709.36 | E27: 922.62 | F27: 1329.94 | G27: 1468.94 | H27: 1974.52 | I27: 2357.8 | J27: 2180.51
B28: J. Revenue CAGR (FY18-FY25) | J28: 0.0993
B29: K. EBIT CAGR (FY18-FY25) | J29: 0.3758
B31: Hotel
B32: A. External Revenue (Rs Cr) | C32: 1480.02 | D32: 1728.15 | E32: 1911.59 | F32: 659.76 | G32: 1341.02 | H32: 2672.79 | I32: 3085.49 | J32: 0
B33: B. Segment EBIT (Rs Cr) | C33: 145 | D33: 185.69 | E33: 154 | F33: -563.87 | G33: 185.23 | H33: 557.31 | I33: 764.94 | J33: 0
B34: C. EBIT Margin % | C34: 0.098 | D34: 0.107 | E34: 0.081 | F34: -0.855 | G34: 0.138 | H34: 0.209 | I34: 0.248 | J34: 0
B35: D. Segment Assets (Rs Cr) | C35: 6564.68 | D35: 7302.46 | E35: 7563.12 | F35: 7544.39 | G35: 7470.93 | H35: 7896.45 | I35: 8765.18 | J35: 0
B36: E. Segment Liabilities (Rs Cr) | C36: 619.34 | D36: 637.39 | E36: 830.17 | F36: 731.34 | G36: 807.44 | H36: 920.3 | I36: 1159.06 | J36: 0
B37: F. Net Segment Assets (Rs Cr) | C37: 5945.34 | D37: 6665.07 | E37: 6732.95 | F37: 6813.05 | G37: 6663.49 | H37: 6976.15 | I37: 7606.12 | J37: 0
B38: G. Capital Expenditure (Rs Cr) | C38: 918.64 | D38: 936.48 | E38: 857.36 | F38: 409.54 | G38: 499.56 | H38: 588.7 | I38: 882.47 | J38: 0
B39: H. Depreciation & Amort. (Rs Cr) | C39: 174.98 | D39: 199.7 | E39: 267.17 | F39: 271.03 | G39: 265.77 | H39: 294.67 | I39: 300.84 | J39: 0
B40: I. EBITDA (Rs Cr) | C40: 319.98 | D40: 385.39 | E40: 421.17 | F40: -292.84 | G40: 451 | H40: 851.98 | I40: 1065.78 | J40: 0
B42: Agri Business
B43: A. External Revenue (Rs Cr) | C43: 4474.22 | D43: 6075.3 | E43: 5912.54 | F43: 8001.87 | G43: 12192.01 | H43: 12361.62 | I43: 8523.79 | J43: 12244
B44: B. Segment EBIT (Rs Cr) | C44: 841.49 | D44: 793.38 | E44: 829.74 | F44: 918.24 | G44: 1086.22 | H44: 1380.21 | I44: 1278.33 | J44: 1540.3
B45: C. EBIT Margin % | C45: 0.188 | D45: 0.131 | E45: 0.14 | F45: 0.115 | G45: 0.089 | H45: 0.112 | I45: 0.15 | J45: 0.126
B46: D. Segment Assets (Rs Cr) | C46: 3693.37 | D46: 4191.18 | E46: 4333.55 | F46: 5375.51 | G46: 5202.93 | H46: 4836.69 | I46: 5850.07 | J46: 7904.83
B47: E. Segment Liabilities (Rs Cr) | C47: 807.75 | D47: 785.36 | E47: 972.06 | F47: 1053.09 | G47: 1724.46 | H47: 1750.62 | I47: 1467.72 | J47: 2176.93
B48: F. Net Segment Assets (Rs Cr) | C48: 2885.62 | D48: 3405.82 | E48: 3361.49 | F48: 4322.42 | G48: 3478.47 | H48: 3086.07 | I48: 4382.35 | J48: 5727.9
B49: G. Capital Expenditure (Rs Cr) | C49: 92.9 | D49: 54.1 | E49: 57.74 | F49: 58.18 | G49: 215.26 | H49: 258.41 | I49: 143.61 | J49: 168.68
B50: H. Depreciation & Amort. (Rs Cr) | C50: 68.04 | D50: 72.36 | E50: 74.35 | F50: 77.1 | G50: 82.92 | H50: 69.6 | I50: 81.47 | J50: 91.14
B51: I. EBITDA (Rs Cr) | C51: 909.53 | D51: 865.74 | E51: 904.09 | F51: 995.34 | G51: 1169.14 | H51: 1449.81 | I51: 1359.8 | J51: 1631.44
B52: J. Revenue CAGR (FY18-FY25) | J52: 0.1547
B53: K. EBIT CAGR (FY18-FY25) | J53: 0.0902
B55: Paperboards Paper Pack.
B56: A. External Revenue (Rs Cr) | C56: 3695.41 | D56: 4230.4 | E56: 4498.98 | F56: 4549.83 | G56: 6203.79 | H56: 7233.69 | I56: 6474.74 | J56: 6575.88
B57: B. Segment EBIT (Rs Cr) | C57: 1042.16 | D57: 1239.23 | E57: 1305.33 | F57: 1098.68 | G57: 1700 | H57: 2293.95 | I57: 1372.34 | J57: 883.11
B58: C. EBIT Margin % | C58: 0.282 | D58: 0.293 | E58: 0.29 | F58: 0.241 | G58: 0.274 | H58: 0.317 | I58: 0.212 | J58: 0.134
B59: D. Segment Assets (Rs Cr) | C59: 6730.78 | D59: 6960.54 | E59: 6816.9 | F59: 7237.93 | G59: 8482.37 | H59: 9195.24 | I59: 9596.76 | J59: 9908.98
B60: E. Segment Liabilities (Rs Cr) | C60: 786.73 | D60: 755.48 | E60: 764.12 | F60: 1080.24 | G60: 1326.05 | H60: 1315.18 | I60: 1287.23 | J60: 1384.96
B61: F. Net Segment Assets (Rs Cr) | C61: 5944.05 | D61: 6205.06 | E61: 6052.78 | F61: 6157.69 | G61: 7156.32 | H61: 7880.06 | I61: 8309.53 | J61: 8524.02
B62: G. Capital Expenditure (Rs Cr) | C62: 910.01 | D62: 258.74 | E62: 247.86 | F62: 775.4 | G62: 896.72 | H62: 744.56 | I62: 872.47 | J62: 452.42
B63: H. Depreciation & Amort. (Rs Cr) | C63: 274.6 | D63: 326.24 | E63: 357.51 | F63: 359.81 | G63: 410.97 | H63: 347.99 | I63: 359.93 | J63: 400.79
B64: I. EBITDA (Rs Cr) | C64: 1316.76 | D64: 1565.47 | E64: 1662.84 | F64: 1458.49 | G64: 2110.97 | H64: 2641.94 | I64: 1732.27 | J64: 1283.9
B65: J. Revenue CAGR (FY18-FY25) | J65: 0.0858
B66: K. EBIT CAGR (FY18-FY25) | J66: -0.0234
B68: Others/Infotech
B69: A. External Revenue (Rs Cr) | C69: 1525.46 | D69: 1884.24 | E69: 2122.27 | F69: 2329.31 | G69: 2729.98 | H69: 3181.69 | I69: 3691.55 | J69: 4224.04
B70: B. Segment EBIT (Rs Cr) | C70: 126.81 | D70: 172.45 | E70: 290.95 | F70: 558.69 | G70: 723.73 | H70: 534.62 | I70: 642.7 | J70: 670.73
B71: C. EBIT Margin % | C71: 0.083 | D71: 0.092 | E71: 0.137 | F71: 0.24 | G71: 0.265 | H71: 0.168 | I71: 0.174 | J71: 0.159
B72: D. Segment Assets (Rs Cr) | C72: 900.81 | D72: 901.55 | E72: 1601.91 | F72: 1629.47 | G72: 1713.01 | H72: 3090.47 | I72: 3496.86 | J72: 2736.44
B73: E. Segment Liabilities (Rs Cr) | C73: 229.54 | D73: 296.42 | E73: 375.72 | F73: 395.4 | G73: 463.17 | H73: 1210.08 | I73: 1252.5 | J73: 1101.44
B74: F. Net Segment Assets (Rs Cr) | C74: 671.27 | D74: 605.13 | E74: 1226.19 | F74: 1234.07 | G74: 1249.84 | H74: 1880.39 | I74: 2244.36 | J74: 1635
B75: G. Capital Expenditure (Rs Cr) | C75: 16.25 | D75: 22.09 | E75: 142.94 | F75: 14.84 | G75: 25.45 | H75: 809.52 | I75: 41.77 | J75: 336.17
B76: H. Depreciation & Amort. (Rs Cr) | C76: 25.68 | D76: 24.43 | E76: 26.8 | F76: 32.04 | G76: 28.45 | H76: 91.69 | I76: 106.53 | J76: 133.49
B77: I. EBITDA (Rs Cr) | C77: 152.49 | D77: 196.88 | E77: 317.75 | F77: 590.73 | G77: 752.18 | H77: 626.31 | I77: 749.23 | J77: 804.22
B78: J. Revenue CAGR (FY18-FY25) | J78: 0.1566
B79: K. EBIT CAGR (FY18-FY25) | J79: 0.2687
B81: Consolidated Totals
B82: Total External Revenue | C82: 47362.51 | D82: 49348.43 | E82: 50968.5 | F82: 52835.15 | G82: 64618.23 | H82: 75826.58 | I82: 76436.02 | J82: 80942.76
B83: Total Segment EBIT | C83: 16454.04 | D83: 18128.07 | E83: 18843.42 | F83: 16348.09 | G83: 20398.56 | H83: 25035.17 | I83: 25919.26 | J83: 25775.72
B84: Total Capex | C84: 2869.88 | D84: 2767.66 | E84: 2304.66 | F84: 1835.28 | G84: 2127.45 | H84: 3005.03 | I84: 3160.31 | J84: 1817.92
B85: Total Depreciation | C85: 1140.42 | D85: 1292.15 | E85: 1535.88 | F85: 1531.02 | G85: 1619.17 | H85: 1695.72 | I85: 1708.25 | J85: 1513.25

Sheet Growth_assumptions
B2: Reinvestment Rate Schedule
B4: Year | C4: Net Capex | D4: NOPAT | E4: WC Changes | F4: Full RR | G4: RR used in DCF
B5: FY22 | C5: {=TRANSPOSE('Intrinsic Growth'!G44:J44)} -> -2009 | D5: {=TRANSPOSE('Intrinsic Growth'!G37:J37)} -> 13636.715 | E5: {=TRANSPOSE('Intrinsic Growth'!G45:J45)} -> 2014 | F5: =(C5+E5)/D5 -> 0.00036665721 | G5: excluded
B6: FY23 | C6: -2694 | D6: 17435.827 | E6: 519 | F6: =(C6+E6)/D6 -> -0.12474315 | G6: excluded
B7: FY24 | C7: -3456 | D7: 17449.743 | E7: -515 | F7: =(C7+E7)/D7 -> -0.22756782 | G7: excluded
B8: FY25 | C8: -2104 | D8: 17289.802 | E8: 2744 | F8: =(C8+E8)/D8 -> 0.037016039 | G8: 0.0503
B9: FY26-30 1 | C9: — | D9: — | E9: — | F9: — | G9: 10% - 12%
B10: Terminal | C10: — | D10: — | E10: — | F10: — | G10: 0.075
B12: Expected Growth Rate
B14: Segment | C14: FY25 EBIT | D14: EBIT Weight | E14: Segment CAGR | F14: Forward Growth | G14: Contribution
B15: Cigarettes | C15: =Raw_seg_data!J7 -> 21091.35 | D15: =C15/$C$20 -> 0.81826424 | E15: =Raw_seg_data!J16 -> 0.0589 | F15: 0.055 | G15: =D15*F15 -> 0.045004533
B16: FMCG Others | C16: =Raw_seg_data!J20 -> 1590.23 | D16: =C16/$C$20 -> 0.061694882 | E16: =Raw_seg_data!J29 -> 0.3758 | F16: 0.15 | G16: =D16*F16 -> 0.0092542323
B17: Agri | C17: =Raw_seg_data!J44 -> 1540.3 | D17: =C17/$C$20 -> 0.059757788 | E17: =Raw_seg_data!J53 -> 0.0902 | F17: 0.08 | G17: =D17*F17 -> 0.004780623
B18: Paperboards | C18: =Raw_seg_data!J57 -> 883.11 | D18: =C18/$C$20 -> 0.034261313 | E18: =Raw_seg_data!J66 -> -0.0234 | F18: 0.04 | G18: =D18*F18 -> 0.0013704525
B19: Others | C19: =Raw_seg_data!J70 -> 670.73 | D19: =C19/$C$20 -> 0.026021776 | E19: =Raw_seg_data!J79 -> 0.2687 | F19: 0.12 | G19: =D19*F19 -> 0.0031226131
B20: Expected Growth | C20: =SUM(C15:C19) -> 25775.72 | G20: =SUM(G15:G19) -> 0.063532454
B22: Terminal Growth Rate
B24: Segment 2 | C24: FY25 EBIT | D24: EBIT Weight | E24: Segment CAGR | F24: Long Run Rate | G24: Contribution
B25: Cigarettes | C25: =C15 -> 21091.35 | D25: =D15 -> 0.81826424 | E25: =E15 -> 0.0589 | F25: 0.035 | G25: =D25*F25 -> 0.028639248
B26: FMCG Others | C26: =C16 -> 1590.23 | D26: =D16 -> 0.061694882 | E26: =E16 -> 0.3758 | F26: 0.045 | G26: =D26*F26 -> 0.0027762697
B27: Agri | C27: =C17 -> 1540.3 | D27: =D17 -> 0.059757788 | E27: =E17 -> 0.0902 | F27: 0.055 | G27: =D27*F27 -> 0.0032866783
B28: Paperboards | C28: =C18 -> 883.11 | D28: =D18 -> 0.034261313 | E28: =E18 -> -0.0234 | F28: 0.04 | G28: =D28*F28 -> 0.0013704525
B29: Others | C29: =C19 -> 670.73 | D29: =D19 -> 0.026021776 | E29: =E19 -> 0.2687 | F29: 0.05 | G29: =D29*F29 -> 0.0013010888
B30: Expected Growth | G30: =SUM(G25:G29) -> 0.037373738
B32: Notes:
B33: 1.I used ITC's FY25 actual capex divided by NOPAT which gave 12.2%, so I rounded to 12%.
B34: 2. Long Run Rates-for terminal Growth Rate Calculation:
B35: Cigarettes 3.5% — volume flat, pure pricing = inflation-linked growth
B36: FMCG Others 5.5% — India FMCG long-run industry rate
B37: Agri 4.5% — India agri GDP + export growth
B38: Paperboards 4.0% — packaging demand steady state
B39: Others 5.0% — conservative IT/hospitality long-run

Sheet Peer_data
B2: Company | C2: Ticker | D2: Market Cap (Cr) | E2: EV/EBIT
A4: # | B4: FMCG Cigarettes
B5: VST INDUSTRIES LTD | C5: VSTIND.NS | D5: 4389 | E5: 10.89
B6: GODFREY PHILLIPS INDIA LT | C6: GODFRYPHLP.NS | D6: 32975 | E6: 21.62
D8: Average | E8: =AVERAGE(E5:E6) -> 16.255
D9: Median | E9: =MEDIAN(E5:E6) -> 16.255
A11: # | B11: FMCG Others
B12: HINDUSTAN UNILEVER LTD. | C12: HINDUNILVR.NS | D12: 547055 | E12: 36.5
B13: DABUR INDIA LTD | C13: DABUR.NS | D13: 80171 | E13: 32.07
B14: MARICO LIMITED | C14: MARICO.NS | D14: 101967 | E14: 46.89
B15: GODREJ CONSUMER PRODUCTS | C15: GODREJCP.NS | D15: 111457 | E15: 37.84
B16: BRITANNIA INDUSTRIES LTD | C16: BRITANNIA.NS | D16: 137716 | E16: 45.38
D18: Average | E18: =AVERAGE(E12:E16) -> 39.736
D19: Median | E19: =MEDIAN(E12:E16) -> 37.84
A21: # | B21: Agri Business
B22: KRBL LIMITED | C22: KRBL.NS | D22: 8620 | E22: 9.76
B23: LT FOODS LIMITED | C23: LTFOODS.NS | D23: 14890 | E23: 17.02
B24: AVANTI FEEDS LIMITED | C24: AVANTIFEED.NS | D24: 19431 | E24: 22.58
B25: GODREJ AGROVET LIMITED | C25: GODREJAGRO.NS | D25: 11637 | E25: 20.09
B26: COROMANDEL INTERNTL. LTD | C26: COROMANDEL.NS | D26: 59860 | E26: 19.15
D28: Average | E28: =AVERAGE(E22:E26) -> 17.72
D29: Median | E29: =MEDIAN(E22:E26) -> 19.15
A31: # | B31: Paperboards Paper Pack.
B32: JK PAPER LIMITED | C32: JKPAPER.NS | D32: 6784 | E32: 11.96
B33: TAMILNADU NEWSPRT & PAPER | C33: TNPL.NS | D33: 1023 | E33: 11.79
B34: CENTURY PLYBOARDS (I) LTD | C34: CENTURYPLY.NS | D34: 17585 | E34: 55.66
B35: EMAMI PAPER MILLS LIMITED | C35: EMAMIPAP.NS | D35: 462 | E35: 11.76
D37: Average | E37: =AVERAGE(E32:E35) -> 22.7925
D38: Median | E38: =MEDIAN(E32:E35) -> 11.875
A40: # | B40: Others/Infotech
B41: Mphasis | C41: MPHASIS.NS | D41: 43218 | E41: 17.58
B42: Coforge | C42: COFORGE.NS | D42: 40383 | E42: 28.61
B43: Birlasoft | C43: BSOFT.NS | D43: 10393 | E43: 11.82
B44: KPIT Technologies | C44: KPITTECH.NS | D44: 20044 | E44: 16.54
D46: Average | E46: =AVERAGE(E41:E44) -> 18.6375
D47: Median | E47: =MEDIAN(E41:E44) -> 17.06

Sheet Raw FS
B2: ="RAW Balance Sheet"&" - "&'Data Sheet'!B1 -> RAW Balance Sheet - ITC LTD
B3: Particulars | C3: 41699 | D3: 42064 | E3: 42430 | F3: 42795 | G3: 43160 | H3: 43525 | I3: 43891 | J3: 44256 | K3: 44621 | L3: 44986 | M3: 45352 | N3: 45717
B5: Equity Capital | C5: 795 | D5: 802 | E5: 805 | F5: 1215 | G5: 1220 | H5: 1226 | I5: 1229 | J5: 1231 | K5: 1232 | L5: 1243 | M5: 1248 | N5: 1251
B6: Reserves | C6: 26442 | D6: 30934 | E6: 41875 | F6: 45198 | G6: 51290 | H6: 57915 | I6: 64044 | J6: 59116 | K6: 61223 | L6: 67912 | M6: 73259 | N6: 68779
B7: Borrowings -
B8: Long term Borrowings | C8: 76 | D8: 61 | E8: 27 | F8: 18 | G8: 12 | H8: 8 | I8: 6 | J8: 6 | K8: 5 | L8: 3 | M8: 2 | N8: 0
B9: Short term Borrowings | C9: 150 | D9: 195 | E9: 44 | F9: 19 | G9: 17 | H9: 2 | I9: 1 | J9: 4 | K9: 1 | L9: 35 | M9: 10 | N9: 91
B10: Lease Liabilities | C10: 0 | D10: 0 | E10: 0 | F10: 0 | G10: 0 | H10: 0 | I10: 268 | J10: 261 | K10: 244 | L10: 267 | M10: 292 | N10: 193
B11: Other Borrowings | C11: 16 | D11: 13 | E11: 13 | F11: 8 | G11: 7 | H11: 3 | I11: 2 | J11: 0 | K11: 0 | L11: 0 | M11: 0 | N11: 0
B12: Other Liabilities -
B13: Non controlling int | C13: 203 | D13: 225 | E13: 261 | F13: 295 | G13: 334 | H13: 343 | I13: 377 | J13: 347 | K13: 366 | L13: 384 | M13: 383 | N13: 368
B14: Trade Payables | C14: 2106 | D14: 2020 | E14: 2339 | F14: 2659 | G14: 3496 | H14: 3510 | I14: 3630 | J14: 4319 | K14: 4417 | L14: 4659 | M14: 4798 | N14: 4807
B15: Advance from Customers | C15: 0 | D15: 0 | E15: 805 | F15: 495 | G15: 461 | H15: 430 | I15: 703 | J15: 811 | K15: 1278 | L15: 1295 | M15: 886 | N15: 1264
B16: Other liability items | C16: 11060 | D16: 11702 | E16: 5483 | F16: 5991 | G16: 7404 | H16: 8301 | I16: 7050 | J16: 7666 | K16: 8429 | L16: 10032 | M16: 10877 | N16: 11249
B17: Total Liabilities | C17: 40848 | D17: 45952 | E17: 51651 | F17: 55898 | G17: 64241 | H17: 71739 | I17: 77311 | J17: 73761 | K17: 77196 | L17: 85831 | M17: 91754 | N17: 88003
B19: Fixed Assets -
B20: Land | C20: 1564 | D20: 1717 | E20: 1615 | F20: 1673 | G20: 1685 | H20: 2021 | I20: 2797 | J20: 2889 | K20: 2829 | L20: 2830 | M20: 2865 | N20: 1588
B21: Building | C21: 4110 | D21: 4860 | E21: 4219 | F21: 4716 | G21: 5331 | H21: 6996 | I21: 8161 | J21: 8387 | K21: 9100 | L21: 9789 | M21: 10944 | N21: 7550
B22: Plant Machinery | C22: 12633 | D22: 14667 | E22: 9112 | F22: 10384 | G22: 11453 | H22: 13316 | I22: 14625 | J22: 15307 | K22: 16912 | L22: 18480 | M22: 20718 | N22: 19423
B23: Equipments | C23: 34 | D23: 46 | E23: 27 | F23: 32 | G23: 32 | H23: 34 | I23: 40 | J23: 41 | K23: 44 | L23: 44 | M23: 53 | N23: 63
B24: Furniture n fittings | C24: 729 | D24: 805 | E24: 413 | F24: 459 | G24: 497 | H24: 644 | I24: 810 | J24: 833 | K24: 907 | L24: 1000 | M24: 1068 | N24: 282
B25: Railway sidings | C25: 2 | D25: 2 | E25: 2 | F25: 2 | G25: 2 | H25: 2 | I25: 2 | J25: 2 | K25: 2 | L25: 2 | M25: 2 | N25: 2
B26: Vehicles | C26: 120 | D26: 128 | E26: 107 | F26: 128 | G26: 140 | H26: 161 | I26: 184 | J26: 180 | K26: 179 | L26: 189 | M26: 192 | N26: 141
B27: Intangible Assets | C27: 398 | D27: 678 | E27: 563 | F27: 563 | G27: 570 | H27: 684 | I27: 684 | J27: 2734 | K27: 2744 | L27: 3490 | M27: 3505 | N27: 3622
B28: Other fixed assets | C28: 411 | D28: 458 | E28: 117 | F28: 138 | G28: 212 | H28: 234 | I28: 663 | J28: 716 | K28: 719 | L28: 786 | M28: 841 | N28: 967
B29: Gross Block | C29: 20000 | D29: 23361 | E29: 16176 | F29: 18094 | G29: 19920 | H29: 24090 | I29: 27965 | J29: 31088 | K29: 33435 | L29: 36608 | M29: 40189 | N29: 33638
B30: Accumulated Depreciation | C30: 7073 | D30: 8057 | E30: 1069 | F30: 2201 | G30: 3396 | H30: 4716 | I30: 6252 | J30: 7790 | K30: 9204 | L30: 10757 | M30: 12368 | N30: 11683
B31: Net Block | C31: =IFERROR(C29-C30,0) -> 12927 | D31: =IFERROR(D29-D30,0) -> 15304 | E31: =IFERROR(E29-E30,0) -> 15107 | F31: =IFERROR(F29-F30,0) -> 15893 | G31: =IFERROR(G29-G30,0) -> 16524 | H31: =IFERROR(H29-H30,0) -> 19374 | I31: =IFERROR(I29-I30,0) -> 21713 | J31: =IFERROR(J29-J30,0) -> 23298 | ... N31: =IFERROR(N29-N30,0) -> 21955
B33: CWIP | C33: 3117 | D33: 2700 | E33: 2560 | F33: 3730 | G33: 5508 | H33: 4136 | I33: 3256 | J33: 4011 | K33: 3226 | L33: 3003 | M33: 2861 | N33: 1091
B34: Investments | C34: 7284 | D34: 6943 | E34: 11748 | F34: 17581 | G34: 22053 | H34: 25043 | I34: 28663 | J34: 24871 | K34: 24841 | L34: 29415 | M34: 31114 | N34: 34720
B36: Other Assets -
B37: Inventories | C37: 8255 | D37: 8587 | E37: 9062 | F37: 8116 | G37: 7495 | H37: 7860 | I37: 8879 | J37: 10397 | K37: 10864 | L37: 11771 | M37: 14153 | N37: 15638
B38: Trade receivables | C38: 2439 | D38: 1982 | E38: 1917 | F38: 2474 | G38: 2682 | H38: 4035 | I38: 2562 | J38: 2502 | K38: 2462 | L38: 2956 | M38: 4026 | N38: 4720
B39: Cash Equivalents | C39: 3490 | D39: 7896 | E39: 6063 | F39: 2967 | G39: 2900 | H39: 4152 | I39: 7277 | J39: 4659 | K39: 4654 | L39: 4880 | M39: 7218 | N39: 4012
B40: Loans n Advances | C40: 107 | D40: 150 | E40: 14 | F40: 7 | G40: 74 | H40: 67 | I40: 6 | J40: 7 | K40: 11 | L40: 13 | M40: 31 | N40: 10
B41: Other asset items | C41: 3234 | D41: 2391 | E41: 5180 | F41: 5129 | G41: 7004 | H41: 7071 | I41: 4952 | J41: 4015 | K41: 6906 | L41: 7941 | M41: 4531 | N41: 5858
B42: Total Assets | C42: 40848 | D42: 45952 | E42: 51651 | F42: 55898 | G42: 64241 | H42: 71739 | I42: 77311 | J42: 73761 | K42: 77196 | L42: 85831 | M42: 91754 | N42: 88003
B45: ="RAW Cash Flow Statement"&" - "&'Data Sheet'!B1 -> RAW Cash Flow Statement - ITC LTD
B46: Particulars | C46: 41699 | D46: 42064 | E46: 42430 | F46: 42795 | G46: 43160 | H46: 43525 | I46: 43891 | J46: 44256 | K46: 44621 | L46: 44986 | M46: 45352 | N46: 45717
B48: Cash from Operating Activity - | C48: 7344 | D48: 9843 | E48: 9799 | F48: 10627 | G48: 13169 | H48: 12583 | I48: 14690 | J48: 12527 | K48: 15776 | L48: 18878 | M48: 17179 | N48: 17627
B49: Profit from operations | C49: 13172 | D49: 14261 | E49: 15154 | F49: 16075 | G49: 17433 | H49: 18862 | I49: 19416 | J49: 17326 | K49: 20857 | L49: 26052 | M49: 26635 | N49: 26719
B50: Receivables | C50: -1546 | D50: 558 | E50: -207 | F50: -870 | G50: -964 | H50: -755 | I50: 1411 | J50: -66 | K50: -732 | L50: -884 | M50: -934 | N50: -1023
B51: Inventory | C51: -755 | D51: -505 | E51: -693 | F51: 593 | G51: 602 | H51: -359 | I51: -508 | J51: -1460 | K51: -466 | L51: -1098 | M51: -2545 | N51: -2975
B52: Payables | C52: 456 | D52: -23 | E52: 622 | F52: 321 | G52: 2098 | H52: 639 | I52: -607 | J52: 1112 | K52: 1099 | L52: 1058 | M52: 141 | N52: 1256
B53: Working capital changes | C53: -1844 | D53: 31 | E53: -277 | F53: 44 | G53: 1736 | H53: -476 | I53: 296 | J53: -413 | K53: -100 | L53: -924 | M53: -3337 | N53: -2742
B54: Direct taxes | C54: -3984 | D54: -4449 | E54: -5078 | F54: -5492 | G54: -6000 | H54: -5803 | I54: -5023 | J54: -4387 | K54: -4982 | L54: -6250 | M54: -6120 | N54: -6350
B56: Cash from Investing Activity - | C56: -3254 | D56: -5275 | E56: -3921 | F56: -3251 | G56: -7114 | H56: -5546 | I56: -6174 | J56: 5740 | K56: -2238 | L56: -5732 | M56: 1563 | N56: -564
B57: Fixed assets purchased | C57: -2887 | D57: -3300 | E57: -2348 | F57: -3122 | G57: -2878 | H57: -3169 | I57: -2441 | J57: -1837 | K57: -2142 | L57: -2743 | M57: -3563 | N57: -2279
B58: Fixed assets sold | C58: 38 | D58: 9 | E58: 8 | F58: 50 | G58: 80 | H58: 28 | I58: 27 | J58: 3 | K58: 133 | L58: 49 | M58: 107 | N58: 175
B59: Investments purchased | C59: -94242 | D59: -98742 | E59: -154081 | F59: -85683 | G59: -98330 | H59: -94187 | I59: -79835 | J59: -57553 | K59: -69776 | L59: -80932 | M59: -75107 | N59: -66373
... B79: CFO/OP | C79: 0.87 | D79: 1 | E79: 1.02 | F79: 1.04 | G79: 1.16 | H79: 0.99 | I79: 1.02 | J79: 0.99 | K79: 1.01 | L79: 0.98 | M79: 0.92 | N79: 0.93

Sheet Peer Comps
B2: Peer Comps - Data
B3: S.No. | C3: Name | D3: CMP Rs. | E3: Mar Cap Rs.Cr. | F3: Debt Rs.Cr. | G3: Debt / Eq | H3: Beta
B4: 1 | C4: Hind. Unilever | D4: 2305.4 | E4: 540705.54 | F4: 1775 | G4: 0.04 | H4: 0.584
B5: 2 | C5: ITC | D5: 309.15 | E5: 387348.51 | F5: 362.97 | G5: 0.01 | H5: 0.515
B6: 3 | C6: Nestle India | D6: 1379.9 | E6: 265881.4 | F6: 444.16 | G6: 0.1 | H6: 0.751
B7: 4 | C7: Varun Beverages | D7: 485.1 | E7: 164118.16 | F7: 2508.18 | G7: 0.13 | H7: 1.16
B8: 5 | C8: Britannia Inds. | D8: 5844 | E8: 140725.16 | F8: 2196.3 | G8: 0.59 | H8: 0.51
B10: Peer Comps - Tax Rates
B11: S.No. | C11: Company | D11: FY2021 | E11: FY2022 | F11: FY2023 | G11: FY2024 | H11: FY2025 | I11: 5-Yr Avg | J11: 5-Yr Median
B12: 1 | C12: ITC | D12: ='Historical FS'!H35 -> 0.29654481 | E12: ='Historical FS'!I35 -> 0.278127 | F12: ='Historical FS'!J35 -> 0.27032247 | G12: ='Historical FS'!K35 -> 0.26277456 | H12: ='Historical FS'!L35 -> 0.28534247 | I12: =AVERAGE(D12:H12) -> 0.27862226 | J12: =MEDIAN(D12:H12) -> 0.278127
B13: 2 | C13: Hind. Unilever | D13: 0.26 | E13: 0.26 | F13: 0.26 | G13: 0.26 | H13: 0.256 | I13: =AVERAGE(D13:H13) -> 0.2592 | J13: =MEDIAN(D13:H13) -> 0.26
B14: 3 | C14: Nestle India | D14: 0.2597 | E14: 0.2586 | F14: 0.2658 | G14: 0.2564 | H14: 0.2547 | I14: =AVERAGE(D14:H14) -> 0.25904 | J14: =MEDIAN(D14:H14) -> 0.2586
B15: 4 | C15: Varun Beverages | D15: 0.25 | E15: 0.25 | F15: 0.25 | G15: 0.25 | H15: 0.25 | I15: =AVERAGE(D15:H15) -> 0.25 | J15: =MEDIAN(D15:H15) -> 0.25
B16: 5 | C16: Britannia Inds. | D16: 0.2638 | E16: 0.2706 | F16: 0.2362 | G16: 0.2675 | H16: 0.2558 | I16: =AVERAGE(D16:H16) -> 0.25878 | J16: =MEDIAN(D16:H16) -> 0.2638

Sheet RV Data
B2: S.No. | C2: Name | D2: Ticker | E2: CMP Rs. | F2: No. Eq. Shares | G2: Market Cap | H2: Net Debt | I2: Debt | J2: EV | K2: Cash | L2: Sales | M2: EBITDA | N2: Net Profit
B3: 1 | C3: ITC | D3: ITC | E3: 305 | F3: 1252.95 | G3: =F3*E3 -> 382149.75 | H3: =I3-K3 -> -3649.39 | I3: 362.97 | J3: =G3+H3 -> 378500.36 | K3: 4012.36 | L3: ='Historical FS'!L7 -> 75323.34 | M3: 28612.68 | N3: ='Historical FS'!L37 -> 17257.6
B4: 2 | C4: Hind. Unilever | D4: HINDUNILVR | E4: 2231.5 | F4: 234.96 | G4: =F4*E4 -> 524313.24 | H4: =I4-K4 -> -5779 | I4: 1775 | J4: =G4+H4 -> 518534.24 | K4: 7554 | L4: 64544 | M4: 16265 | N4: 14540
B5: 3 | C5: Nestle India | D5: NESTLEIND | E5: 1286.4 | F5: 192.83 | G5: =F5*E5 -> 248056.51 | H5: =I5-K5 -> 381.2 | I5: 476.85 | J5: =G5+H5 -> 248437.71 | K5: 95.65 | L5: 21910.69 | M5: 6005.29 | N5: 3315.9
B6: 4 | C6: Varun Beverages | D6: VBL | E6: 466.55 | F6: 338.21 | G6: =F6*E6 -> 157791.88 | H6: =I6-K6 -> 509.69 | I6: 2508.18 | J6: =G6+H6 -> 158301.57 | K6: 1998.49 | L6: 21685.37 | M6: 6605.66 | N6: 3062.04
B7: 5 | C7: Britannia Inds. | D7: BRITANNIA | E7: 5700 | F7: 24.09 | G7: =F7*E7 -> 137313 | H7: =I7-K7 -> 1883.82 | I7: 2196.3 | J7: =G7+H7 -> 139196.82 | K7: 312.48 | L7: 18864.86 | M7: 3813.85 | N7: 2416.46
B8: 6 | C8: Godrej Consumer | D8: GODREJCP | E8: 1104.8 | F8: 102.32 | G8: =F8*E8 -> 113043.14 | H8: =I8-K8 -> 3630.43 | I8: 4113.49 | J8: =G8+H8 -> 116673.57 | K8: 483.06 | L8: 15184.02 | M8: 3331.5 | N8: 1821.6
B9: 7 | C9: Tata Consumer | D9: TATACONSUM | E9: 1120.4 | F9: 98.96 | G9: =F9*E9 -> 110874.78 | H9: =I9-K9 -> -241.75 | I9: 2576.11 | J9: =G9+H9 -> 110633.03 | K9: 2817.86 | L9: 19465.03 | M9: 3234.93 | N9: 1471.5
B10: 8 | C10: Marico | D10: MARICO | E10: 760.7 | F10: 129.81 | G10: =F10*E10 -> 98746.467 | H10: =I10-K10 -> -202 | I10: 575 | J10: =G10+H10 -> 98544.467 | K10: 777 | L10: 13008 | M10: 2459 | N10: 1750
B11: 9 | C11: United Spirits | D11: MCDOWELL-N | E11: 1307.7 | F11: 72.74 | G11: =F11*E11 -> 95122.098 | H11: =I11-K11 -> -1618 | I11: 412 | J11: =G11+H11 -> 93504.098 | K11: 2030 | L11: 12919 | M11: 2646 | N11: 1720
B12: 10 | C12: Dabur India | D12: DABUR | E12: 441.7 | F12: 177.37 | G12: =F12*E12 -> 78344.329 | H12: =I12-K12 -> 723.42 | I12: 1301.43 | J12: =G12+H12 -> 79067.749 | K12: 578.01 | L12: 12984.69 | M12: 2879.69 | N12: 1819.42

Sheet Return on Market
B2: Return on Market
B4: Years | C4: Annual
B5: 2000 | C5: -0.1465 | E5: Average Return | F5: =AVERAGE(C5:C30) -> 0.15149231
B6: 2001 | C6: -0.1618 | E6: Dividend Yield 1 | F6: 0.0128
B7: 2002 | C7: 0.0325 | E7: Total Market Return | F7: =SUM(F5:F6) -> 0.16429231
B8: 2003 | C8: 0.719
B9: 2004 | C9: 0.1068
B10: 2005 | C10: 0.3634
B11: 2006 | C11: 0.3983
B12: 2007 | C12: 0.5477
B13: 2008 | C13: -0.5179
B14: 2009 | C14: 0.7576
B15: 2010 | C15: 0.1795
B16: 2011 | C16: -0.2462
B17: 2012 | C17: 0.277
B18: 2013 | C18: 0.0676
B19: 2014 | C19: 0.3139
... B23: 2018 | C23: 0.0315
B24: 2019 | C24: 0.1202 | E24: Notes:
B25: 2020 | C25: 0.149 | E25: 1.The dividend yield is taken from the investors.com.
B26: 2021 | C26: 0.2412
B27: 2022 | C27: 0.0432
B28: 2023 | C28: 0.1942
B29: 2024 | C29: 0.0875
B30: 2025 | C30: 0.1051

Sheet Profit & Loss
A1: ='Data Sheet'!B1 -> ITC LTD | H1: =UPDATE | M1: SCREENER.IN
A3: Narration | B3: ='Data Sheet'!B16 -> 42460 | C3: ='Data Sheet'!C16 -> 42825 | D3: ='Data Sheet'!D16 -> 43190 | E3: ='Data Sheet'!E16 -> 43555 | F3: ='Data Sheet'!F16 -> 43921 | G3: ='Data Sheet'!G16 -> 44286 | H3: ='Data Sheet'!H16 -> 44651 | I3: ='Data Sheet'!I16 -> 45016 | ... K3: ='Data Sheet'!K16 -> 45747 | L3: Trailing | M3: Best Case | N3: Worst Case
A4: Sales | B4: ='Data Sheet'!B17 -> 39192.1 | C4: ='Data Sheet'!C17 -> 42767.6 | D4: ='Data Sheet'!D17 -> 43448.94 | E4: ='Data Sheet'!E17 -> 48339.58 | F4: ='Data Sheet'!F17 -> 49387.7 | G4: ='Data Sheet'!G17 -> 49257.45 | H4: ='Data Sheet'!H17 -> 60644.54 | I4: ='Data Sheet'!I17 -> 70919.03 | ... K4: ='Data Sheet'!K17 -> 75323.34 | L4: =SUM(Quarters!H4:K4) -> 79808.72 | M4: =$K4+M23*K4 -> 83518.968 | N4: =$K4+N23*L4 -> 81303.23
A5: Expenses | B5: =SUM('Data Sheet'!B18,'Data Sheet'!B20:B24, -1*'Data Sheet'!B19) -> 24660.61 | C5: =SUM('Data Sheet'!C18,'Data Sheet'!C20:C24, -1*'Data Sheet'!C19) -> 27298.09 | D5: =SUM('Data Sheet'!D18,'Data Sheet'!D20:D24, -1*'Data Sheet'!D19) -> 26928.35 | E5: =SUM('Data Sheet'!E18,'Data Sheet'!E20:E24, -1*'Data Sheet'!E19) -> 29802.19 | F5: =SUM('Data Sheet'!F18,'Data Sheet'!F20:F24, -1*'Data Sheet'!F19) -> 30044.16 | G5: =SUM('Data Sheet'!G18,'Data Sheet'!G20:G24, -1*'Data Sheet'!G19) -> 32192.67 | H5: =SUM('Data Sheet'!H18,'Data Sheet'!H20:H24, -1*'Data Sheet'!H19) -> 40021.39 | I5: =SUM('Data Sheet'!I18,'Data Sheet'!I20:I24, -1*'Data Sheet'!I19) -> 45214.77 | ... K5: =SUM('Data Sheet'!K18,'Data Sheet'!K20:K24, -1*'Data Sheet'!K19) -> 49483.89 | L5: =SUM(Quarters!H5:K5) -> 52895.65 | M5: =M4-M6 -> 53597.014 | N5: =N4-N6 -> 53886.182
A6: Operating Profit | B6: =B4-B5 -> 14531.49 | C6: =C4-C5 -> 15469.51 | D6: =D4-D5 -> 16520.59 | E6: =E4-E5 -> 18537.39 | F6: =F4-F5 -> 19343.54 | G6: =G4-G5 -> 17064.78 | H6: =H4-H5 -> 20623.15 | I6: =I4-I5 -> 25704.26 | ... K6: =K4-K5 -> 25839.45 | L6: =SUM(Quarters!H6:K6) -> 26913.07 | M6: =M4*M24 -> 29921.955 | N6: =N4*N24 -> 27417.048
A7: Other Income | B7: ='Data Sheet'!B25 -> 1483.11 | C7: ='Data Sheet'!C25 -> 1758.63 | D7: ='Data Sheet'!D25 -> 2239.81 | E7: ='Data Sheet'!E25 -> 2080.44 | F7: ='Data Sheet'!F25 -> 2417.32 | G7: ='Data Sheet'!G25 -> 2576.95 | H7: ='Data Sheet'!H25 -> 1909.72 | I7: ='Data Sheet'!I25 -> 2097.64 | ... K7: ='Data Sheet'!K25 -> 17794.88 | L7: =SUM(Quarters!H7:K7) -> 17202.94 | M7: 0 | N7: 0
A8: Depreciation | B8: ='Data Sheet'!B26 -> 1077.4 | C8: ='Data Sheet'!C26 -> 1152.79 | D8: ='Data Sheet'!D26 -> 1236.28 | E8: ='Data Sheet'!E26 -> 1396.61 | F8: ='Data Sheet'!F26 -> 1644.91 | G8: ='Data Sheet'!G26 -> 1645.59 | H8: ='Data Sheet'!H26 -> 1732.41 | I8: ='Data Sheet'!I26 -> 1809.01 | ... K8: ='Data Sheet'!K26 -> 1646.32 | L8: =SUM(Quarters!H8:K8) -> 1699.61 | M8: =+$L8 -> 1699.61 | N8: =+$L8 -> 1699.61
A9: Interest | B9: ='Data Sheet'!B27 -> 78.13 | C9: ='Data Sheet'!C27 -> 49.03 | D9: ='Data Sheet'!D27 -> 115.01 | E9: ='Data Sheet'!E27 -> 71.4 | F9: ='Data Sheet'!F27 -> 81.38 | G9: ='Data Sheet'!G27 -> 57.97 | H9: ='Data Sheet'!H27 -> 59.99 | I9: ='Data Sheet'!I27 -> 77.77 | ... K9: ='Data Sheet'!K27 -> 45.06 | L9: =SUM(Quarters!H9:K9) -> 66.9 | M9: =+$L9 -> 66.9 | N9: =+$L9 -> 66.9
A10: Profit before tax | B10: ='Data Sheet'!B28 -> 14859.07 | C10: ='Data Sheet'!C28 -> 16026.32 | D10: ='Data Sheet'!D28 -> 17409.11 | E10: ='Data Sheet'!E28 -> 19149.82 | F10: ='Data Sheet'!F28 -> 20034.57 | G10: ='Data Sheet'!G28 -> 17938.17 | H10: ='Data Sheet'!H28 -> 20740.47 | I10: ='Data Sheet'!I28 -> 25915.12 | ... K10: ='Data Sheet'!K28 -> 41942.95 | L10: =SUM(Quarters!H10:K10) -> 42349.5 | M10: =M6+M7-SUM(M8:M9) -> 28155.445 | N10: =N6+N7-SUM(N8:N9) -> 25650.538
A11: Tax | B11: ='Data Sheet'!B29 -> 5358.21 | C11: ='Data Sheet'!C29 -> 5549.09 | D11: ='Data Sheet'!D29 -> 5916.43 | E11: ='Data Sheet'!E29 -> 6313.92 | F11: ='Data Sheet'!F29 -> 4441.79 | G11: ='Data Sheet'!G29 -> 4555.29 | H11: ='Data Sheet'!H29 -> 5237.34 | I11: ='Data Sheet'!I29 -> 6438.4 | ... K11: ='Data Sheet'!K29 -> 6890.47 | L11: =SUM(Quarters!H11:K11) -> 6993.21 | M11: =IF($L10>0,$L11/$L10,0) -> 0.16513088 | N11: =IF($L10>0,$L11/$L10,0) -> 0.16513088
A12: Net profit | B12: ='Data Sheet'!B30 -> 9344.45 | C12: ='Data Sheet'!C30 -> 10289.44 | D12: ='Data Sheet'!D30 -> 11271.2 | E12: ='Data Sheet'!E30 -> 12592.33 | F12: ='Data Sheet'!F30 -> 15306.23 | G12: ='Data Sheet'!G30 -> 13161.19 | H12: ='Data Sheet'!H30 -> 15242.66 | I12: ='Data Sheet'!I30 -> 19191.66 | ... K12: ='Data Sheet'!K30 -> 34746.63 | L12: =SUM(Quarters!H12:K12) -> 35028.87 | M12: =M10-M11*M10 -> 23506.111 | N12: =N10-N11*N10 -> 21414.842
A13: EPS | B13: =IF('Data Sheet'!B93>0,B12/'Data Sheet'!B93,0) -> 7.7413676 | C13: =IF('Data Sheet'!C93>0,C12/'Data Sheet'!C93,0) -> 8.4704875 | D13: =IF('Data Sheet'!D93>0,D12/'Data Sheet'!D93,0) -> 9.2354334 | E13: =IF('Data Sheet'!E93>0,E12/'Data Sheet'!E93,0) -> 10.272242 | F13: =IF('Data Sheet'!F93>0,F12/'Data Sheet'!F93,0) -> 12.451986 | G13: =IF('Data Sheet'!G93>0,G12/'Data Sheet'!G93,0) -> 10.692505 | H13: =IF('Data Sheet'!H93>0,H12/'Data Sheet'!H93,0) -> 12.368976 | I13: =IF('Data Sheet'!I93>0,I12/'Data Sheet'!I93,0) -> 15.442276 | ... K13: =IF('Data Sheet'!K93>0,K12/'Data Sheet'!K93,0) -> 27.765984 | L13: =IF('Data Sheet'!$B6>0,'Profit & Loss'!L12/'Data Sheet'!$B6,0) -> 27.95719 | M13: =IF('Data Sheet'!$B6>0,'Profit & Loss'!M12/'Data Sheet'!$B6,0) -> 18.760663 | N13: =IF('Data Sheet'!$B6>0,'Profit & Loss'!N12/'Data Sheet'!$B6,0) -> 17.091582
A14: Price to earning | B14: =IF(B15>0,B15/B13,"") -> 26.497902 | C14: =IF(C15>0,C15/C13,"") -> 31.019466 | D14: =IF(D15>0,D15/D13,"") -> 25.93273 | E14: =IF(E15>0,E15/E13,"") -> 27.12553 | F14: =IF(F15>0,F15/F13,"") -> 12.925649 | G14: =IF(G15>0,G15/G13,"") -> 19.155475 | H14: =IF(H15>0,H15/H13,"") -> 18.995914 | I14: =IF(I15>0,I15/I13,"") -> 23.2796 | ... K14: =IF(K15>0,K15/K13,"") -> 14.757266 | L14: =IF(L13>0,L15/L13,0) -> 11.031152 | M14: =M25 -> 18.392714 | N14: =N25 -> 11.031152
A15: Price | B15: ='Data Sheet'!B90 -> 205.13 | C15: ='Data Sheet'!C90 -> 262.75 | D15: ='Data Sheet'!D90 -> 239.5 | E15: ='Data Sheet'!E90 -> 278.64 | F15: ='Data Sheet'!F90 -> 160.95 | G15: ='Data Sheet'!G90 -> 204.82 | H15: ='Data Sheet'!H90 -> 234.96 | I15: ='Data Sheet'!I90 -> 359.49 | ... K15: ='Data Sheet'!K90 -> 409.75 | L15: ='Data Sheet'!B8 -> 308.4 | M15: =M13*M14 -> 345.0595 | N15: =N13*N14 -> 188.53984
A17: RATIOS:
A18: Dividend Payout | B18: =IF('Data Sheet'!B30>0, 'Data Sheet'!B31/'Data Sheet'!B30, 0) -> 0.73199814 | C18: =IF('Data Sheet'!C30>0, 'Data Sheet'!C31/'Data Sheet'!C30, 0) -> 0.56077104 | D18: =IF('Data Sheet'!D30>0, 'Data Sheet'!D31/'Data Sheet'!D30, 0) -> 0.5576345 | E18: =IF('Data Sheet'!E30>0, 'Data Sheet'!E31/'Data Sheet'!E30, 0) -> 0.55976138 | F18: =IF('Data Sheet'!F30>0, 'Data Sheet'!F31/'Data Sheet'!F30, 0) -> 0.81513083 | G18: =IF('Data Sheet'!G30>0, 'Data Sheet'!G31/'Data Sheet'!G30, 0) -> 1.0053772 | H18: =IF('Data Sheet'!H30>0, 'Data Sheet'!H31/'Data Sheet'!H30, 0) -> 0.92974586 | I18: =IF('Data Sheet'!I30>0, 'Data Sheet'!I31/'Data Sheet'!I30, 0) -> 1.0037381 | ... K18: =IF('Data Sheet'!K30>0, 'Data Sheet'!K31/'Data Sheet'!K30, 0) -> 0.51681933
A19: OPM | B19: =IF(B6>0,B6/B4,0) -> 0.370776 | C19: =IF(C6>0,C6/C4,0) -> 0.36171097 | D19: =IF(D6>0,D6/D4,0) -> 0.38022999 | E19: =IF(E6>0,E6/E4,0) -> 0.38348265 | F19: =IF(F6>0,F6/F4,0) -> 0.39166716 | G19: =IF(G6>0,G6/G4,0) -> 0.34644059 | H19: =IF(H6>0,H6/H4,0) -> 0.34006606 | I19: =IF(I6>0,I6/I4,0) -> 0.36244517 | ... L19: =IF(L6>0,L6/L4,0) -> 0.33721967
G22: TRENDS: | H22: 10 YEARS | I22: 7 YEARS | J22: 5 YEARS | K22: 3 YEARS | L22: RECENT | M22: BEST | N22: WORST
G23: Sales Growth | H23: =IF(B4=0,"",POWER($K4/B4,1/9)-1) -> 0.075290157 | I23: =IF(D4=0,"",POWER($K4/D4,1/7)-1) -> 0.081772082 | J23: =IF(F4=0,"",POWER($K4/F4,1/5)-1) -> 0.088083322 | K23: =IF(H4=0,"",POWER($K4/H4, 1/3)-1) -> 0.074927782 | L23: =IF(ISERROR(MAX(IF(J4=0,"",(K4-J4)/J4),IF(K4=0,"",(L4-K4)/K4))),"",MAX(IF(J4=0,"",(K4-J4)/J4),IF(K4=0,"",(L4-K4)/K4))) -> 0.10880596 | M23: =MAX(K23:L23) -> 0.10880596 | N23: =MIN(H23:L23) -> 0.074927782
G24: OPM | H24: =IF(SUM(B4:$K$4)=0,"",SUMPRODUCT(B19:$K$19,B4:$K$4)/SUM(B4:$K$4)) -> 0.36333562 | I24: =IF(SUM(E4:$K$4)=0,"",SUMPRODUCT(E19:$K$19,E4:$K$4)/SUM(E4:$K$4)) -> 0.36106877 | J24: =IF(SUM(G4:$K$4)=0,"",SUMPRODUCT(G19:$K$19,G4:$K$4)/SUM(G4:$K$4)) -> 0.35306244 | K24: =IF(SUM(I4:$K$4)=0, "", SUMPRODUCT(I19:$K$19,I4:$K$4)/SUM(I4:$K$4)) -> 0.35826538 | L24: =L19 -> 0.33721967 | M24: =MAX(K24:L24) -> 0.35826538 | N24: =MIN(H24:L24) -> 0.33721967
G25: Price to Earning | H25: =IF(ISERROR(AVERAGEIF(B14:$L14,">0")),"",AVERAGEIF(B14:$L14,">0")) -> 21.383956 | I25: =IF(ISERROR(AVERAGEIF(E14:$L14,">0")),"",AVERAGEIF(E14:$L14,">0")) -> 18.971678 | J25: =IF(ISERROR(AVERAGEIF(G14:$L14,">0")),"",AVERAGEIF(G14:$L14,">0")) -> 18.620374 | K25: =IF(ISERROR(AVERAGEIF(I14:$L14,">0")),"",AVERAGEIF(I14:$L14,">0")) -> 18.392714 | L25: =L14 -> 11.031152 | M25: =MAX(K25:L25) -> 18.392714 | N25: =MIN(H25:L25) -> 11.031152

Sheet Quarters
A1: ='Profit & Loss'!A1 -> ITC LTD | E1: =UPDATE | J1: SCREENER.IN
A3: Narration | B3: ='Data Sheet'!B41 -> 45199 | C3: ='Data Sheet'!C41 -> 45291 | D3: ='Data Sheet'!D41 -> 45382 | E3: ='Data Sheet'!E41 -> 45473 | F3: ='Data Sheet'!F41 -> 45565 | G3: ='Data Sheet'!G41 -> 45657 | H3: ='Data Sheet'!H41 -> 45747 | I3: ='Data Sheet'!I41 -> 45838 | ... K3: ='Data Sheet'!K41 -> 46022
A4: Sales | B4: ='Data Sheet'!B42 -> 17774.47 | C4: ='Data Sheet'!C42 -> 17195.24 | D4: ='Data Sheet'!D42 -> 17037.8 | E4: ='Data Sheet'!E42 -> 17777.81 | F4: ='Data Sheet'!F42 -> 19990.36 | G4: ='Data Sheet'!G42 -> 18790.17 | H4: ='Data Sheet'!H42 -> 18765 | I4: ='Data Sheet'!I42 -> 21494.79 | ... K4: ='Data Sheet'!K42 -> 20047.3
A5: Expenses | B5: ='Data Sheet'!B43 -> 11320.23 | C5: ='Data Sheet'!C43 -> 10985.01 | D5: ='Data Sheet'!D43 -> 10735.73 | E5: ='Data Sheet'!E43 -> 11232.97 | F5: ='Data Sheet'!F43 -> 13438.28 | G5: ='Data Sheet'!G43 -> 12428.27 | H5: ='Data Sheet'!H43 -> 12245.61 | I5: ='Data Sheet'!I43 -> 14678.32 | ... K5: ='Data Sheet'!K43 -> 13164.78
A6: Operating Profit | B6: ='Data Sheet'!B50 -> 6454.24 | C6: ='Data Sheet'!C50 -> 6210.23 | D6: ='Data Sheet'!D50 -> 6302.07 | E6: ='Data Sheet'!E50 -> 6544.84 | F6: ='Data Sheet'!F50 -> 6552.08 | G6: ='Data Sheet'!G50 -> 6361.9 | H6: ='Data Sheet'!H50 -> 6519.39 | I6: ='Data Sheet'!I50 -> 6816.47 | ... K6: ='Data Sheet'!K50 -> 6882.52
A7: Other Income | B7: ='Data Sheet'!B44 -> 673.5 | C7: ='Data Sheet'!C44 -> 820.26 | D7: ='Data Sheet'!D44 -> 868 | E7: ='Data Sheet'!E44 -> 771.13 | F7: ='Data Sheet'!F44 -> 690.31 | G7: ='Data Sheet'!G44 -> 803.4 | H7: ='Data Sheet'!H44 -> 15391.28 | I7: ='Data Sheet'!I44 -> 750.97 | ... K7: ='Data Sheet'!K44 -> 321.85
A8: Depreciation | B8: ='Data Sheet'!B45 -> 453.04 | C8: ='Data Sheet'!C45 -> 384.04 | D8: ='Data Sheet'!D45 -> 385.09 | E8: ='Data Sheet'!E45 -> 403.13 | F8: ='Data Sheet'!F45 -> 416.18 | G8: ='Data Sheet'!G45 -> 415.98 | H8: ='Data Sheet'!H45 -> 411.03 | I8: ='Data Sheet'!I45 -> 422.96 | ... K8: ='Data Sheet'!K45 -> 430.82
A9: Interest | B9: ='Data Sheet'!B46 -> 9.87 | C9: ='Data Sheet'!C46 -> 11.94 | D9: ='Data Sheet'!D46 -> 10.72 | E9: ='Data Sheet'!E46 -> 9.6 | F9: ='Data Sheet'!F46 -> 14.73 | G9: ='Data Sheet'!G46 -> 9.82 | H9: ='Data Sheet'!H46 -> 10.91 | I9: ='Data Sheet'!I46 -> 16.47 | ... K9: ='Data Sheet'!K46 -> 19.47
A10: Profit before tax | B10: ='Data Sheet'!B47 -> 6664.83 | C10: ='Data Sheet'!C47 -> 6634.51 | D10: ='Data Sheet'!D47 -> 6774.26 | E10: ='Data Sheet'!E47 -> 6903.24 | F10: ='Data Sheet'!F47 -> 6811.48 | G10: ='Data Sheet'!G47 -> 6739.5 | H10: ='Data Sheet'!H47 -> 21488.73 | I10: ='Data Sheet'!I47 -> 7128.01 | ... K10: ='Data Sheet'!K47 -> 6754.08
A11: Tax | B11: ='Data Sheet'!B48 -> 1700.31 | C11: ='Data Sheet'!C48 -> 1227.99 | D11: ='Data Sheet'!D48 -> 1583.55 | E11: ='Data Sheet'!E48 -> 1726.25 | F11: ='Data Sheet'!F48 -> 1757.05 | G11: ='Data Sheet'!G48 -> 1726.32 | H11: ='Data Sheet'!H48 -> 1680.85 | I11: ='Data Sheet'!I48 -> 1784.6 | ... K11: ='Data Sheet'!K48 -> 1735.63
A12: Net profit | B12: ='Data Sheet'!B49 -> 4898.07 | C12: ='Data Sheet'!C49 -> 5335.23 | D12: ='Data Sheet'!D49 -> 5120.55 | E12: ='Data Sheet'!E49 -> 5091.59 | F12: ='Data Sheet'!F49 -> 4992.87 | G12: ='Data Sheet'!G49 -> 4934.8 | H12: ='Data Sheet'!H49 -> 19727.37 | I12: ='Data Sheet'!I49 -> 5244.2 | ... K12: ='Data Sheet'!K49 -> 4931.19
A14: OPM | B14: =IF(B4>0,B6/B4,"") -> 0.36311856 | C14: =IF(C4>0,C6/C4,"") -> 0.36115983 | D14: =IF(D4>0,D6/D4,"") -> 0.36988754 | E14: =IF(E4>0,E6/E4,"") -> 0.36814658 | F14: =IF(F4>0,F6/F4,"") -> 0.32776198 | G14: =IF(G4>0,G6/G4,"") -> 0.33857597 | H14: =IF(H4>0,H6/H4,"") -> 0.34742286 | I14: =IF(I4>0,I6/I4,"") -> 0.31712196 | ... K14: =IF(K4>0,K6/K4,"") -> 0.34331406

Sheet Balance Sheet
A1: ='Profit & Loss'!A1 -> ITC LTD | E1: =UPDATE | J1: SCREENER.IN
A3: Narration | B3: ='Data Sheet'!B56 -> 42460 | C3: ='Data Sheet'!C56 -> 42825 | D3: ='Data Sheet'!D56 -> 43190 | E3: ='Data Sheet'!E56 -> 43555 | F3: ='Data Sheet'!F56 -> 43921 | G3: ='Data Sheet'!G56 -> 44286 | H3: ='Data Sheet'!H56 -> 44651 | I3: ='Data Sheet'!I56 -> 45016 | ... K3: ='Data Sheet'!K56 -> 45747
A4: Equity Share Capital | B4: ='Data Sheet'!B57 -> 804.72 | C4: ='Data Sheet'!C57 -> 1214.74 | D4: ='Data Sheet'!D57 -> 1220.43 | E4: ='Data Sheet'!E57 -> 1225.86 | F4: ='Data Sheet'!F57 -> 1229.22 | G4: ='Data Sheet'!G57 -> 1230.88 | H4: ='Data Sheet'!H57 -> 1232.33 | I4: ='Data Sheet'!I57 -> 1242.8 | ... K4: ='Data Sheet'!K57 -> 1251.41
A5: Reserves | B5: ='Data Sheet'!B58 -> 41874.8 | C5: ='Data Sheet'!C58 -> 45198.19 | D5: ='Data Sheet'!D58 -> 51289.68 | E5: ='Data Sheet'!E58 -> 57915.01 | F5: ='Data Sheet'!F58 -> 64044.04 | G5: ='Data Sheet'!G58 -> 59116.46 | H5: ='Data Sheet'!H58 -> 61223.24 | I5: ='Data Sheet'!I58 -> 67912.46 | ... K5: ='Data Sheet'!K58 -> 68778.64
A6: Borrowings | B6: ='Data Sheet'!B59 -> 83.78 | C6: ='Data Sheet'!C59 -> 45.72 | D6: ='Data Sheet'!D59 -> 35.92 | E6: ='Data Sheet'!E59 -> 13.44 | F6: ='Data Sheet'!F59 -> 277.45 | G6: ='Data Sheet'!G59 -> 270.83 | H6: ='Data Sheet'!H59 -> 249.44 | I6: ='Data Sheet'!I59 -> 306.04 | ... K6: ='Data Sheet'!K59 -> 284.54
A7: Other Liabilities | B7: ='Data Sheet'!B60 -> 8888.04 | C7: ='Data Sheet'!C60 -> 9439.67 | D7: ='Data Sheet'!D60 -> 11694.85 | E7: ='Data Sheet'!E60 -> 12584.73 | F7: ='Data Sheet'!F60 -> 11760.04 | G7: ='Data Sheet'!G60 -> 13142.59 | H7: ='Data Sheet'!H60 -> 14491.01 | I7: ='Data Sheet'!I60 -> 16369.66 | ... K7: ='Data Sheet'!K60 -> 17688.11
A8: Total | B8: ='Data Sheet'!B61 -> 51651.34 | C8: ='Data Sheet'!C61 -> 55898.32 | D8: ='Data Sheet'!D61 -> 64240.88 | E8: ='Data Sheet'!E61 -> 71739.04 | F8: ='Data Sheet'!F61 -> 77310.75 | G8: ='Data Sheet'!G61 -> 73760.76 | H8: ='Data Sheet'!H61 -> 77196.02 | I8: ='Data Sheet'!I61 -> 85830.96 | ... K8: ='Data Sheet'!K61 -> 88002.7
A10: Net Block | B10: ='Data Sheet'!B62 -> 15106.63 | C10: ='Data Sheet'!C62 -> 15893.48 | D10: ='Data Sheet'!D62 -> 16523.96 | E10: ='Data Sheet'!E62 -> 19374.19 | F10: ='Data Sheet'!F62 -> 21713.34 | G10: ='Data Sheet'!G62 -> 23298.48 | H10: ='Data Sheet'!H62 -> 24231.59 | I10: ='Data Sheet'!I62 -> 25851.27 | ... K10: ='Data Sheet'!K62 -> 21954.85
A11: Capital Work in Progress | B11: ='Data Sheet'!B63 -> 2559.72 | C11: ='Data Sheet'!C63 -> 3729.89 | D11: ='Data Sheet'!D63 -> 5508.33 | E11: ='Data Sheet'!E63 -> 4136.42 | F11: ='Data Sheet'!F63 -> 3256.46 | G11: ='Data Sheet'!G63 -> 4011.29 | H11: ='Data Sheet'!H63 -> 3225.54 | I11: ='Data Sheet'!I63 -> 3003.3 | ... K11: ='Data Sheet'!K63 -> 1090.91
A12: Investments | B12: ='Data Sheet'!B64 -> 11747.59 | C12: ='Data Sheet'!C64 -> 17581.38 | D12: ='Data Sheet'!D64 -> 22052.86 | E12: ='Data Sheet'!E64 -> 25043.49 | F12: ='Data Sheet'!F64 -> 28663.35 | G12: ='Data Sheet'!G64 -> 24870.87 | H12: ='Data Sheet'!H64 -> 24841.01 | I12: ='Data Sheet'!I64 -> 29415.02 | ... K12: ='Data Sheet'!K64 -> 34719.82
A13: Other Assets | B13: ='Data Sheet'!B65 -> 22237.4 | C13: ='Data Sheet'!C65 -> 18693.57 | D13: ='Data Sheet'!D65 -> 20155.73 | E13: ='Data Sheet'!E65 -> 23184.94 | F13: ='Data Sheet'!F65 -> 23677.6 | G13: ='Data Sheet'!G65 -> 21580.12 | H13: ='Data Sheet'!H65 -> 24897.88 | I13: ='Data Sheet'!I65 -> 27561.37 | ... K13: ='Data Sheet'!K65 -> 30237.12
A14: Total | B14: ='Data Sheet'!B66 -> 51651.34 | C14: ='Data Sheet'!C66 -> 55898.32 | D14: ='Data Sheet'!D66 -> 64240.88 | E14: ='Data Sheet'!E66 -> 71739.04 | F14: ='Data Sheet'!F66 -> 77310.75 | G14: ='Data Sheet'!G66 -> 73760.76 | H14: ='Data Sheet'!H66 -> 77196.02 | I14: ='Data Sheet'!I66 -> 85830.96 | ... K14: ='Data Sheet'!K66 -> 88002.7
A16: Working Capital | B16: =B13-B7 -> 13349.36 | C16: =C13-C7 -> 9253.9 | D16: =D13-D7 -> 8460.88 | E16: =E13-E7 -> 10600.21 | F16: =F13-F7 -> 11917.56 | G16: =G13-G7 -> 8437.53 | H16: =H13-H7 -> 10406.87 | I16: =I13-I7 -> 11191.71 | ... K16: =K13-K7 -> 12549.01
A17: Debtors | B17: ='Data Sheet'!B67 -> 1917.18 | C17: ='Data Sheet'!C67 -> 2474.29 | D17: ='Data Sheet'!D67 -> 2682.29 | E17: ='Data Sheet'!E67 -> 4035.28 | F17: ='Data Sheet'!F67 -> 2562.48 | G17: ='Data Sheet'!G67 -> 2501.7 | H17: ='Data Sheet'!H67 -> 2461.9 | I17: ='Data Sheet'!I67 -> 2956.17 | ... K17: ='Data Sheet'!K67 -> 4719.67
A18: Inventory | B18: ='Data Sheet'!B68 -> 9062.1 | C18: ='Data Sheet'!C68 -> 8116.1 | D18: ='Data Sheet'!D68 -> 7495.09 | E18: ='Data Sheet'!E68 -> 7859.56 | F18: ='Data Sheet'!F68 -> 8879.33 | G18: ='Data Sheet'!G68 -> 10397.16 | H18: ='Data Sheet'!H68 -> 10864.15 | I18: ='Data Sheet'!I68 -> 11771.16 | ... K18: ='Data Sheet'!K68 -> 15637.56
A20: Debtor Days | B20: =IF('Profit & Loss'!B4>0,'Balance Sheet'!B17/('Profit & Loss'!B4/365),0) -> 17.854892 | C20: =IF('Profit & Loss'!C4>0,'Balance Sheet'!C17/('Profit & Loss'!C4/365),0) -> 21.116823 | D20: =IF('Profit & Loss'!D4>0,'Balance Sheet'!D17/('Profit & Loss'!D4/365),0) -> 22.53302 | E20: =IF('Profit & Loss'!E4>0,'Balance Sheet'!E17/('Profit & Loss'!E4/365),0) -> 30.469383 | F20: =IF('Profit & Loss'!F4>0,'Balance Sheet'!F17/('Profit & Loss'!F4/365),0) -> 18.938019 | G20: =IF('Profit & Loss'!G4>0,'Balance Sheet'!G17/('Profit & Loss'!G4/365),0) -> 18.537714 | H20: =IF('Profit & Loss'!H4>0,'Balance Sheet'!H17/('Profit & Loss'!H4/365),0) -> 14.817385 | I20: =IF('Profit & Loss'!I4>0,'Balance Sheet'!I17/('Profit & Loss'!I4/365),0) -> 15.214563 | ... K20: =IF('Profit & Loss'!K4>0,'Balance Sheet'!K17/('Profit & Loss'!K4/365),0) -> 22.870462
A21: Inventory Turnover | B21: =IF('Balance Sheet'!B18>0,'Profit & Loss'!B4/'Balance Sheet'!B18,0) -> 4.3248364 | C21: =IF('Balance Sheet'!C18>0,'Profit & Loss'!C4/'Balance Sheet'!C18,0) -> 5.2694767 | D21: =IF('Balance Sheet'!D18>0,'Profit & Loss'!D4/'Balance Sheet'!D18,0) -> 5.7969871 | E21: =IF('Balance Sheet'!E18>0,'Profit & Loss'!E4/'Balance Sheet'!E18,0) -> 6.1504181 | F21: =IF('Balance Sheet'!F18>0,'Profit & Loss'!F4/'Balance Sheet'!F18,0) -> 5.5620976 | G21: =IF('Balance Sheet'!G18>0,'Profit & Loss'!G4/'Balance Sheet'!G18,0) -> 4.737587 | H21: =IF('Balance Sheet'!H18>0,'Profit & Loss'!H4/'Balance Sheet'!H18,0) -> 5.5820787 | I21: =IF('Balance Sheet'!I18>0,'Profit & Loss'!I4/'Balance Sheet'!I18,0) -> 6.0248123 | ... K21: =IF('Balance Sheet'!K18>0,'Profit & Loss'!K4/'Balance Sheet'!K18,0) -> 4.8168218
A23: Return on Equity | B23: =IF(SUM('Balance Sheet'!B4:B5)>0,'Profit & Loss'!B12/SUM('Balance Sheet'!B4:B5),"") -> 0.21894459 | C23: =IF(SUM('Balance Sheet'!C4:C5)>0,'Profit & Loss'!C12/SUM('Balance Sheet'!C4:C5),"") -> 0.22169339 | D23: =IF(SUM('Balance Sheet'!D4:D5)>0,'Profit & Loss'!D12/SUM('Balance Sheet'!D4:D5),"") -> 0.21464819 | E23: =IF(SUM('Balance Sheet'!E4:E5)>0,'Profit & Loss'!E12/SUM('Balance Sheet'!E4:E5),"") -> 0.21292095 | F23: =IF(SUM('Balance Sheet'!F4:F5)>0,'Profit & Loss'!F12/SUM('Balance Sheet'!F4:F5),"") -> 0.23449465 | G23: =IF(SUM('Balance Sheet'!G4:G5)>0,'Profit & Loss'!G12/SUM('Balance Sheet'!G4:G5),"") -> 0.21809064 | H23: =IF(SUM('Balance Sheet'!H4:H5)>0,'Profit & Loss'!H12/SUM('Balance Sheet'!H4:H5),"") -> 0.24405605 | I23: =IF(SUM('Balance Sheet'!I4:I5)>0,'Profit & Loss'!I12/SUM('Balance Sheet'!I4:I5),"") -> 0.27751555 | ... K23: =IF(SUM('Balance Sheet'!K4:K5)>0,'Profit & Loss'!K12/SUM('Balance Sheet'!K4:K5),"") -> 0.49616743
A24: Return on Capital Emp | C24: =IF((B4+B5+B6+C4+C5+C6)>0,('Profit & Loss'!C10+'Profit & Loss'!C9)*2/(B4+B5+B6+C4+C5+C6),"") -> 0.36034518 | D24: =IF((C4+C5+C6+D4+D5+D6)>0,('Profit & Loss'!D10+'Profit & Loss'!D9)*2/(C4+C5+C6+D4+D5+D6),"") -> 0.35400589 | E24: =IF((D4+D5+D6+E4+E5+E6)>0,('Profit & Loss'!E10+'Profit & Loss'!E9)*2/(D4+D5+D6+E4+E5+E6),"") -> 0.34415688 | F24: =IF((E4+E5+E6+F4+F5+F6)>0,('Profit & Loss'!F10+'Profit & Loss'!F9)*2/(E4+E5+E6+F4+F5+F6),"") -> 0.32261652 | G24: =IF((F4+F5+F6+G4+G5+G6)>0,('Profit & Loss'!G10+'Profit & Loss'!G9)*2/(F4+F5+F6+G4+G5+G6),"") -> 0.28527066 | H24: =IF((G4+G5+G6+H4+H5+H6)>0,('Profit & Loss'!H10+'Profit & Loss'!H9)*2/(G4+G5+G6+H4+H5+H6),"") -> 0.33733253 | I24: =IF((H4+H5+H6+I4+I5+I6)>0,('Profit & Loss'!I10+'Profit & Loss'!I9)*2/(H4+H5+H6+I4+I5+I6),"") -> 0.39333609 | J24: =IF((I4+I5+I6+J4+J5+J6)>0,('Profit & Loss'!J10+'Profit & Loss'!J9)*2/(I4+I5+I6+J4+J5+J6),"") -> 0.37429273 | K24: =IF((J4+J5+J6+K4+K5+K6)>0,('Profit & Loss'!K10+'Profit & Loss'!K9)*2/(J4+J5+J6+K4+K5+K6),"") -> 0.57864605

Sheet Cash Flow
A1: ='Balance Sheet'!A1 -> ITC LTD | E1: =UPDATE | J1: SCREENER.IN
A3: Narration | B3: ='Data Sheet'!B81 -> 42460 | C3: ='Data Sheet'!C81 -> 42825 | D3: ='Data Sheet'!D81 -> 43190 | E3: ='Data Sheet'!E81 -> 43555 | F3: ='Data Sheet'!F81 -> 43921 | G3: ='Data Sheet'!G81 -> 44286 | H3: ='Data Sheet'!H81 -> 44651 | I3: ='Data Sheet'!I81 -> 45016 | ... K3: ='Data Sheet'!K81 -> 45747
A4: Cash from Operating Activity | B4: ='Data Sheet'!B82 -> 9799.04 | C4: ='Data Sheet'!C82 -> 10627.31 | D4: ='Data Sheet'!D82 -> 13169.4 | E4: ='Data Sheet'!E82 -> 12583.41 | F4: ='Data Sheet'!F82 -> 14689.66 | G4: ='Data Sheet'!G82 -> 12526.97 | H4: ='Data Sheet'!H82 -> 15775.51 | I4: ='Data Sheet'!I82 -> 18877.55 | ... K4: ='Data Sheet'!K82 -> 17627.04
A5: Cash from Investing Activity | B5: ='Data Sheet'!B83 -> -3920.73 | C5: ='Data Sheet'!C83 -> -3250.93 | D5: ='Data Sheet'!D83 -> -7113.89 | E5: ='Data Sheet'!E83 -> -5545.68 | F5: ='Data Sheet'!F83 -> -6174.02 | G5: ='Data Sheet'!G83 -> 5739.98 | H5: ='Data Sheet'!H83 -> -2238.49 | I5: ='Data Sheet'!I83 -> -5732.29 | ... K5: ='Data Sheet'!K83 -> -563.84
A6: Cash from Financing Activity | B6: ='Data Sheet'!B84 -> -5612.52 | C6: ='Data Sheet'!C84 -> -7301.03 | D6: ='Data Sheet'!D84 -> -6221.13 | E6: ='Data Sheet'!E84 -> -6868.64 | F6: ='Data Sheet'!F84 -> -8181.48 | G6: ='Data Sheet'!G84 -> -18633.83 | H6: ='Data Sheet'!H84 -> -13580.5 | I6: ='Data Sheet'!I84 -> -13006.03 | ... K6: ='Data Sheet'!K84 -> -17037.4
A7: Net Cash Flow | B7: ='Data Sheet'!B85 -> 265.79 | C7: ='Data Sheet'!C85 -> 75.35 | D7: ='Data Sheet'!D85 -> -165.62 | E7: ='Data Sheet'!E85 -> 169.09 | F7: ='Data Sheet'!F85 -> 334.16 | G7: ='Data Sheet'!G85 -> -366.88 | H7: ='Data Sheet'!H85 -> -43.48 | I7: ='Data Sheet'!I85 -> 139.23 | ... K7: ='Data Sheet'!K85 -> 25.8

Sheet Customization
A1: How to use it?
A3: You can customize this workbook as you want.
B4: You can add custom formating, add conditional formating, add your own formulas… do ANYTHING.
B5: Please don't edit the "Data Sheet" only.
A7: After customization, you can upload this back on Screener.
B8: Upload on: | C8: https://www.screener.in/excel/
A10: Download your customized workbooks now onwards.
B11: Now whenever you will "Export to excel" from Screener, it will export your customized file.
A14: TESTING:
B15: This is a testing feature currently.
B16: You can report any formula errors on the worksheet at: support@screener.in

Sheet Data Sheet
A1: COMPANY NAME | B1: ITC LTD | E1: =IF(B2<>B3, "A NEW VERSION OF THE WORKSHEET IS AVAILABLE", "")
A2: LATEST VERSION | B2: 2.1 | E2: PLEASE DO NOT MAKE ANY CHANGES TO THIS SHEET
A3: CURRENT VERSION | B3: 2.1
A5: META
A6: Number of shares | B6: =IF(B9>0, B9/B8, 0) -> 1252.9468
A7: Face Value | B7: 1
A8: Current Price | B8: 308.4
A9: Market Capitalization | B9: 386408.78
A15: PROFIT & LOSS
A16: Report Date | B16: 42460 | C16: 42825 | D16: 43190 | E16: 43555 | F16: 43921 | G16: 44286 | H16: 44651 | I16: 45016 | J16: 45382 | K16: 45747
A17: Sales | B17: 39192.1 | C17: 42767.6 | D17: 43448.94 | E17: 48339.58 | F17: 49387.7 | G17: 49257.45 | H17: 60644.54 | I17: 70919.03 | J17: 67931.94 | K17: 75323.34
A18: Raw Material Cost | B18: 13763.88 | C18: 15456.59 | D18: 14827.72 | E18: 17623.52 | F18: 18048.6 | G18: 20776.71 | H18: 27071.07 | I18: 29364.36 | J18: 27348.57 | K18: 32704.37
A19: Change in Inventory | B19: 195.38 | C19: -592.57 | D19: -1027.76 | E19: 203.19 | F19: 703.13 | G19: 645.27 | H19: 686 | I19: 358.59 | J19: 367.77 | K19: 725.65
A20: Power and Fuel | B20: 571.88 | C20: 584.33 | D20: 653.5 | E20: 746.73 | F20: 780.85 | G20: 699.56 | H20: 889.77 | I20: 1232.34 | J20: 952.9 | K20: 975.35
A21: Other Mfr. Exp | B21: 1581.59 | C21: 1683.9 | D21: 1697.62 | E21: 1871.01 | F21: 1908.29 | G21: 1587.18 | H21: 1887.67 | I21: 2327.8 | J21: 2183.76 | K21: 2345.36
A22: Employee Cost | B22: 3440.97 | C22: 3631.73 | D22: 3760.9 | E22: 4177.88 | F22: 4295.79 | G22: 4463.33 | H22: 4890.55 | I22: 5736.22 | J22: 5548.53 | K22: 6169.78
A23: Selling and admin | B23: 4261.78 | C23: 4179.74 | D23: 3954.87 | E23: 4546.39 | F23: 4488.63 | G23: 4236.77 | H23: 4858.38 | I23: 5604.08 | J23: 5312.45 | K23: 5793.29
A24: Other Expenses | B24: 1235.89 | C24: 1169.23 | D24: 1005.98 | E24: 1039.85 | F24: 1225.13 | G24: 1074.39 | H24: 1109.95 | I24: 1308.56 | J24: 1765.97 | K24: 2221.39
A25: Other Income | B25: 1483.11 | C25: 1758.63 | D25: 2239.81 | E25: 2080.44 | F25: 2417.32 | G25: 2576.95 | H25: 1909.72 | I25: 2097.64 | J25: 3330.45 | K25: 17794.88
A26: Depreciation | B26: 1077.4 | C26: 1152.79 | D26: 1236.28 | E26: 1396.61 | F26: 1644.91 | G26: 1645.59 | H26: 1732.41 | I26: 1809.01 | J26: 1518.05 | K26: 1646.32
A27: Interest | B27: 78.13 | C27: 49.03 | D27: 115.01 | E27: 71.4 | F27: 81.38 | G27: 57.97 | H27: 59.99 | I27: 77.77 | J27: 39.11 | K27: 45.06
... A31: Dividend Amount | B31: 6840.12 | C31: 5770.02 | D31: 6285.21 | E31: 7048.7 | F31: 12476.58 | G31: 13231.96 | H31: 14171.8 | I31: 19263.4 | J31: 17166.46 | K31: 17957.73
A40: Quarters
A41: Report Date | B41: 45199 | C41: 45291 | D41: 45382 | E41: 45473 | F41: 45565 | G41: 45657 | H41: 45747 | I41: 45838 | J41: 45930 | K41: 46022
A42: Sales | B42: 17774.47 | C42: 17195.24 | D42: 17037.8 | E42: 17777.81 | F42: 19990.36 | G42: 18790.17 | H42: 18765 | I42: 21494.79 | J42: 19501.63 | K42: 20047.3
A43: Expenses | B43: 11320.23 | C43: 10985.01 | D43: 10735.73 | E43: 11232.97 | F43: 13438.28 | G43: 12428.27 | H43: 12245.61 | I43: 14678.32 | J43: 12806.94 | K43: 13164.78
A44: Other Income | B44: 673.5 | C44: 820.26 | D44: 868 | E44: 771.13 | F44: 690.31 | G44: 803.4 | H44: 15391.28 | I44: 750.97 | J44: 738.84 | K44: 321.85
A45: Depreciation | B45: 453.04 | C45: 384.04 | D45: 385.09 | E45: 403.13 | F45: 416.18 | G45: 415.98 | H45: 411.03 | I45: 422.96 | J45: 434.8 | K45: 430.82
A46: Interest | B46: 9.87 | C46: 11.94 | D46: 10.72 | E46: 9.6 | F46: 14.73 | G46: 9.82 | H46: 10.91 | I46: 16.47 | J46: 20.05 | K46: 19.47
A47: Profit before tax | B47: 6664.83 | C47: 6634.51 | D47: 6774.26 | E47: 6903.24 | F47: 6811.48 | G47: 6739.5 | H47: 21488.73 | I47: 7128.01 | J47: 6978.68 | K47: 6754.08
A48: Tax | B48: 1700.31 | C48: 1227.99 | D48: 1583.55 | E48: 1726.25 | F48: 1757.05 | G48: 1726.32 | H48: 1680.85 | I48: 1784.6 | J48: 1792.13 | K48: 1735.63
A49: Net profit | B49: 4898.07 | C49: 5335.23 | D49: 5120.55 | E49: 5091.59 | F49: 4992.87 | G49: 4934.8 | H49: 19727.37 | I49: 5244.2 | J49: 5126.11 | K49: 4931.19
A50: Operating Profit | B50: 6454.24 | C50: 6210.23 | D50: 6302.07 | E50: 6544.84 | F50: 6552.08 | G50: 6361.9 | H50: 6519.39 | I50: 6816.47 | J50: 6694.69 | K50: 6882.52
A55: BALANCE SHEET
A56: Report Date | B56: 42460 | C56: 42825 | D56: 43190 | E56: 43555 | F56: 43921 | G56: 44286 | H56: 44651 | I56: 45016 | J56: 45382 | K56: 45747
A57: Equity Share Capital | B57: 804.72 | C57: 1214.74 | D57: 1220.43 | E57: 1225.86 | F57: 1229.22 | G57: 1230.88 | H57: 1232.33 | I57: 1242.8 | J57: 1248.47 | K57: 1251.41
A58: Reserves | B58: 41874.8 | C58: 45198.19 | D58: 51289.68 | E58: 57915.01 | F58: 64044.04 | G58: 59116.46 | H58: 61223.24 | I58: 67912.46 | J58: 73258.53 | K58: 68778.64
A59: Borrowings | B59: 83.78 | C59: 45.72 | D59: 35.92 | E59: 13.44 | F59: 277.45 | G59: 270.83 | H59: 249.44 | I59: 306.04 | J59: 303.43 | K59: 284.54
A60: Other Liabilities | B60: 8888.04 | C60: 9439.67 | D60: 11694.85 | E60: 12584.73 | F60: 11760.04 | G60: 13142.59 | H60: 14491.01 | I60: 16369.66 | J60: 16943.54 | K60: 17688.11
A61: Total | B61: 51651.34 | C61: 55898.32 | D61: 64240.88 | E61: 71739.04 | F61: 77310.75 | G61: 73760.76 | H61: 77196.02 | I61: 85830.96 | J61: 91753.97 | K61: 88002.7
A62: Net Block | B62: 15106.63 | C62: 15893.48 | D62: 16523.96 | E62: 19374.19 | F62: 21713.34 | G62: 23298.48 | H62: 24231.59 | I62: 25851.27 | J62: 27820.22 | K62: 21954.85
A63: Capital Work in Progress | B63: 2559.72 | C63: 3729.89 | D63: 5508.33 | E63: 4136.42 | F63: 3256.46 | G63: 4011.29 | H63: 3225.54 | I63: 3003.3 | J63: 2860.78 | K63: 1090.91
A64: Investments | B64: 11747.59 | C64: 17581.38 | D64: 22052.86 | E64: 25043.49 | F64: 28663.35 | G64: 24870.87 | H64: 24841.01 | I64: 29415.02 | J64: 31114.02 | K64: 34719.82
A65: Other Assets | B65: 22237.4 | C65: 18693.57 | D65: 20155.73 | E65: 23184.94 | F65: 23677.6 | G65: 21580.12 | H65: 24897.88 | I65: 27561.37 | J65: 29958.95 | K65: 30237.12
A66: Total | B66: 51651.34 | C66: 55898.32 | D66: 64240.88 | E66: 71739.04 | F66: 77310.75 | G66: 73760.76 | H66: 77196.02 | I66: 85830.96 | J66: 91753.97 | K66: 88002.7
A67: Receivables | B67: 1917.18 | C67: 2474.29 | D67: 2682.29 | E67: 4035.28 | F67: 2562.48 | G67: 2501.7 | H67: 2461.9 | I67: 2956.17 | J67: 4025.82 | K67: 4719.67
... A70: No. of Equity Shares | B70: 8047206991 | C70: 12147383071 | D70: 12204294911 | E70: 12258631601 | F70: 12292231241 | G70: 12308844231 | H70: 12323255931 | I70: 12428017741 | J70: 12484700000 | K70: 12514119781
A71: New Bonus Shares | C71: 4026657100
A72: Face value | B72: 1 | C72: 1 | D72: 1 | E72: 1 | F72: 1 | G72: 1 | H72: 1 | I72: 1 | J72: 1 | K72: 1
A80: CASH FLOW:
A81: Report Date | B81: 42460 | C81: 42825 | D81: 43190 | E81: 43555 | F81: 43921 | G81: 44286 | H81: 44651 | I81: 45016 | J81: 45382 | K81: 45747
A82: Cash from Operating Activity | B82: 9799.04 | C82: 10627.31 | D82: 13169.4 | E82: 12583.41 | F82: 14689.66 | G82: 12526.97 | H82: 15775.51 | I82: 18877.55 | J82: 17178.86 | K82: 17627.04
A83: Cash from Investing Activity | B83: -3920.73 | C83: -3250.93 | D83: -7113.89 | E83: -5545.68 | F83: -6174.02 | G83: 5739.98 | H83: -2238.49 | I83: -5732.29 | J83: 1562.77 | K83: -563.84
A84: Cash from Financing Activity | B84: -5612.52 | C84: -7301.03 | D84: -6221.13 | E84: -6868.64 | F84: -8181.48 | G84: -18633.83 | H84: -13580.5 | I84: -13006.03 | J84: -18550.96 | K84: -17037.4
A85: Net Cash Flow | B85: 265.79 | C85: 75.35 | D85: -165.62 | E85: 169.09 | F85: 334.16 | G85: -366.88 | H85: -43.48 | I85: 139.23 | J85: 190.67 | K85: 25.8
A90: PRICE: | B90: 205.13 | C90: 262.75 | D90: 239.5 | E90: 278.64 | F90: 160.95 | G90: 204.82 | H90: 234.96 | I90: 359.49 | J90: 401.53 | K90: 409.75
A92: DERIVED:
A93: Adjusted Equity Shares in Cr | B93: 1207.08 | C93: 1214.74 | D93: 1220.43 | E93: 1225.86 | F93: 1229.22 | G93: 1230.88 | H93: 1232.33 | I93: 1242.8 | J93: 1248.47 | K93: 1251.41
